Workbook
Name 結餘: #REF!

Sheet 現金流量表 (手打、整合)
D2: 現在日期 | E2: =TODAY() -> 45957
D3: 年月 | E3: 估值 | F3: 結構 | G3: 45839 | H3: =EDATE(G3,1) -> 45870 | I3: =EDATE(H3,1) -> 45901 | J3: =EDATE(I3,1) -> 45931 | K3: =EDATE(J3,1) -> 45962 | L3: =EDATE(K3,1) -> 45992 | M3: =EDATE(L3,1) -> 46023 | N3: =EDATE(M3,1) -> 46054 | O3: =EDATE(N3,1) -> 46082 | ... AV3: =EDATE(AU3,1) -> 47088
D4: 持有資金 | F4: 0 | G4: =F4+G5 -> -425 | H4: =G4+H5 -> 3100 | I4: =H4+I5 -> 2725 | J4: =I4+J5 -> -10600 | K4: =J4+K5 -> -23925 | L4: =K4+L5 -> -46250 | M4: =L4+M5 -> -54620 | N4: =M4+N5 -> 37010 | ... AV4: =AU4+AV5 -> -417480
D5: 現金流 | G5: =G6-G27-G37 -> -425 | H5: =H6-H27-H37 -> 3525 | I5: =I6-I27-I37 -> -375 | J5: =J6-J27-J37 -> -13325 | K5: =K6-K27-K37 -> -13325 | L5: =L6-L27-L37 -> -22325 | M5: =M6-M27-M37 -> -8370 | N5: =N6-N27-N37 -> 91630 | ... AV5: =AV6-AV27-AV37 -> -13081
B6: 收入 | D6: 總計 | E6: {=AVERAGE(_xlfn._xlws.FILTER(G6:AV6, $G$3:$AV$3 <= $E$2))} -> #NAME? | G6: =SUM(G7+G14+G19) -> 86244 | H6: =SUM(H7+H14+H19) -> 90194 | I6: =SUM(I7+I14+I19) -> 92694 | J6: =SUM(J7+J14+J19) -> 79744 | K6: =SUM(K7+K14+K19) -> 79744 | L6: =SUM(L7+L14+L19) -> 79744 | M6: =SUM(M7+M14+M19) -> 79744 | N6: =SUM(N7+N14+N19) -> 179744 | ... AV6: =SUM(AV7+AV14+AV19) -> 60008
D7: 工資收入 | E7: {=AVERAGE(_xlfn._xlws.FILTER(G7:AV7, $G$3:$AV$3 <= $E$2))} -> #NAME? | F7: =E7/$E$6 -> #NAME? | G7: =SUM(G8:G13) -> 86244 | H7: =SUM(H8:H13) -> 90194 | I7: =SUM(I8:I13) -> 90194 | J7: =SUM(J8:J13) -> 79744 | K7: =SUM(K8:K13) -> 79744 | L7: =SUM(L8:L13) -> 79744 | M7: =SUM(M8:M13) -> 79744 | N7: =SUM(N8:N12) -> 179744 | O7: =SUM(O8:O13) -> 79744 | P7: =SUM(P8:P13) -> 0 | Q7: =SUM(Q8:Q13) -> 0 | R7: =SUM(R8:R13) -> 360000 | S7: =SUM(S8:S13) -> 60000 | T7: =SUM(T8:T13) -> 60000 | U7: =SUM(U8:U13) -> 60000 | V7: =SUM(V8:V13) -> 60000 | ... AV7: =SUM(AV8:AV13) -> 60008
D8: 薪資 | E8: {=AVERAGE(_xlfn._xlws.FILTER(G8:AV8, $G$3:$AV$3 <= $E$2))} -> #NAME? | G8: 71244 | H8: 71244 | I8: 71244 | J8: 66244 | K8: 66244 | L8: 66244 | M8: 66244 | N8: 66244 | O8: 66244 | P8: 0 | Q8: 0 | R8: 60000 | S8: 60000 | T8: 60000 | U8: 60000 | V8: 60000 | W8: 60000 | X8: 60000 | Y8: 60000 | Z8: 60000 | AA8: 60000 | AB8: 60000 | AC8: 60000 | AD8: 60000 | AE8: 60000 | AF8: 60000 | AG8: 60000 | AH8: 60000 | AI8: 60000 | AJ8: 60000 | AK8: 60000 | AL8: 60000 | AM8: 60000 | AN8: 60000 | AO8: 60001 | AP8: 60002 | AQ8: 60003 | AR8: 60004 | AS8: 60005 | AT8: 60006 | AU8: 60007 | AV8: 60008
D9: 加班費 | E9: {=AVERAGE(_xlfn._xlws.FILTER(G9:AV9, $G$3:$AV$3 <= $E$2))} -> #NAME? | G9: 0 | H9: 18950 | I9: 18950 | J9: 13500 | K9: 13500 | L9: 13500 | M9: 13500 | N9: 13500 | O9: 13500 | P9: 0 | Q9: 0 | R9: 0 | S9: 0 | T9: 0 | U9: 0 | V9: 0 | W9: 0 | X9: 0 | Y9: 0 | Z9: 0 | AA9: 0 | AB9: 0 | AC9: 0 | AD9: 0 | AE9: 0 | AF9: 0 | AG9: 0 | AH9: 0 | AI9: 0 | AJ9: 0 | AK9: 0 | AL9: 0 | AM9: 0 | AN9: 0 | AO9: 0 | AP9: 0 | AQ9: 0 | AR9: 0 | AS9: 0 | AT9: 0 | AU9: 0 | AV9: 0
D10: 佣金(考績獎金) | E10: {=AVERAGE(_xlfn._xlws.FILTER(G10:AV10, $G$3:$AV$3 <= $E$2))} -> #NAME? | G10: 0 | H10: 0 | I10: 0 | J10: 0 | K10: 0 | L10: 0 | M10: 0 | N10: 50000 | O10: 0 | P10: 0 | Q10: 0 | R10: 0 | S10: 0 | T10: 0 | U10: 0 | V10: 0 | W10: 0 | X10: 0 | Y10: 0 | Z10: 0 | AA10: 0 | AB10: 0 | AC10: 0 | AD10: 0 | AE10: 0 | AF10: 0 | AG10: 0 | AH10: 0 | AI10: 0 | AJ10: 0 | AK10: 0 | AL10: 0 | AM10: 0 | AN10: 0 | AO10: 0 | AP10: 0 | AQ10: 0 | AR10: 0 | AS10: 0 | AT10: 0 | AU10: 0 | AV10: 0
D11: 年終獎金 | E11: {=AVERAGE(_xlfn._xlws.FILTER(G11:AV11, $G$3:$AV$3 <= $E$2))} -> #NAME? | G11: 0 | H11: 0 | I11: 0 | J11: 0 | K11: 0 | L11: 0 | M11: 0 | N11: 50000 | O11: 0 | P11: 0 | Q11: 0 | R11: 0 | S11: 0 | T11: 0 | U11: 0 | V11: 0 | W11: 0 | X11: 0 | Y11: 0 | Z11: 0 | AA11: 0 | AB11: 0 | AC11: 0 | AD11: 0 | AE11: 0 | AF11: 0 | AG11: 0 | AH11: 0 | AI11: 0 | AJ11: 0 | AK11: 0 | AL11: 0 | AM11: 0 | AN11: 0 | AO11: 0 | AP11: 0 | AQ11: 0 | AR11: 0 | AS11: 0 | AT11: 0 | AU11: 0 | AV11: 0
D12: 兼職收入 | E12: {=AVERAGE(_xlfn._xlws.FILTER(G12:AV12, $G$3:$AV$3 <= $E$2))} -> #NAME? | G12: 15000 | H12: 0 | I12: 0 | J12: 0 | K12: 0 | L12: 0 | M12: 0 | N12: 0 | O12: 0 | P12: 0 | Q12: 0 | R12: 0 | S12: 0 | T12: 0 | U12: 0 | V12: 0 | W12: 0 | X12: 0 | Y12: 0 | Z12: 0 | AA12: 0 | AB12: 0 | AC12: 0 | AD12: 0 | AE12: 0 | AF12: 0 | AG12: 0 | AH12: 0 | AI12: 0 | AJ12: 0 | AK12: 0 | AL12: 0 | AM12: 0 | AN12: 0 | AO12: 0 | AP12: 0 | AQ12: 0 | AR12: 0 | AS12: 0 | AT12: 0 | AU12: 0 | AV12: 0
D13: 其他 | E13: {=AVERAGE(_xlfn._xlws.FILTER(G13:AV13, $G$3:$AV$3 <= $E$2))} -> #NAME? | G13: 0 | H13: 0 | I13: 0 | J13: 0 | K13: 0 | L13: 0 | M13: 0 | N13: 0 | O13: 0 | P13: 0 | Q13: 0 | R13: 300000 | S13: 0 | T13: 0 | U13: 0 | V13: 0 | W13: 0 | X13: 0 | Y13: 0 | Z13: 0 | AA13: 0 | AB13: 0 | AC13: 0 | AD13: 0 | AE13: 0 | AF13: 0 | AG13: 0 | AH13: 0 | AI13: 0 | AJ13: 0 | AK13: 0 | AL13: 0 | AM13: 0 | AN13: 0 | AO13: 0 | AP13: 0 | AQ13: 0 | AR13: 0 | AS13: 0 | AT13: 0 | AU13: 0 | AV13: 0
D14: 非工資收入 | E14: {=AVERAGE(_xlfn._xlws.FILTER(G14:AV14, $G$3:$AV$3 <= $E$2))} -> #NAME? | F14: =E14/$E$6 -> #NAME? | G14: =SUM(G15:G18) -> 0 | H14: =SUM(H15:H18) -> 0 | I14: =SUM(I15:I18) -> 2500 | J14: =SUM(J15:J18) -> 0 | K14: =SUM(K15:K18) -> 0 | L14: =SUM(L15:L18) -> 0 | M14: =SUM(M15:M18) -> 0 | N14: =SUM(N15:N18) -> 0 | ... AV14: =SUM(AV15:AV18) -> 0
D15: 營利所得 | E15: {=AVERAGE(_xlfn._xlws.FILTER(G15:AV15, $G$3:$AV$3 <= $E$2))} -> #NAME? | G15: 0 | H15: 0 | I15: 0 | J15: 0 | K15: 0 | L15: 0 | M15: 0 | N15: 0 | O15: 0 | P15: 0 | Q15: 0 | R15: 0 | S15: 0 | T15: 0 | U15: 0 | V15: 0 | W15: 0 | X15: 0 | Y15: 0 | Z15: 0 | AA15: 0 | AB15: 0 | AC15: 0 | AD15: 0 | AE15: 0 | AF15: 0 | AG15: 0 | AH15: 0 | AI15: 0 | AJ15: 0 | AK15: 0 | AL15: 0 | AM15: 0 | AN15: 0 | AO15: 0 | AP15: 0 | AQ15: 0 | AR15: 0 | AS15: 0 | AT15: 0 | AU15: 0 | AV15: 0
D16: 資本利得 | E16: {=AVERAGE(_xlfn._xlws.FILTER(G16:AV16, $G$3:$AV$3 <= $E$2))} -> #NAME? | G16: 0 | H16: 0 | I16: =I36*0.1 -> 2500 | J16: =J36*0.1 -> 0 | K16: =K36*0.1 -> 0 | L16: =L36*0.1 -> 0 | M16: =M36*0.1 -> 0 | N16: =N36*0.1 -> 0 | O16: =O36*0.1 -> 0 | P16: =P36*0.1 -> 0 | ... AV16: =AV36*0.1 -> 0
D17: 人情借款 | E17: {=AVERAGE(_xlfn._xlws.FILTER(G17:AV17, $G$3:$AV$3 <= $E$2))} -> #NAME? | G17: 0 | H17: 0 | I17: 0 | J17: 0 | K17: 0 | L17: 0 | M17: 0 | N17: 0 | O17: 0 | P17: 0 | Q17: 0 | R17: 0 | S17: 0 | T17: 0 | U17: 0 | V17: 0 | W17: 0 | X17: 0 | Y17: 0 | Z17: 0 | AA17: 0 | AB17: 0 | AC17: 0 | AD17: 0 | AE17: 0 | AF17: 0 | AG17: 0 | AH17: 0 | AI17: 0 | AJ17: 0 | AK17: 0 | AL17: 0 | AM17: 0 | AN17: 0 | AO17: 0 | AP17: 0 | AQ17: 0 | AR17: 0 | AS17: 0 | AT17: 0 | AU17: 0 | AV17: 0
D18: 其他 | E18: {=AVERAGE(_xlfn._xlws.FILTER(G18:AV18, $G$3:$AV$3 <= $E$2))} -> #NAME? | G18: 0 | H18: 0 | I18: 0 | J18: 0 | K18: 0 | L18: 0 | M18: 0 | N18: 0 | O18: 0 | P18: 0 | Q18: 0 | R18: 0 | S18: 0 | T18: 0 | U18: 0 | V18: 0 | W18: 0 | X18: 0 | Y18: 0 | Z18: 0 | AA18: 0 | AB18: 0 | AC18: 0 | AD18: 0 | AE18: 0 | AF18: 0 | AG18: 0 | AH18: 0 | AI18: 0 | AJ18: 0 | AK18: 0 | AL18: 0 | AM18: 0 | AN18: 0 | AO18: 0 | AP18: 0 | AQ18: 0 | AR18: 0 | AS18: 0 | AT18: 0 | AU18: 0 | AV18: 0
D19: 被動 | E19: {=AVERAGE(_xlfn._xlws.FILTER(G19:AV19, $G$3:$AV$3 <= $E$2))} -> #NAME? | F19: =E19/$E$6 -> #NAME? | G19: =SUM(G20:G26) -> 0 | H19: =SUM(H20:H26) -> 0 | I19: =SUM(I20:I26) -> 0 | J19: =SUM(J20:J26) -> 0 | K19: =SUM(K20:K26) -> 0 | L19: =SUM(L20:L26) -> 0 | M19: =SUM(M20:M26) -> 0 | N19: =SUM(N20:N26) -> 0 | ... AV19: =SUM(AV20:AV26) -> 0
D20: 退休金 | E20: {=AVERAGE(_xlfn._xlws.FILTER(G20:AV20, $G$3:$AV$3 <= $E$2))} -> #NAME? | G20: 0 | H20: 0 | I20: 0 | J20: 0 | K20: 0 | L20: 0 | M20: 0 | N20: 0 | O20: 0 | P20: 0 | Q20: 0 | R20: 0 | S20: 0 | T20: 0 | U20: 0 | V20: 0 | W20: 0 | X20: 0 | Y20: 0 | Z20: 0 | AA20: 0 | AB20: 0 | AC20: 0 | AD20: 0 | AE20: 0 | AF20: 0 | AG20: 0 | AH20: 0 | AI20: 0 | AJ20: 0 | AK20: 0 | AL20: 0 | AM20: 0 | AN20: 0 | AO20: 0 | AP20: 0 | AQ20: 0 | AR20: 0 | AS20: 0 | AT20: 0 | AU20: 0 | AV20: 0
D21: 保險滿期金 | E21: {=AVERAGE(_xlfn._xlws.FILTER(G21:AV21, $G$3:$AV$3 <= $E$2))} -> #NAME? | G21: 0 | H21: 0 | I21: 0 | J21: 0 | K21: 0 | L21: 0 | M21: 0 | N21: 0 | O21: 0 | P21: 0 | Q21: 0 | R21: 0 | S21: 0 | T21: 0 | U21: 0 | V21: 0 | W21: 0 | X21: 0 | Y21: 0 | Z21: 0 | AA21: 0 | AB21: 0 | AC21: 0 | AD21: 0 | AE21: 0 | AF21: 0 | AG21: 0 | AH21: 0 | AI21: 0 | AJ21: 0 | AK21: 0 | AL21: 0 | AM21: 0 | AN21: 0 | AO21: 0 | AP21: 0 | AQ21: 0 | AR21: 0 | AS21: 0 | AT21: 0 | AU21: 0 | AV21: 0
D22: 跟會到期 | E22: {=AVERAGE(_xlfn._xlws.FILTER(G22:AV22, $G$3:$AV$3 <= $E$2))} -> #NAME? | G22: 0 | H22: 0 | I22: 0 | J22: 0 | K22: 0 | L22: 0 | M22: 0 | N22: 0 | O22: 0 | P22: 0 | Q22: 0 | R22: 0 | S22: 0 | T22: 0 | U22: 0 | V22: 0 | W22: 0 | X22: 0 | Y22: 0 | Z22: 0 | AA22: 0 | AB22: 0 | AC22: 0 | AD22: 0 | AE22: 0 | AF22: 0 | AG22: 0 | AH22: 0 | AI22: 0 | AJ22: 0 | AK22: 0 | AL22: 0 | AM22: 0 | AN22: 0 | AO22: 0 | AP22: 0 | AQ22: 0 | AR22: 0 | AS22: 0 | AT22: 0 | AU22: 0 | AV22: 0
D23: 利息收入 | E23: {=AVERAGE(_xlfn._xlws.FILTER(G23:AV23, $G$3:$AV$3 <= $E$2))} -> #NAME? | G23: 0 | H23: 0 | I23: 0 | J23: 0 | K23: 0 | L23: 0 | M23: 0 | N23: 0 | O23: 0 | P23: 0 | Q23: 0 | R23: 0 | S23: 0 | T23: 0 | U23: 0 | V23: 0 | W23: 0 | X23: 0 | Y23: 0 | Z23: 0 | AA23: 0 | AB23: 0 | AC23: 0 | AD23: 0 | AE23: 0 | AF23: 0 | AG23: 0 | AH23: 0 | AI23: 0 | AJ23: 0 | AK23: 0 | AL23: 0 | AM23: 0 | AN23: 0 | AO23: 0 | AP23: 0 | AQ23: 0 | AR23: 0 | AS23: 0 | AT23: 0 | AU23: 0 | AV23: 0
D24: 租金收入 | E24: {=AVERAGE(_xlfn._xlws.FILTER(G24:AV24, $G$3:$AV$3 <= $E$2))} -> #NAME? | G24: 0 | H24: 0 | I24: 0 | J24: 0 | K24: 0 | L24: 0 | M24: 0 | N24: 0 | O24: 0 | P24: 0 | Q24: 0 | R24: 0 | S24: 0 | T24: 0 | U24: 0 | V24: 0 | W24: 0 | X24: 0 | Y24: 0 | Z24: 0 | AA24: 0 | AB24: 0 | AC24: 0 | AD24: 0 | AE24: 0 | AF24: 0 | AG24: 0 | AH24: 0 | AI24: 0 | AJ24: 0 | AK24: 0 | AL24: 0 | AM24: 0 | AN24: 0 | AO24: 0 | AP24: 0 | AQ24: 0 | AR24: 0 | AS24: 0 | AT24: 0 | AU24: 0 | AV24: 0
D25: 股利 | E25: {=AVERAGE(_xlfn._xlws.FILTER(G25:AV25, $G$3:$AV$3 <= $E$2))} -> #NAME? | G25: 0 | H25: 0 | I25: 0 | J25: 0 | K25: 0 | L25: 0 | M25: 0 | N25: 0 | O25: 0 | P25: 0 | Q25: 0 | R25: 0 | S25: 0 | T25: 0 | U25: 0 | V25: 0 | W25: 0 | X25: 0 | Y25: 0 | Z25: 0 | AA25: 0 | AB25: 0 | AC25: 0 | AD25: 0 | AE25: 0 | AF25: 0 | AG25: 0 | AH25: 0 | AI25: 0 | AJ25: 0 | AK25: 0 | AL25: 0 | AM25: 0 | AN25: 0 | AO25: 0 | AP25: 0 | AQ25: 0 | AR25: 0 | AS25: 0 | AT25: 0 | AU25: 0 | AV25: 0
D26: 其他 | E26: {=AVERAGE(_xlfn._xlws.FILTER(G26:AV26, $G$3:$AV$3 <= $E$2))} -> #NAME? | G26: 0 | H26: 0 | I26: 0 | J26: 0 | K26: 0 | L26: 0 | M26: 0 | N26: 0 | O26: 0 | P26: 0 | Q26: 0 | R26: 0 | S26: 0 | T26: 0 | U26: 0 | V26: 0 | W26: 0 | X26: 0 | Y26: 0 | Z26: 0 | AA26: 0 | AB26: 0 | AC26: 0 | AD26: 0 | AE26: 0 | AF26: 0 | AG26: 0 | AH26: 0 | AI26: 0 | AJ26: 0 | AK26: 0 | AL26: 0 | AM26: 0 | AN26: 0 | AO26: 0 | AP26: 0 | AQ26: 0 | AR26: 0 | AS26: 0 | AT26: 0 | AU26: 0 | AV26: 0
B27: 理財支出 | D27: 總計 | E27: {=AVERAGE(_xlfn._xlws.FILTER(G27:AV27, $G$3:$AV$3 <= $E$2))} -> #NAME? | G27: =SUM(G28+G31+G35) -> 0 | H27: =SUM(H28+H31+H35) -> 0 | I27: =SUM(I28+I31+I35) -> 0 | J27: =SUM(J28+J31+J35) -> 0 | K27: =SUM(K28+K31+K35) -> 0 | L27: =SUM(L28+L31+L35) -> 0 | M27: =SUM(M28+M31+M35) -> 0 | N27: =SUM(N28+N31+N35) -> 0 | ... S27: =SUM(S28+S31+S35) -> 0 | T27: 0 | U27: 0 | V27: 0 | W27: 0 | X27: 0 | Y27: 0 | Z27: 0 | AA27: 0 | AB27: 0 | AC27: 0 | AD27: 0 | AE27: 0 | AF27: 0 | AG27: 0 | AH27: 0 | AI27: 0 | AJ27: 0 | AK27: 0 | AL27: 0 | AM27: 0 | AN27: 0 | AO27: 0 | AP27: 0 | AQ27: 0 | AR27: 0 | AS27: 0 | AT27: 0 | AU27: 0 | AV27: 0
D28: 緊急預備金 | E28: {=AVERAGE(_xlfn._xlws.FILTER(G28:AV28, $G$3:$AV$3 <= $E$2))} -> #NAME? | G28: 0 | H28: 0 | I28: 0 | J28: 0 | K28: 0 | L28: 0 | M28: 0 | N28: 0 | O28: 0 | P28: 0 | Q28: 0 | R28: 0 | S28: 0 | T28: 0 | U28: 0 | V28: 0 | W28: 0 | X28: 0 | Y28: 0 | Z28: 0 | AA28: 0 | AB28: 0 | AC28: 0 | AD28: 0 | AE28: 0 | AF28: 0 | AG28: 0 | AH28: 0 | AI28: 0 | AJ28: 0 | AK28: 0 | AL28: 0 | AM28: 0 | AN28: 0 | AO28: 0 | AP28: 0 | AQ28: 0 | AR28: 0 | AS28: 0 | AT28: 0 | AU28: 0 | AV28: 0
D29: 夢想基金 | E29: {=AVERAGE(_xlfn._xlws.FILTER(G29:AV29, $G$3:$AV$3 <= $E$2))} -> #NAME? | G29: 0 | H29: 0 | I29: 0 | J29: 0 | K29: 0 | L29: 0 | M29: 0 | N29: 0 | O29: 0 | P29: 0 | Q29: 0 | R29: 0 | S29: 0 | T29: 0 | U29: 0 | V29: 0 | W29: 0 | X29: 0 | Y29: 0 | Z29: 0 | AA29: 0 | AB29: 0 | AC29: 0 | AD29: 0 | AE29: 0 | AF29: 0 | AG29: 0 | AH29: 0 | AI29: 0 | AJ29: 0 | AK29: 0 | AL29: 0 | AM29: 0 | AN29: 0 | AO29: 0 | AP29: 0 | AQ29: 0 | AR29: 0 | AS29: 0 | AT29: 0 | AU29: 0 | AV29: 0
D30: 退休基金 | E30: {=AVERAGE(_xlfn._xlws.FILTER(G30:AV30, $G$3:$AV$3 <= $E$2))} -> #NAME? | G30: 0 | H30: 0 | I30: 0 | J30: 0 | K30: 0 | L30: 0 | M30: 0 | N30: 0 | O30: 0 | P30: 0 | Q30: 0 | R30: 0 | S30: 0 | T30: 0 | U30: 0 | V30: 0 | W30: 0 | X30: 0 | Y30: 0 | Z30: 0 | AA30: 0 | AB30: 0 | AC30: 0 | AD30: 0 | AE30: 0 | AF30: 0 | AG30: 0 | AH30: 0 | AI30: 0 | AJ30: 0 | AK30: 0 | AL30: 0 | AM30: 0 | AN30: 0 | AO30: 0 | AP30: 0 | AQ30: 0 | AR30: 0 | AS30: 0 | AT30: 0 | AU30: 0 | AV30: 0
D31: 投資資金 | E31: {=AVERAGE(_xlfn._xlws.FILTER(G31:AV31, $G$3:$AV$3 <= $E$2))} -> #NAME? | G31: 0 | H31: 0 | I31: 0 | J31: 0 | K31: 0 | L31: 0 | M31: 0 | N31: 0 | O31: 0 | P31: 0 | Q31: 0 | R31: 0 | S31: 0 | T31: 0 | U31: 0 | V31: 0 | W31: 0 | X31: 0 | Y31: 0 | Z31: 0 | AA31: 0 | AB31: 0 | AC31: 0 | AD31: 0 | AE31: 0 | AF31: 0 | AG31: 0 | AH31: 0 | AI31: 0 | AJ31: 0 | AK31: =EDATE(AJ31,1) -> 31 | AL31: =EDATE(AK31,1) -> 59 | AM31: =EDATE(AL31,1) -> 88 | AN31: =EDATE(AM31,1) -> 119 | AO31: =EDATE(AN31,1) -> 149 | AP31: =EDATE(AO31,1) -> 180 | AQ31: =EDATE(AP31,1) -> 210 | AR31: =EDATE(AQ31,1) -> 241 | ... AV31: =EDATE(AU31,1) -> 363
D32: 教育基金 | E32: {=AVERAGE(_xlfn._xlws.FILTER(G32:AV32, $G$3:$AV$3 <= $E$2))} -> #NAME? | G32: 0 | H32: 0 | I32: 0 | J32: 0 | K32: 0 | L32: 0 | M32: 0 | N32: 0 | O32: 0 | P32: 0 | Q32: 0 | R32: 0 | S32: 0 | T32: 0 | U32: 0 | V32: 0 | W32: 0 | X32: 0 | Y32: 0 | Z32: 0 | AA32: 0 | AB32: 0 | AC32: 0 | AD32: 0 | AE32: 0 | AF32: 0 | AG32: 0 | AH32: 0 | AI32: 0 | AJ32: 0 | AK32: 0 | AL32: 0 | AM32: 0 | AN32: 0 | AO32: 0 | AP32: 0 | AQ32: 0 | AR32: 0 | AS32: 0 | AT32: 0 | AU32: 0 | AV32: 0
D33: 其他 | E33: {=AVERAGE(_xlfn._xlws.FILTER(G33:AV33, $G$3:$AV$3 <= $E$2))} -> #NAME? | G33: 0 | H33: 0 | I33: 0 | J33: 0 | K33: 0 | L33: 0 | M33: 0 | N33: 0 | O33: 0 | P33: 0 | Q33: 0 | R33: 0 | S33: 0 | T33: 0 | U33: 0 | V33: 0 | W33: 0 | X33: 0 | Y33: 0 | Z33: 0 | AA33: 0 | AB33: 0 | AC33: 0 | AD33: 0 | AE33: 0 | AF33: 0 | AG33: 0 | AH33: 0 | AI33: 0 | AJ33: 0 | AK33: 0 | AL33: 0 | AM33: 0 | AN33: 0 | AO33: 0 | AP33: 0 | AQ33: 0 | AR33: 0 | AS33: 0 | AT33: 0 | AU33: 0 | AV33: 0
E34: {=AVERAGE(_xlfn._xlws.FILTER(G34:AV34, $G$3:$AV$3 <= $E$2))} -> #NAME? | G34: 0 | H34: 0 | I34: 0 | J34: 0 | K34: 0 | L34: 0 | M34: 0 | N34: 0 | O34: 0 | P34: 0 | Q34: 0 | R34: 0 | S34: 0 | T34: 0 | U34: 0 | V34: 0 | W34: 0 | X34: 0 | Y34: 0 | Z34: 0 | AA34: 0 | AB34: 0 | AC34: 0 | AD34: 0 | AE34: 0 | AF34: 0 | AG34: 0 | AH34: 0 | AI34: 0 | AJ34: 0 | AK34: 0 | AL34: 0 | AM34: 0 | AN34: 0 | AO34: 0 | AP34: 0 | AQ34: 0 | AR34: 0 | AS34: 0 | AT34: 0 | AU34: 0 | AV34: 0
E35: {=AVERAGE(_xlfn._xlws.FILTER(G35:AV35, $G$3:$AV$3 <= $E$2))} -> #NAME? | G35: 0 | H35: 0 | I35: 0 | J35: 0 | K35: 0 | L35: 0 | M35: 0 | N35: 0 | O35: 0 | P35: 0 | Q35: 0 | R35: 0 | S35: 0 | T35: 0 | U35: 0 | V35: 0 | W35: 0 | X35: 0 | Y35: 0 | Z35: 0 | AA35: 0 | AB35: 0 | AC35: 0 | AD35: 0 | AE35: 0 | AF35: 0 | AG35: 0 | AH35: 0 | AI35: 0 | AJ35: 0 | AK35: 0 | AL35: 0 | AM35: 0 | AN35: 0 | AO35: 0 | AP35: 0 | AQ35: 0 | AR35: 0 | AS35: 0 | AT35: 0 | AU35: 0 | AV35: 0
E36: {=AVERAGE(_xlfn._xlws.FILTER(G36:AV36, $G$3:$AV$3 <= $E$2))} -> #NAME? | G36: 0 | H36: 0 | I36: 25000 | J36: 0 | K36: 0 | L36: 0 | M36: 0 | N36: 0 | O36: 0 | P36: 0 | Q36: 0 | R36: 0 | S36: 0 | T36: 0 | U36: 0 | V36: 0 | W36: 0 | X36: 0 | Y36: 0 | Z36: 0 | AA36: 0 | AB36: 0 | AC36: 0 | AD36: 0 | AE36: 0 | AF36: 0 | AG36: 0 | AH36: 0 | AI36: 0 | AJ36: 0 | AK36: 0 | AL36: 0 | AM36: 0 | AN36: 0 | AO36: 0 | AQ36: 0 | AR36: 0 | AT36: 0 | AU36: 0 | AV36: 0
D37: 總計 | E37: {=AVERAGE(_xlfn._xlws.FILTER(G37:AV37, $G$3:$AV$3 <= $E$2))} -> #NAME? | G37: =SUM(G38+G41+G45+G53+G60+G70+G81+G87+G93+G96+G99) -> 86669 | H37: =SUM(H38+H41+H45+H53+H60+H70+H81+H87+H93+H96+H99) -> 86669 | I37: =SUM(I38+I41+I45+I53+I60+I70+I81+I87+I93+I96+I99) -> 93069 | J37: =SUM(J38+J41+J45+J53+J60+J70+J81+J87+J93+J96+J99) -> 93069 | K37: =SUM(K38+K41+K45+K53+K60+K70+K81+K87+K93+K96+K99) -> 93069 | L37: =SUM(L38+L41+L45+L53+L60+L70+L81+L87+L93+L96+L99) -> 102069 | M37: =SUM(M38+M41+M45+M53+M60+M70+M81+M87+M93+M96+M99) -> 88114 | N37: =SUM(N38+N41+N45+N53+N60+N70+N81+N87+N93+N96+N99) -> 88114 | ... AV37: =SUM(AV38+AV41+AV45+AV53+AV60+AV70+AV81+AV87+AV93+AV96+AV99) -> 73089
B38: 支出 | C38: 必要支出 | D38: 食 | E38: {=AVERAGE(_xlfn._xlws.FILTER(G38:AV38, $G$3:$AV$3 <= $E$2))} -> #NAME? | G38: =SUM(G39:G40) -> 0 | H38: =SUM(H39:H40) -> 0 | I38: =SUM(I39:I40) -> 0 | J38: =SUM(J39:J40) -> 0 | K38: =SUM(K39:K40) -> 0 | L38: =SUM(L39:L40) -> 0 | M38: =SUM(M39:M40) -> 0 | N38: =SUM(N39:N40) -> 0 | ... AV38: =SUM(AV39:AV40) -> 0
D39: 外食 | E39: {=AVERAGE(_xlfn._xlws.FILTER(G39:AV39, $G$3:$AV$3 <= $E$2))} -> #NAME? | G39: 0 | H39: 0 | I39: 0 | J39: 0 | K39: 0 | L39: 0 | M39: 0 | N39: 0 | O39: 0 | P39: 0 | Q39: 0 | R39: 0 | S39: 0 | T39: 0 | U39: 0 | V39: 0 | W39: 0 | X39: 0 | Y39: 0 | Z39: 0 | AA39: 0 | AB39: 0 | AC39: 0 | AD39: 0 | AE39: 0 | AF39: 0 | AG39: 0 | AH39: 0 | AI39: 0 | AJ39: 0 | AK39: 0 | AL39: 0 | AM39: 0 | AN39: 0 | AO39: 0 | AP39: 0 | AQ39: 0 | AR39: 0 | AS39: 0 | AT39: 0 | AU39: 0 | AV39: 0
D40: 食材 | E40: {=AVERAGE(_xlfn._xlws.FILTER(G40:AV40, $G$3:$AV$3 <= $E$2))} -> #NAME? | G40: 0 | H40: 0 | I40: 0 | J40: 0 | K40: 0 | L40: 0 | M40: 0 | N40: 0 | O40: 0 | P40: 0 | Q40: 0 | R40: 0 | S40: 0 | T40: 0 | U40: 0 | V40: 0 | W40: 0 | X40: 0 | Y40: 0 | Z40: 0 | AA40: 0 | AB40: 0 | AC40: 0 | AD40: 0 | AE40: 0 | AF40: 0 | AG40: 0 | AH40: 0 | AI40: 0 | AJ40: 0 | AK40: 0 | AL40: 0 | AM40: 0 | AN40: 0 | AO40: 0 | AP40: 0 | AQ40: 0 | AR40: 0 | AS40: 0 | AT40: 0 | AU40: 0 | AV40: 0
D41: 衣 | E41: {=AVERAGE(_xlfn._xlws.FILTER(G41:AV41, $G$3:$AV$3 <= $E$2))} -> #NAME? | G41: 0 | H41: 0 | I41: =SUM(I42:I44) -> 0 | J41: =SUM(J42:J44) -> 0 | K41: =SUM(K42:K44) -> 0 | L41: =SUM(L42:L44) -> 0 | M41: =SUM(M42:M44) -> 0 | N41: =SUM(N42:N44) -> 0 | O41: =SUM(O42:O44) -> 0 | P41: =SUM(P42:P44) -> 0 | ... AV41: =SUM(AV42:AV44) -> 0
D42: 治裝 | E42: {=AVERAGE(_xlfn._xlws.FILTER(G42:AV42, $G$3:$AV$3 <= $E$2))} -> #NAME? | G42: 0 | H42: 0 | I42: 0 | J42: 0 | K42: 0 | L42: 0 | M42: 0 | N42: 0 | O42: 0 | P42: 0 | Q42: 0 | R42: 0 | S42: 0 | T42: 0 | U42: 0 | V42: 0 | W42: 0 | X42: 0 | Y42: 0 | Z42: 0 | AA42: 0 | AB42: 0 | AC42: 0 | AD42: 0 | AE42: 0 | AF42: 0 | AG42: 0 | AH42: 0 | AI42: 0 | AJ42: 0 | AK42: 0 | AL42: 0 | AM42: 0 | AN42: 0 | AO42: 0 | AP42: 0 | AQ42: 0 | AR42: 0 | AS42: 0 | AT42: 0 | AU42: 0 | AV42: 0
D43: 美容美髮 | E43: {=AVERAGE(_xlfn._xlws.FILTER(G43:AV43, $G$3:$AV$3 <= $E$2))} -> #NAME? | G43: 0 | H43: 0 | I43: 0 | J43: 0 | K43: 0 | L43: 0 | M43: 0 | N43: 0 | O43: 0 | P43: 0 | Q43: 0 | R43: 0 | S43: 0 | T43: 0 | U43: 0 | V43: 0 | W43: 0 | X43: 0 | Y43: 0 | Z43: 0 | AA43: 0 | AB43: 0 | AC43: 0 | AD43: 0 | AE43: 0 | AF43: 0 | AG43: 0 | AH43: 0 | AI43: 0 | AJ43: 0 | AK43: 0 | AL43: 0 | AM43: 0 | AN43: 0 | AO43: 0 | AP43: 0 | AQ43: 0 | AR43: 0 | AS43: 0 | AT43: 0 | AU43: 0 | AV43: 0
D44: 衣物送洗 | E44: {=AVERAGE(_xlfn._xlws.FILTER(G44:AV44, $G$3:$AV$3 <= $E$2))} -> #NAME? | G44: 0 | H44: 0 | I44: 0 | J44: 0 | K44: 0 | L44: 0 | M44: 0 | N44: 0 | O44: 0 | P44: 0 | Q44: 0 | R44: 0 | S44: 0 | T44: 0 | U44: 0 | V44: 0 | W44: 0 | X44: 0 | Y44: 0 | Z44: 0 | AA44: 0 | AB44: 0 | AC44: 0 | AD44: 0 | AE44: 0 | AF44: 0 | AG44: 0 | AH44: 0 | AI44: 0 | AJ44: 0 | AK44: 0 | AL44: 0 | AM44: 0 | AN44: 0 | AO44: 0 | AP44: 0 | AQ44: 0 | AR44: 0 | AS44: 0 | AT44: 0 | AU44: 0 | AV44: 0
D45: 住 | E45: {=AVERAGE(_xlfn._xlws.FILTER(G45:AV45, $G$3:$AV$3 <= $E$2))} -> #NAME? | G45: 0 | H45: 0 | I45: =SUM(I46:I52) -> 1400 | J45: =SUM(J46:J52) -> 1400 | K45: =SUM(K46:K52) -> 1400 | L45: =SUM(L46:L52) -> 10400 | M45: =SUM(M46:M52) -> 10400 | N45: =SUM(N46:N52) -> 10400 | O45: =SUM(O46:O52) -> 10400 | P45: =SUM(P46:P52) -> 10400 | ... AV45: =SUM(AV46:AV52) -> 10408
D46: 抵押貸款/租金 | E46: {=AVERAGE(_xlfn._xlws.FILTER(G46:AV46, $G$3:$AV$3 <= $E$2))} -> #NAME? | G46: 0 | H46: 0 | I46: 0 | J46: 0 | K46: 0 | L46: 9000 | M46: 9000 | N46: 9000 | O46: 9000 | P46: 9000 | Q46: 9000 | R46: 9000 | S46: 9000 | T46: 9000 | U46: 9000 | V46: 9000 | W46: 9000 | X46: 9000 | Y46: 9000 | Z46: 9000 | AA46: 9000 | AB46: 9000 | AC46: 9000 | AD46: 9000 | AE46: 9000 | AF46: 9000 | AG46: 9000 | AH46: 9000 | AI46: 9000 | AJ46: 9000 | AK46: 9000 | AL46: 9000 | AM46: 9000 | AN46: 9000 | AO46: 9000 | AP46: 9000 | AQ46: 9000 | AR46: 9000 | AS46: 9000 | AT46: 9000 | AU46: 9000 | AV46: 9000
D47: 電 | E47: {=AVERAGE(_xlfn._xlws.FILTER(G47:AV47, $G$3:$AV$3 <= $E$2))} -> #NAME? | G47: 0 | H47: 0 | I47: 0 | J47: 0 | K47: 0 | L47: 0 | M47: 0 | N47: 0 | O47: 0 | P47: 0 | Q47: 0 | R47: 0 | S47: 0 | T47: 0 | U47: 0 | V47: 0 | W47: 0 | X47: 0 | Y47: 0 | Z47: 0 | AA47: 0 | AB47: 0 | AC47: 0 | AD47: 0 | AE47: 0 | AF47: 0 | AG47: 0 | AH47: 0 | AI47: 0 | AJ47: 0 | AK47: 0 | AL47: 0 | AM47: 0 | AN47: 0 | AO47: 0 | AP47: 0 | AQ47: 0 | AR47: 0 | AS47: 0 | AT47: 0 | AU47: 0 | AV47: 0
D48: 天然氣/瓦斯 | E48: {=AVERAGE(_xlfn._xlws.FILTER(G48:AV48, $G$3:$AV$3 <= $E$2))} -> #NAME? | G48: 0 | H48: 0 | I48: 0 | J48: 0 | K48: 0 | L48: 0 | M48: 0 | N48: 0 | O48: 0 | P48: 0 | Q48: 0 | R48: 0 | S48: 0 | T48: 0 | U48: 0 | V48: 0 | W48: 0 | X48: 0 | Y48: 0 | Z48: 0 | AA48: 0 | AB48: 0 | AC48: 0 | AD48: 0 | AE48: 0 | AF48: 0 | AG48: 0 | AH48: 0 | AI48: 0 | AJ48: 0 | AK48: 0 | AL48: 0 | AM48: 0 | AN48: 0 | AO48: 0 | AP48: 0 | AQ48: 0 | AR48: 0 | AS48: 0 | AT48: 0 | AU48: 0 | AV48: 0
D49: 水 | E49: {=AVERAGE(_xlfn._xlws.FILTER(G49:AV49, $G$3:$AV$3 <= $E$2))} -> #NAME? | G49: 0 | H49: 0 | I49: 0 | J49: 0 | K49: 0 | L49: 0 | M49: 0 | N49: 0 | O49: 0 | P49: 0 | Q49: 0 | R49: 0 | S49: 0 | T49: 0 | U49: 0 | V49: 0 | W49: 0 | X49: 0 | Y49: 0 | Z49: 0 | AA49: 0 | AB49: 0 | AC49: 0 | AD49: 0 | AE49: 0 | AF49: 0 | AG49: 0 | AH49: 0 | AI49: 0 | AJ49: 0 | AK49: 0 | AL49: 0 | AM49: 0 | AN49: 0 | AO49: 0 | AP49: 0 | AQ49: 0 | AR49: 0 | AS49: 0 | AT49: 0 | AU49: 0 | AV49: 0
D50: 有線/衛星/網路 | E50: {=AVERAGE(_xlfn._xlws.FILTER(G50:AV50, $G$3:$AV$3 <= $E$2))} -> #NAME? | G50: 0 | H50: 0 | I50: 1400 | J50: 1400 | K50: 1400 | L50: 1400 | M50: 1400 | N50: 1400 | O50: 1400 | P50: 1400 | Q50: 1400 | R50: 1400 | S50: 1400 | T50: 1400 | U50: 1400 | V50: 1400 | W50: 1400 | X50: 1400 | Y50: 1400 | Z50: 1400 | AA50: 1400 | AB50: 1400 | AC50: 1400 | AD50: 1400 | AE50: 1400 | AF50: 1400 | AG50: 1400 | AH50: 1400 | AI50: 1400 | AJ50: 1400 | AK50: 1400 | AL50: 1400 | AM50: 1400 | AN50: 1400 | AO50: 1401 | AP50: 1402 | AQ50: 1403 | AR50: 1404 | AS50: 1405 | AT50: 1406 | AU50: 1407 | AV50: 1408
D51: 家具/家電 | E51: {=AVERAGE(_xlfn._xlws.FILTER(G51:AV51, $G$3:$AV$3 <= $E$2))} -> #NAME? | G51: 0 | H51: 0 | I51: 0 | J51: 0 | K51: 0 | L51: 0 | M51: 0 | N51: 0 | O51: 0 | P51: 0 | Q51: 0 | R51: 0 | S51: 0 | T51: 0 | U51: 0 | V51: 0 | W51: 0 | X51: 0 | Y51: 0 | Z51: 0 | AA51: 0 | AB51: 0 | AC51: 0 | AD51: 0 | AE51: 0 | AF51: 0 | AG51: 0 | AH51: 0 | AI51: 0 | AJ51: 0 | AK51: 0 | AL51: 0 | AM51: 0 | AN51: 0 | AO51: 0 | AP51: 0 | AQ51: 0 | AR51: 0 | AS51: 0 | AT51: 0 | AU51: 0 | AV51: 0
D52: 家居用品 | E52: {=AVERAGE(_xlfn._xlws.FILTER(G52:AV52, $G$3:$AV$3 <= $E$2))} -> #NAME? | G52: 0 | H52: 0 | I52: 0 | J52: 0 | K52: 0 | L52: 0 | M52: 0 | N52: 0 | O52: 0 | P52: 0 | Q52: 0 | R52: 0 | S52: 0 | T52: 0 | U52: 0 | V52: 0 | W52: 0 | X52: 0 | Y52: 0 | Z52: 0 | AA52: 0 | AB52: 0 | AC52: 0 | AD52: 0 | AE52: 0 | AF52: 0 | AG52: 0 | AH52: 0 | AI52: 0 | AJ52: 0 | AK52: 0 | AL52: 0 | AM52: 0 | AN52: 0 | AO52: 0 | AP52: 0 | AQ52: 0 | AR52: 0 | AS52: 0 | AT52: 0 | AU52: 0 | AV52: 0
D53: 行 | E53: {=AVERAGE(_xlfn._xlws.FILTER(G53:AV53, $G$3:$AV$3 <= $E$2))} -> #NAME? | G53: 0 | H53: 0 | I53: =SUM(I54:I59) -> 0 | J53: 0 | K53: 0 | L53: 0 | M53: 0 | N53: 0 | O53: 0 | P53: 0 | Q53: 0 | R53: 0 | S53: 0 | T53: 0 | U53: 0 | V53: 0 | W53: 0 | X53: 0 | Y53: 0 | Z53: 0 | AA53: 0 | AB53: 0 | AC53: 0 | AD53: 0 | AE53: 0 | AF53: 0 | AG53: 0 | AH53: 0 | AI53: 0 | AJ53: 0 | AK53: 0 | AL53: 0 | AM53: 0 | AN53: 0 | AO53: 0 | AP53: 0 | AQ53: 0 | AR53: 0 | AS53: 0 | AT53: 0 | AU53: 0 | AV53: 0
D54: 停車費 | E54: {=AVERAGE(_xlfn._xlws.FILTER(G54:AV54, $G$3:$AV$3 <= $E$2))} -> #NAME? | G54: 0 | H54: 0 | I54: 0 | J54: 0 | K54: 0 | L54: 0 | M54: 0 | N54: 0 | O54: 0 | P54: 0 | Q54: 0 | R54: 0 | S54: 0 | T54: 0 | U54: 0 | V54: 0 | W54: 0 | X54: 0 | Y54: 0 | Z54: 0 | AA54: 0 | AB54: 0 | AC54: 0 | AD54: 0 | AE54: 0 | AF54: 0 | AG54: 0 | AH54: 0 | AI54: 0 | AJ54: 0 | AK54: 0 | AL54: 0 | AM54: 0 | AN54: 0 | AO54: 0 | AP54: 0 | AQ54: 0 | AR54: 0 | AS54: 0 | AT54: 0 | AU54: 0 | AV54: 0
D55: 加油費 | E55: {=AVERAGE(_xlfn._xlws.FILTER(G55:AV55, $G$3:$AV$3 <= $E$2))} -> #NAME? | G55: 0 | H55: 0 | I55: 0 | J55: 0 | K55: 0 | L55: 0 | M55: 0 | N55: 0 | O55: 0 | P55: 0 | Q55: 0 | R55: 0 | S55: 0 | T55: 0 | U55: 0 | V55: 0 | W55: 0 | X55: 0 | Y55: 0 | Z55: 0 | AA55: 0 | AB55: 0 | AC55: 0 | AD55: 0 | AE55: 0 | AF55: 0 | AG55: 0 | AH55: 0 | AI55: 0 | AJ55: 0 | AK55: 0 | AL55: 0 | AM55: 0 | AN55: 0 | AO55: 0 | AP55: 0 | AQ55: 0 | AR55: 0 | AS55: 0 | AT55: 0 | AU55: 0 | AV55: 0
D56: 過路費 | E56: {=AVERAGE(_xlfn._xlws.FILTER(G56:AV56, $G$3:$AV$3 <= $E$2))} -> #NAME? | G56: 0 | H56: 0 | I56: 0 | J56: 0 | K56: 0 | L56: 0 | M56: 0 | N56: 0 | O56: 0 | P56: 0 | Q56: 0 | R56: 0 | S56: 0 | T56: 0 | U56: 0 | V56: 0 | W56: 0 | X56: 0 | Y56: 0 | Z56: 0 | AA56: 0 | AB56: 0 | AC56: 0 | AD56: 0 | AE56: 0 | AF56: 0 | AG56: 0 | AH56: 0 | AI56: 0 | AJ56: 0 | AK56: 0 | AL56: 0 | AM56: 0 | AN56: 0 | AO56: 0 | AP56: 0 | AQ56: 0 | AR56: 0 | AS56: 0 | AT56: 0 | AU56: 0 | AV56: 0
D57: 保養 | E57: {=AVERAGE(_xlfn._xlws.FILTER(G57:AV57, $G$3:$AV$3 <= $E$2))} -> #NAME? | G57: 0 | H57: 0 | I57: 0 | J57: 0 | K57: 0 | L57: 0 | M57: 0 | N57: 0 | O57: 0 | P57: 0 | Q57: 0 | R57: 0 | S57: 0 | T57: 0 | U57: 0 | V57: 0 | W57: 0 | X57: 0 | Y57: 0 | Z57: 0 | AA57: 0 | AB57: 0 | AC57: 0 | AD57: 0 | AE57: 0 | AF57: 0 | AG57: 0 | AH57: 0 | AI57: 0 | AJ57: 0 | AK57: 0 | AL57: 0 | AM57: 0 | AN57: 0 | AO57: 0 | AP57: 0 | AQ57: 0 | AR57: 0 | AS57: 0 | AT57: 0 | AU57: 0 | AV57: 0
D58: 大眾交通 | E58: {=AVERAGE(_xlfn._xlws.FILTER(G58:AV58, $G$3:$AV$3 <= $E$2))} -> #NAME? | G58: 0 | H58: 0 | I58: 0 | J58: 0 | K58: 0 | L58: 0 | M58: 0 | N58: 0 | O58: 0 | P58: 0 | Q58: 0 | R58: 0 | S58: 0 | T58: 0 | U58: 0 | V58: 0 | W58: 0 | X58: 0 | Y58: 0 | Z58: 0 | AA58: 0 | AB58: 0 | AC58: 0 | AD58: 0 | AE58: 0 | AF58: 0 | AG58: 0 | AH58: 0 | AI58: 0 | AJ58: 0 | AK58: 0 | AL58: 0 | AM58: 0 | AN58: 0 | AO58: 0 | AP58: 0 | AQ58: 0 | AR58: 0 | AS58: 0 | AT58: 0 | AU58: 0 | AV58: 0
D59: 其他 | E59: {=AVERAGE(_xlfn._xlws.FILTER(G59:AV59, $G$3:$AV$3 <= $E$2))} -> #NAME? | G59: 0 | H59: 0 | I59: 0 | J59: 0 | K59: 0 | L59: 0 | M59: 0 | N59: 0 | O59: 0 | P59: 0 | Q59: 0 | R59: 0 | S59: 0 | T59: 0 | U59: 0 | V59: 0 | W59: 0 | X59: 0 | Y59: 0 | Z59: 0 | AA59: 0 | AB59: 0 | AC59: 0 | AD59: 0 | AE59: 0 | AF59: 0 | AG59: 0 | AH59: 0 | AI59: 0 | AJ59: 0 | AK59: 0 | AL59: 0 | AM59: 0 | AN59: 0 | AO59: 0 | AP59: 0 | AQ59: 0 | AR59: 0 | AS59: 0 | AT59: 0 | AU59: 0 | AV59: 0
D60: 稅 | E60: {=AVERAGE(_xlfn._xlws.FILTER(G60:AV60, $G$3:$AV$3 <= $E$2))} -> #NAME? | G60: 0 | H60: 0 | I60: =SUM(I61:I62) -> 0 | J60: 0 | K60: 0 | L60: 0 | M60: 0 | N60: 0 | O60: 0 | P60: 0 | Q60: 0 | R60: 0 | S60: 0 | T60: 0 | U60: 0 | V60: 0 | W60: 0 | X60: 0 | Y60: 0 | Z60: 0 | AA60: 0 | AB60: 0 | AC60: 0 | AD60: 0 | AE60: 0 | AF60: 0 | AG60: 0 | AH60: 0 | AI60: 0 | AJ60: 0 | AK60: 0 | AL60: 0 | AM60: 0 | AN60: 0 | AO60: 0 | AP60: 0 | AQ60: 0 | AR60: 0 | AS60: 0 | AT60: 0 | AU60: 0 | AV60: 0
D61: 所得稅 | E61: {=AVERAGE(_xlfn._xlws.FILTER(G61:AV61, $G$3:$AV$3 <= $E$2))} -> #NAME? | G61: 0 | H61: 0 | I61: 0 | J61: 0 | K61: 0 | L61: 0 | M61: 0 | N61: 0 | O61: 0 | P61: 0 | Q61: 0 | R61: 0 | S61: 0 | T61: 0 | U61: 0 | V61: 0 | W61: 0 | X61: 0 | Y61: 0 | Z61: 0 | AA61: 0 | AB61: 0 | AC61: 0 | AD61: 0 | AE61: 0 | AF61: 0 | AG61: 0 | AH61: 0 | AI61: 0 | AJ61: 0 | AK61: 0 | AL61: 0 | AM61: 0 | AN61: 0 | AO61: 0 | AP61: 0 | AQ61: 0 | AR61: 0 | AS61: 0 | AT61: 0 | AU61: 0 | AV61: 0
D62: 牌照稅 | E62: {=AVERAGE(_xlfn._xlws.FILTER(G62:AV62, $G$3:$AV$3 <= $E$2))} -> #NAME? | G62: 0 | H62: 0 | I62: 0 | J62: 0 | K62: 0 | L62: 0 | M62: 0 | N62: 0 | O62: 0 | P62: 0 | Q62: 0 | R62: 0 | S62: 0 | T62: 0 | U62: 0 | V62: 0 | W62: 0 | X62: 0 | Y62: 0 | Z62: 0 | AA62: 0 | AB62: 0 | AC62: 0 | AD62: 0 | AE62: 0 | AF62: 0 | AG62: 0 | AH62: 0 | AI62: 0 | AJ62: 0 | AK62: 0 | AL62: 0 | AM62: 0 | AN62: 0 | AO62: 0 | AP62: 0 | AQ62: 0 | AR62: 0 | AS62: 0 | AT62: 0 | AU62: 0 | AV62: 0
D63: 燃料稅 | E63: {=AVERAGE(_xlfn._xlws.FILTER(G63:AV63, $G$3:$AV$3 <= $E$2))} -> #NAME? | G63: 0 | H63: 0 | I63: 0 | J63: 0 | K63: 0 | L63: 0 | M63: 0 | N63: 0 | O63: 0 | P63: 0 | Q63: 0 | R63: 0 | S63: 0 | T63: 0 | U63: 0 | V63: 0 | W63: 0 | X63: 0 | Y63: 0 | Z63: 0 | AA63: 0 | AB63: 0 | AC63: 0 | AD63: 0 | AE63: 0 | AF63: 0 | AG63: 0 | AH63: 0 | AI63: 0 | AJ63: 0 | AK63: 0 | AL63: 0 | AM63: 0 | AN63: 0 | AO63: 0 | AP63: 0 | AQ63: 0 | AR63: 0 | AS63: 0 | AT63: 0 | AU63: 0 | AV63: 0
D64: 勞健保 | E64: {=AVERAGE(_xlfn._xlws.FILTER(G64:AV64, $G$3:$AV$3 <= $E$2))} -> #NAME? | G64: 0 | H64: 0 | I64: 0 | J64: 0 | K64: 0 | L64: 0 | M64: 0 | N64: 0 | O64: 0 | P64: 0 | Q64: 0 | R64: 0 | S64: 0 | T64: 0 | U64: 0 | V64: 0 | W64: 0 | X64: 0 | Y64: 0 | Z64: 0 | AA64: 0 | AB64: 0 | AC64: 0 | AD64: 0 | AE64: 0 | AF64: 0 | AG64: 0 | AH64: 0 | AI64: 0 | AJ64: 0 | AK64: 0 | AL64: 0 | AM64: 0 | AN64: 0 | AO64: 0 | AP64: 0 | AQ64: 0 | AR64: 0 | AS64: 0 | AT64: 0 | AU64: 0 | AV64: 0
D65: 保險 | E65: {=AVERAGE(_xlfn._xlws.FILTER(G65:AV65, $G$3:$AV$3 <= $E$2))} -> #NAME? | G65: 0 | H65: 0 | I65: =SUM(I66:I67) -> 0 | J65: 0 | K65: 0 | L65: 0 | M65: 0 | N65: 0 | O65: 0 | P65: 0 | Q65: 0 | R65: 0 | S65: 0 | T65: 0 | U65: 0 | V65: 0 | W65: 0 | X65: 0 | Y65: 0 | Z65: 0 | AA65: 0 | AB65: 0 | AC65: 0 | AD65: 0 | AE65: 0 | AF65: 0 | AG65: 0 | AH65: 0 | AI65: 0 | AJ65: 0 | AK65: 0 | AL65: 0 | AM65: 0 | AN65: 0 | AO65: 0 | AP65: 0 | AQ65: 0 | AR65: 0 | AS65: 0 | AT65: 0 | AU65: 0 | AV65: 0
D66: 車輛 | E66: {=AVERAGE(_xlfn._xlws.FILTER(G66:AV66, $G$3:$AV$3 <= $E$2))} -> #NAME? | G66: 0 | H66: 0 | I66: 0 | J66: 0 | K66: 0 | L66: 0 | M66: 0 | N66: 0 | O66: 0 | P66: 0 | Q66: 0 | R66: 0 | S66: 0 | T66: 0 | U66: 0 | V66: 0 | W66: 0 | X66: 0 | Y66: 0 | Z66: 0 | AA66: 0 | AB66: 0 | AC66: 0 | AD66: 0 | AE66: 0 | AF66: 0 | AG66: 0 | AH66: 0 | AI66: 0 | AJ66: 0 | AK66: 0 | AL66: 0 | AM66: 0 | AN66: 0 | AO66: 0 | AP66: 0 | AQ66: 0 | AR66: 0 | AS66: 0 | AT66: 0 | AU66: 0 | AV66: 0
D67: 健康 | E67: {=AVERAGE(_xlfn._xlws.FILTER(G67:AV67, $G$3:$AV$3 <= $E$2))} -> #NAME? | G67: 0 | H67: 0 | I67: 0 | J67: 0 | K67: 0 | L67: 0 | M67: 0 | N67: 0 | O67: 0 | P67: 0 | Q67: 0 | R67: 0 | S67: 0 | T67: 0 | U67: 0 | V67: 0 | W67: 0 | X67: 0 | Y67: 0 | Z67: 0 | AA67: 0 | AB67: 0 | AC67: 0 | AD67: 0 | AE67: 0 | AF67: 0 | AG67: 0 | AH67: 0 | AI67: 0 | AJ67: 0 | AK67: 0 | AL67: 0 | AM67: 0 | AN67: 0 | AO67: 0 | AP67: 0 | AQ67: 0 | AR67: 0 | AS67: 0 | AT67: 0 | AU67: 0 | AV67: 0
D68: 住家/租賃 | E68: {=AVERAGE(_xlfn._xlws.FILTER(G68:AV68, $G$3:$AV$3 <= $E$2))} -> #NAME? | G68: 0 | H68: 0 | I68: 0 | J68: 0 | K68: 0 | L68: 0 | M68: 0 | N68: 0 | O68: 0 | P68: 0 | Q68: 0 | R68: 0 | S68: 0 | T68: 0 | U68: 0 | V68: 0 | W68: 0 | X68: 0 | Y68: 0 | Z68: 0 | AA68: 0 | AB68: 0 | AC68: 0 | AD68: 0 | AE68: 0 | AF68: 0 | AG68: 0 | AH68: 0 | AI68: 0 | AJ68: 0 | AK68: 0 | AL68: 0 | AM68: 0 | AN68: 0 | AO68: 0 | AP68: 0 | AQ68: 0 | AR68: 0 | AS68: 0 | AT68: 0 | AU68: 0 | AV68: 0
D69: 其他 | E69: {=AVERAGE(_xlfn._xlws.FILTER(G69:AV69, $G$3:$AV$3 <= $E$2))} -> #NAME? | G69: 0 | H69: 0 | I69: 0 | J69: 0 | K69: 0 | L69: 0 | M69: 0 | N69: 0 | O69: 0 | P69: 0 | Q69: 0 | R69: 0 | S69: 0 | T69: 0 | U69: 0 | V69: 0 | W69: 0 | X69: 0 | Y69: 0 | Z69: 0 | AA69: 0 | AB69: 0 | AC69: 0 | AD69: 0 | AE69: 0 | AF69: 0 | AG69: 0 | AH69: 0 | AI69: 0 | AJ69: 0 | AK69: 0 | AL69: 0 | AM69: 0 | AN69: 0 | AO69: 0 | AP69: 0 | AQ69: 0 | AR69: 0 | AS69: 0 | AT69: 0 | AU69: 0 | AV69: 0
C70: 需要 | D70: 貸款 | E70: {=AVERAGE(_xlfn._xlws.FILTER(G70:AV70, $G$3:$AV$3 <= $E$2))} -> #NAME? | G70: =SUM(G71:G80) -> 86669 | H70: =SUM(H71:H80) -> 86669 | I70: =SUM(I71:I80) -> 86669 | J70: =SUM(J71:J80) -> 86669 | K70: =SUM(K71:K80) -> 86669 | L70: =SUM(L71:L80) -> 86669 | M70: =SUM(M71:M80) -> 72714 | N70: =SUM(N71:N80) -> 72714 | ... AV70: =SUM(AV71:AV80) -> 57670
D71: 聯邦信用卡(16.07%) | E71: {=AVERAGE(_xlfn._xlws.FILTER(G71:AV71, $G$3:$AV$3 <= $E$2))} -> #NAME? | G71: 6000 | H71: 6000 | I71: 6000 | J71: 6000 | K71: 6000 | L71: 6000 | M71: 0 | N71: 0 | O71: 0 | P71: 0 | Q71: 0 | R71: 0 | S71: 0 | T71: 0 | U71: 0 | V71: 0 | W71: 0 | X71: 0 | Y71: 0 | Z71: 0 | AA71: 0 | AB71: 0 | AC71: 0 | AD71: 0 | AE71: 0 | AF71: 0 | AG71: 0 | AH71: 0 | AI71: 0 | AJ71: 0 | AK71: 0 | AL71: 0 | AM71: 0 | AN71: 0 | AO71: 0 | AP71: 0 | AQ71: 0 | AR71: 0 | AS71: 0 | AT71: 0 | AU71: 0 | AV71: 0
D72: 星展信用卡(15.89%) | E72: {=AVERAGE(_xlfn._xlws.FILTER(G72:AV72, $G$3:$AV$3 <= $E$2))} -> #NAME? | G72: 3000 | H72: 3000 | I72: 3000 | J72: 3000 | K72: 3000 | L72: 3000 | M72: 0 | N72: 0 | O72: 0 | P72: 0 | Q72: 0 | R72: 0 | S72: 0 | T72: 0 | U72: 0 | V72: 0 | W72: 0 | X72: 0 | Y72: 0 | Z72: 0 | AA72: 0 | AB72: 0 | AC72: 0 | AD72: 0 | AE72: 0 | AF72: 0 | AG72: 0 | AH72: 0 | AI72: 0 | AJ72: 0 | AK72: 0 | AL72: 0 | AM72: 0 | AN72: 0 | AO72: 0 | AP72: 0 | AQ72: 0 | AR72: 0 | AS72: 0 | AT72: 0 | AU72: 0 | AV72: 0
D73: 中信信貸(14.78%) | E73: {=AVERAGE(_xlfn._xlws.FILTER(G73:AV73, $G$3:$AV$3 <= $E$2))} -> #NAME? | G73: 5177 | H73: 5177 | I73: 5177 | J73: 5177 | K73: 5177 | L73: 5177 | M73: 0 | N73: 0 | O73: 0 | P73: 0 | Q73: 0 | R73: 0 | S73: 0 | T73: 0 | U73: 0 | V73: 0 | W73: 0 | X73: 0 | Y73: 0 | Z73: 0 | AA73: 0 | AB73: 0 | AC73: 0 | AD73: 0 | AE73: 0 | AF73: 0 | AG73: 0 | AH73: 0 | AI73: 0 | AJ73: 0 | AK73: 0 | AL73: 0 | AM73: 0 | AN73: 0 | AO73: 0 | AP73: 0 | AQ73: 0 | AR73: 0 | AS73: 0 | AT73: 0 | AU73: 0 | AV73: 0
D74: 中信信貸(14.78%) | E74: {=AVERAGE(_xlfn._xlws.FILTER(G74:AV74, $G$3:$AV$3 <= $E$2))} -> #NAME? | G74: 29911 | H74: 29911 | I74: 29911 | J74: 29911 | K74: 29911 | L74: 29911 | M74: 34526 | N74: 34526 | O74: 34526 | P74: 34526 | Q74: 34526 | R74: 34526 | S74: 34526 | T74: 34526 | U74: 34526 | V74: 34526 | W74: 34526 | X74: 34526 | Y74: 34526 | Z74: 34526 | AA74: 34526 | AB74: 34526 | AC74: 34526 | AD74: 34526 | AE74: 34526 | AF74: 34526 | AG74: 34526 | AH74: 34526 | AI74: 34526 | AJ74: 34526 | AK74: 34526 | AL74: 34526 | AM74: 34526 | AN74: 34526 | AO74: 34527 | AP74: 34528 | AQ74: 34529 | AR74: 34530 | AS74: 34531 | AT74: 34532 | AU74: 34533 | AV74: 34534
D75: 星展信貸(5.99%) | E75: {=AVERAGE(_xlfn._xlws.FILTER(G75:AV75, $G$3:$AV$3 <= $E$2))} -> #NAME? | G75: 1456 | H75: 1456 | I75: 1456 | J75: 1456 | K75: 1456 | L75: 1456 | M75: 0 | N75: 0 | O75: 0 | P75: 0 | Q75: 0 | R75: 0 | S75: 0 | T75: 0 | U75: 0 | V75: 0 | W75: 0 | X75: 0 | Y75: 0 | Z75: 0 | AA75: 0 | AB75: 0 | AC75: 0 | AD75: 0 | AE75: 0 | AF75: 0 | AG75: 0 | AH75: 0 | AI75: 0 | AJ75: 0 | AK75: 0 | AL75: 0 | AM75: 0 | AN75: 0 | AO75: 0 | AP75: 0 | AQ75: 0 | AR75: 0 | AS75: 0 | AT75: 0 | AU75: 0 | AV75: 0
D76: 樂分期 | E76: {=AVERAGE(_xlfn._xlws.FILTER(G76:AV76, $G$3:$AV$3 <= $E$2))} -> #NAME? | G76: 2937 | H76: 2937 | I76: 2937 | J76: 2937 | K76: 2937 | L76: 2937 | M76: 0 | N76: 0 | O76: 0 | P76: 0 | Q76: 0 | R76: 0 | S76: 0 | T76: 0 | U76: 0 | V76: 0 | W76: 0 | X76: 0 | Y76: 0 | Z76: 0 | AA76: 0 | AB76: 0 | AC76: 0 | AD76: 0 | AE76: 0 | AF76: 0 | AG76: 0 | AH76: 0 | AI76: 0 | AJ76: 0 | AK76: 0 | AL76: 0 | AM76: 0 | AN76: 0 | AO76: 0 | AP76: 0 | AQ76: 0 | AR76: 0 | AS76: 0 | AT76: 0 | AU76: 0 | AV76: 0
D77: 裕富分期 | E77: {=AVERAGE(_xlfn._xlws.FILTER(G77:AV77, $G$3:$AV$3 <= $E$2))} -> #NAME? | G77: 7800 | H77: 7800 | I77: 7800 | J77: 7800 | K77: 7800 | L77: 7800 | M77: 7800 | N77: 7800 | O77: 7800 | P77: 0 | Q77: 0 | R77: 0 | S77: 0 | T77: 0 | U77: 0 | V77: 0 | W77: 0 | X77: 0 | Y77: 0 | Z77: 0 | AA77: 0 | AB77: 0 | AC77: 0 | AD77: 0 | AE77: 0 | AF77: 0 | AG77: 0 | AH77: 0 | AI77: 0 | AJ77: 0 | AK77: 0 | AL77: 0 | AM77: 0 | AN77: 0 | AO77: 0 | AP77: 0 | AQ77: 0 | AR77: 0 | AS77: 0 | AT77: 0 | AU77: 0 | AV77: 0
D78: 車貸 | E78: {=AVERAGE(_xlfn._xlws.FILTER(G78:AV78, $G$3:$AV$3 <= $E$2))} -> #NAME? | G78: 23128 | H78: 23128 | I78: 23128 | J78: 23128 | K78: 23128 | L78: 23128 | M78: 23128 | N78: 23128 | O78: 23128 | P78: 23128 | Q78: 23128 | R78: 23128 | S78: 23128 | T78: 23128 | U78: 23128 | V78: 23128 | W78: 23128 | X78: 23128 | Y78: 23128 | Z78: 23128 | AA78: 23128 | AB78: 23128 | AC78: 23128 | AD78: 23128 | AE78: 23128 | AF78: 23128 | AG78: 23128 | AH78: 23128 | AI78: 23128 | AJ78: 23128 | AK78: 23128 | AL78: 23128 | AM78: 23128 | AN78: 23128 | AO78: 23129 | AP78: 23130 | AQ78: 23131 | AR78: 23132 | AS78: 23133 | AT78: 23134 | AU78: 23135 | AV78: 23136
D79: 和潤機車 | E79: {=AVERAGE(_xlfn._xlws.FILTER(G79:AV79, $G$3:$AV$3 <= $E$2))} -> #NAME? | G79: 7260 | H79: 7260 | I79: 7260 | J79: 7260 | K79: 7260 | L79: 7260 | M79: 7260 | N79: 7260 | O79: 7260 | P79: 7260 | Q79: 7260 | R79: 7260 | S79: 7260 | T79: 7260 | U79: 7260 | V79: 7260 | W79: 7260 | X79: 7260 | Y79: 7260 | Z79: 7260 | AA79: 7260 | AB79: 7260 | AC79: 7260 | AD79: 7260 | AE79: 7260 | AF79: 7260 | AG79: 7260 | AH79: 7260 | AI79: 7260 | AJ79: 0 | AK79: 0 | AL79: 0 | AM79: 0 | AN79: 0 | AO79: 0 | AP79: 0 | AQ79: 0 | AR79: 0 | AS79: 0 | AT79: 0 | AU79: 0 | AV79: 0
E80: {=AVERAGE(_xlfn._xlws.FILTER(G80:AV80, $G$3:$AV$3 <= $E$2))} -> #NAME? | G80: 0 | H80: 0 | I80: 0 | J80: 0 | K80: 0 | L80: 0 | M80: 0 | N80: 0 | O80: 0 | P80: 0 | Q80: 0 | R80: 0 | S80: 0 | T80: 0 | U80: 0 | V80: 0 | W80: 0 | X80: 0 | Y80: 0 | Z80: 0 | AA80: 0 | AB80: 0 | AC80: 0 | AD80: 0 | AE80: 0 | AF80: 0 | AG80: 0 | AH80: 0 | AI80: 0 | AJ80: 0 | AK80: 0 | AL80: 0 | AM80: 0 | AN80: 0 | AO80: 0 | AP80: 0 | AQ80: 0 | AR80: 0 | AS80: 0 | AT80: 0 | AU80: 0 | AV80: 0
D81: 育 | E81: {=AVERAGE(_xlfn._xlws.FILTER(G81:AV81, $G$3:$AV$3 <= $E$2))} -> #NAME? | G81: 0 | H81: 0 | I81: =SUM(I82:I86) -> 0 | J81: 0 | K81: 0 | L81: 0 | M81: 0 | N81: 0 | O81: 0 | P81: 0 | Q81: 0 | R81: 0 | S81: 0 | T81: 0 | U81: 0 | V81: 0 | W81: 0 | X81: 0 | Y81: 0 | Z81: 0 | AA81: 0 | AB81: 0 | AC81: 0 | AD81: 0 | AE81: 0 | AF81: 0 | AG81: 0 | AH81: 0 | AI81: 0 | AJ81: 0 | AK81: 0 | AL81: 0 | AM81: 0 | AN81: 0 | AO81: 0 | AP81: 0 | AQ81: 0 | AR81: 0 | AS81: 0 | AT81: 0 | AU81: 0 | AV81: 0
D82: 學費 | E82: {=AVERAGE(_xlfn._xlws.FILTER(G82:AV82, $G$3:$AV$3 <= $E$2))} -> #NAME? | G82: 0 | H82: 0 | I82: 0 | J82: 0 | K82: 0 | L82: 0 | M82: 0 | N82: 0 | O82: 0 | P82: 0 | Q82: 0 | R82: 0 | S82: 0 | T82: 0 | U82: 0 | V82: 0 | W82: 0 | X82: 0 | Y82: 0 | Z82: 0 | AA82: 0 | AB82: 0 | AC82: 0 | AD82: 0 | AE82: 0 | AF82: 0 | AG82: 0 | AH82: 0 | AI82: 0 | AJ82: 0 | AK82: 0 | AL82: 0 | AM82: 0 | AN82: 0 | AO82: 0 | AP82: 0 | AQ82: 0 | AR82: 0 | AS82: 0 | AT82: 0 | AU82: 0 | AV82: 0
D83: 書籍 | E83: {=AVERAGE(_xlfn._xlws.FILTER(G83:AV83, $G$3:$AV$3 <= $E$2))} -> #NAME? | G83: 0 | H83: 0 | I83: 0 | J83: 0 | K83: 0 | L83: 0 | M83: 0 | N83: 0 | O83: 0 | P83: 0 | Q83: 0 | R83: 0 | S83: 0 | T83: 0 | U83: 0 | V83: 0 | W83: 0 | X83: 0 | Y83: 0 | Z83: 0 | AA83: 0 | AB83: 0 | AC83: 0 | AD83: 0 | AE83: 0 | AF83: 0 | AG83: 0 | AH83: 0 | AI83: 0 | AJ83: 0 | AK83: 0 | AL83: 0 | AM83: 0 | AN83: 0 | AO83: 0 | AP83: 0 | AQ83: 0 | AR83: 0 | AS83: 0 | AT83: 0 | AU83: 0 | AV83: 0
D84: 課程 | E84: {=AVERAGE(_xlfn._xlws.FILTER(G84:AV84, $G$3:$AV$3 <= $E$2))} -> #NAME? | G84: 0 | H84: 0 | I84: 0 | J84: 0 | K84: 0 | L84: 0 | M84: 0 | N84: 0 | O84: 0 | P84: 0 | Q84: 0 | R84: 0 | S84: 0 | T84: 0 | U84: 0 | V84: 0 | W84: 0 | X84: 0 | Y84: 0 | Z84: 0 | AA84: 0 | AB84: 0 | AC84: 0 | AD84: 0 | AE84: 0 | AF84: 0 | AG84: 0 | AH84: 0 | AI84: 0 | AJ84: 0 | AK84: 0 | AL84: 0 | AM84: 0 | AN84: 0 | AO84: 0 | AP84: 0 | AQ84: 0 | AR84: 0 | AS84: 0 | AT84: 0 | AU84: 0 | AV84: 0
D85: 其他 | E85: {=AVERAGE(_xlfn._xlws.FILTER(G85:AV85, $G$3:$AV$3 <= $E$2))} -> #NAME? | G85: 0 | H85: 0 | I85: 0 | J85: 0 | K85: 0 | L85: 0 | M85: 0 | N85: 0 | O85: 0 | P85: 0 | Q85: 0 | R85: 0 | S85: 0 | T85: 0 | U85: 0 | V85: 0 | W85: 0 | X85: 0 | Y85: 0 | Z85: 0 | AA85: 0 | AB85: 0 | AC85: 0 | AD85: 0 | AE85: 0 | AF85: 0 | AG85: 0 | AH85: 0 | AI85: 0 | AJ85: 0 | AK85: 0 | AL85: 0 | AM85: 0 | AN85: 0 | AO85: 0 | AP85: 0 | AQ85: 0 | AR85: 0 | AS85: 0 | AT85: 0 | AU85: 0 | AV85: 0
E86: {=AVERAGE(_xlfn._xlws.FILTER(G86:AV86, $G$3:$AV$3 <= $E$2))} -> #NAME? | G86: 0 | H86: 0 | I86: 0 | J86: 0 | K86: 0 | L86: 0 | M86: 0 | N86: 0 | O86: 0 | P86: 0 | Q86: 0 | R86: 0 | S86: 0 | T86: 0 | U86: 0 | V86: 0 | W86: 0 | X86: 0 | Y86: 0 | Z86: 0 | AA86: 0 | AB86: 0 | AC86: 0 | AD86: 0 | AE86: 0 | AF86: 0 | AG86: 0 | AH86: 0 | AI86: 0 | AJ86: 0 | AK86: 0 | AL86: 0 | AM86: 0 | AN86: 0 | AO86: 0 | AP86: 0 | AQ86: 0 | AR86: 0 | AS86: 0 | AT86: 0 | AU86: 0 | AV86: 0
D87: 給予 | E87: {=AVERAGE(_xlfn._xlws.FILTER(G87:AV87, $G$3:$AV$3 <= $E$2))} -> #NAME? | G87: 0 | H87: 0 | I87: =SUM(I88:I92) -> 0 | J87: =SUM(J88:J92) -> 0 | K87: =SUM(K88:K92) -> 0 | L87: =SUM(L88:L92) -> 0 | M87: =SUM(M88:M92) -> 0 | N87: =SUM(N88:N92) -> 0 | O87: =SUM(O88:O92) -> 0 | P87: =SUM(P88:P92) -> 0 | ... AV87: =SUM(AV88:AV92) -> 0
D88: 贈送的禮物 | E88: {=AVERAGE(_xlfn._xlws.FILTER(G88:AV88, $G$3:$AV$3 <= $E$2))} -> #NAME? | G88: 0 | H88: 0 | I88: 0 | J88: 0 | K88: 0 | L88: 0 | M88: 0 | N88: 0 | O88: 0 | P88: 0 | Q88: 0 | R88: 0 | S88: 0 | T88: 0 | U88: 0 | V88: 0 | W88: 0 | X88: 0 | Y88: 0 | Z88: 0 | AA88: 0 | AB88: 0 | AC88: 0 | AD88: 0 | AE88: 0 | AF88: 0 | AG88: 0 | AH88: 0 | AI88: 0 | AJ88: 0 | AK88: 0 | AL88: 0 | AM88: 0 | AN88: 0 | AO88: 0 | AP88: 0 | AQ88: 0 | AR88: 0 | AS88: 0 | AT88: 0 | AU88: 0 | AV88: 0
D89: 慈善捐款 | E89: {=AVERAGE(_xlfn._xlws.FILTER(G89:AV89, $G$3:$AV$3 <= $E$2))} -> #NAME? | G89: 0 | H89: 0 | I89: 0 | J89: 0 | K89: 0 | L89: 0 | M89: 0 | N89: 0 | O89: 0 | P89: 0 | Q89: 0 | R89: 0 | S89: 0 | T89: 0 | U89: 0 | V89: 0 | W89: 0 | X89: 0 | Y89: 0 | Z89: 0 | AA89: 0 | AB89: 0 | AC89: 0 | AD89: 0 | AE89: 0 | AF89: 0 | AG89: 0 | AH89: 0 | AI89: 0 | AJ89: 0 | AK89: 0 | AL89: 0 | AM89: 0 | AN89: 0 | AO89: 0 | AP89: 0 | AQ89: 0 | AR89: 0 | AS89: 0 | AT89: 0 | AU89: 0 | AV89: 0
D90: 紅白包 | E90: {=AVERAGE(_xlfn._xlws.FILTER(G90:AV90, $G$3:$AV$3 <= $E$2))} -> #NAME? | G90: 0 | H90: 0 | I90: 0 | J90: 0 | K90: 0 | L90: 0 | M90: 0 | N90: 0 | O90: 0 | P90: 0 | Q90: 0 | R90: 0 | S90: 0 | T90: 0 | U90: 0 | V90: 0 | W90: 0 | X90: 0 | Y90: 0 | Z90: 0 | AA90: 0 | AB90: 0 | AC90: 0 | AD90: 0 | AE90: 0 | AF90: 0 | AG90: 0 | AH90: 0 | AI90: 0 | AJ90: 0 | AK90: 0 | AL90: 0 | AM90: 0 | AN90: 0 | AO90: 0 | AP90: 0 | AQ90: 0 | AR90: 0 | AS90: 0 | AT90: 0 | AU90: 0 | AV90: 0
D91: 孝親 | E91: {=AVERAGE(_xlfn._xlws.FILTER(G91:AV91, $G$3:$AV$3 <= $E$2))} -> #NAME? | G91: 0 | H91: 0 | I91: 0 | J91: 0 | K91: 0 | L91: 0 | M91: 0 | N91: 0 | O91: 0 | P91: 0 | Q91: 0 | R91: 0 | S91: 0 | T91: 0 | U91: 0 | V91: 0 | W91: 0 | X91: 0 | Y91: 0 | Z91: 0 | AA91: 0 | AB91: 0 | AC91: 0 | AD91: 0 | AE91: 0 | AF91: 0 | AG91: 0 | AH91: 0 | AI91: 0 | AJ91: 0 | AK91: 0 | AL91: 0 | AM91: 0 | AN91: 0 | AO91: 0 | AP91: 0 | AQ91: 0 | AR91: 0 | AS91: 0 | AT91: 0 | AU91: 0 | AV91: 0
D92: 其他 | E92: {=AVERAGE(_xlfn._xlws.FILTER(G92:AV92, $G$3:$AV$3 <= $E$2))} -> #NAME? | G92: 0 | H92: 0 | I92: 0 | J92: 0 | K92: 0 | L92: 0 | M92: 0 | N92: 0 | O92: 0 | P92: 0 | Q92: 0 | R92: 0 | S92: 0 | T92: 0 | U92: 0 | V92: 0 | W92: 0 | X92: 0 | Y92: 0 | Z92: 0 | AA92: 0 | AB92: 0 | AC92: 0 | AD92: 0 | AE92: 0 | AF92: 0 | AG92: 0 | AH92: 0 | AI92: 0 | AJ92: 0 | AK92: 0 | AL92: 0 | AM92: 0 | AN92: 0 | AO92: 0 | AP92: 0 | AQ92: 0 | AR92: 0 | AS92: 0 | AT92: 0 | AU92: 0 | AV92: 0
D93: 醫 | E93: {=AVERAGE(_xlfn._xlws.FILTER(G93:AV93, $G$3:$AV$3 <= $E$2))} -> #NAME? | G93: 0 | H93: 0 | I93: =SUM(I94:I95) -> 0 | J93: 0 | K93: 0 | L93: 0 | M93: 0 | N93: 0 | O93: 0 | P93: 0 | Q93: 0 | R93: 0 | S93: 0 | T93: 0 | U93: 0 | V93: 0 | W93: 0 | X93: 0 | Y93: 0 | Z93: 0 | AA93: 0 | AB93: 0 | AC93: 0 | AD93: 0 | AE93: 0 | AF93: 0 | AG93: 0 | AH93: 0 | AI93: 0 | AJ93: 0 | AK93: 0 | AL93: 0 | AM93: 0 | AN93: 0 | AO93: 0 | AP93: 0 | AQ93: 0 | AR93: 0 | AS93: 0 | AT93: 0 | AU93: 0 | AV93: 0
D94: 藥品 | E94: {=AVERAGE(_xlfn._xlws.FILTER(G94:AV94, $G$3:$AV$3 <= $E$2))} -> #NAME? | G94: 0 | H94: 0 | I94: 0 | J94: 0 | K94: 0 | L94: 0 | M94: 0 | N94: 0 | O94: 0 | P94: 0 | Q94: 0 | R94: 0 | S94: 0 | T94: 0 | U94: 0 | V94: 0 | W94: 0 | X94: 0 | Y94: 0 | Z94: 0 | AA94: 0 | AB94: 0 | AC94: 0 | AD94: 0 | AE94: 0 | AF94: 0 | AG94: 0 | AH94: 0 | AI94: 0 | AJ94: 0 | AK94: 0 | AL94: 0 | AM94: 0 | AN94: 0 | AO94: 0 | AP94: 0 | AQ94: 0 | AR94: 0 | AS94: 0 | AT94: 0 | AU94: 0 | AV94: 0
D95: 門診 | E95: {=AVERAGE(_xlfn._xlws.FILTER(G95:AV95, $G$3:$AV$3 <= $E$2))} -> #NAME? | G95: 0 | H95: 0 | I95: 0 | J95: 0 | K95: 0 | L95: 0 | M95: 0 | N95: 0 | O95: 0 | P95: 0 | Q95: 0 | R95: 0 | S95: 0 | T95: 0 | U95: 0 | V95: 0 | W95: 0 | X95: 0 | Y95: 0 | Z95: 0 | AA95: 0 | AB95: 0 | AC95: 0 | AD95: 0 | AE95: 0 | AF95: 0 | AG95: 0 | AH95: 0 | AI95: 0 | AJ95: 0 | AK95: 0 | AL95: 0 | AM95: 0 | AN95: 0 | AO95: 0 | AP95: 0 | AQ95: 0 | AR95: 0 | AS95: 0 | AT95: 0 | AU95: 0 | AV95: 0
D96: 其他 | E96: {=AVERAGE(_xlfn._xlws.FILTER(G96:AV96, $G$3:$AV$3 <= $E$2))} -> #NAME? | G96: 0 | H96: 0 | I96: =SUM(I97:I98) -> 5000 | J96: =SUM(J97:J98) -> 5000 | K96: =SUM(K97:K98) -> 5000 | L96: =SUM(L97:L98) -> 5000 | M96: =SUM(M97:M98) -> 5000 | N96: =SUM(N97:N98) -> 5000 | O96: =SUM(O97:O98) -> 5000 | P96: =SUM(P97:P98) -> 5000 | ... AV96: =SUM(AV97:AV98) -> 5011
E97: {=AVERAGE(_xlfn._xlws.FILTER(G97:AV97, $G$3:$AV$3 <= $E$2))} -> #NAME? | G97: 0 | H97: 0 | I97: 5000 | J97: 5000 | K97: 5000 | L97: 5000 | M97: 5000 | N97: 5000 | O97: 5000 | P97: 5000 | Q97: 5000 | R97: 55000 | S97: 5000 | T97: 5000 | U97: 5000 | V97: 5000 | W97: 5000 | X97: 5000 | Y97: 5000 | Z97: 5000 | AA97: 5000 | AB97: 5000 | AC97: 5000 | AD97: 5000 | AE97: 5000 | AF97: 5000 | AG97: 5000 | AH97: 5000 | AI97: 5000 | AJ97: 5000 | AK97: 5000 | AL97: 5001 | AM97: 5002 | AN97: 5003 | AO97: 5004 | AP97: 5005 | AQ97: 5006 | AR97: 5007 | AS97: 5008 | AT97: 5009 | AU97: 5010 | AV97: 5011
E98: {=AVERAGE(_xlfn._xlws.FILTER(G98:AV98, $G$3:$AV$3 <= $E$2))} -> #NAME? | G98: 0 | H98: 0 | I98: 0 | J98: 0 | K98: 0 | L98: 0 | M98: 0 | N98: 0 | O98: 0 | P98: 0 | Q98: 0 | R98: 0 | S98: 0 | T98: 0 | U98: 0 | V98: 0 | W98: 0 | X98: 0 | Y98: 0 | Z98: 0 | AA98: 0 | AB98: 0 | AC98: 0 | AD98: 0 | AE98: 0 | AF98: 0 | AG98: 0 | AH98: 0 | AI98: 0 | AJ98: 0 | AK98: 0 | AL98: 0 | AM98: 0 | AN98: 0 | AO98: 0 | AP98: 0 | AQ98: 0 | AR98: 0 | AS98: 0 | AT98: 0 | AU98: 0 | AV98: 0
C99: 想要 | D99: 樂 | E99: {=AVERAGE(_xlfn._xlws.FILTER(G99:AV99, $G$3:$AV$3 <= $E$2))} -> #NAME? | G99: 0 | H99: 0 | I99: 0 | J99: 0 | K99: 0 | L99: 0 | M99: 0 | N99: 0 | O99: 0 | P99: 0 | Q99: 0 | R99: 0 | S99: 0 | T99: 0 | U99: 0 | V99: 0 | W99: 0 | X99: 0 | Y99: 0 | Z99: 0 | AA99: 0 | AB99: 0 | AC99: 0 | AD99: 0 | AE99: 0 | AF99: 0 | AG99: 0 | AH99: 0 | AI99: 0 | AJ99: 0 | AK99: 0 | AL99: 0 | AM99: 0 | AN99: 0 | AO99: 0 | AP99: 0 | AQ99: 0 | AR99: 0 | AS99: 0 | AT99: 0 | AU99: 0 | AV99: 0
D100: 活動 | E100: {=AVERAGE(_xlfn._xlws.FILTER(G100:AV100, $G$3:$AV$3 <= $E$2))} -> #NAME? | G100: 0 | H100: 0 | I100: 0 | J100: 0 | K100: 0 | L100: 0 | M100: 0 | N100: 0 | O100: 0 | P100: 0 | Q100: 0 | R100: 0 | S100: 0 | T100: 0 | U100: 0 | V100: 0 | W100: 0 | X100: 0 | Y100: 0 | Z100: 0 | AA100: 0 | AB100: 0 | AC100: 0 | AD100: 0 | AE100: 0 | AF100: 0 | AG100: 0 | AH100: 0 | AI100: 0 | AJ100: 0 | AK100: 0 | AL100: 0 | AM100: 0 | AN100: 0 | AO100: 0 | AP100: 0 | AQ100: 0 | AR100: 0 | AS100: 0 | AT100: 0 | AU100: 0 | AV100: 0
D101: 書籍 | E101: {=AVERAGE(_xlfn._xlws.FILTER(G101:AV101, $G$3:$AV$3 <= $E$2))} -> #NAME? | G101: 0 | H101: 0 | I101: 0 | J101: 0 | K101: 0 | L101: 0 | M101: 0 | N101: 0 | O101: 0 | P101: 0 | Q101: 0 | R101: 0 | S101: 0 | T101: 0 | U101: 0 | V101: 0 | W101: 0 | X101: 0 | Y101: 0 | Z101: 0 | AA101: 0 | AB101: 0 | AC101: 0 | AD101: 0 | AE101: 0 | AF101: 0 | AG101: 0 | AH101: 0 | AI101: 0 | AJ101: 0 | AK101: 0 | AL101: 0 | AM101: 0 | AN101: 0 | AO101: 0 | AP101: 0 | AQ101: 0 | AR101: 0 | AS101: 0 | AT101: 0 | AU101: 0 | AV101: 0
...

Sheet DASHBOARD

Sheet Resources
B1: 顏色 | C1: 位置 | D1: 傾斜角度 | E1: Transparency | G1: Shadow | H1: 50 | I1: 100 | J1: 40 | K1: 135 | L1: 15
B2: #3883D4 | C2: 0 | D2: 70 | H2: 20 | I2: 100 | J2: 15 | K2: 135 | L2: 8
B3: #224192 | C3: 75 | D3: 70
B5: #21509A | C5: 0 | D5: 135
B6: #0F2453 | C6: 55 | D6: 135
A7: LINE | B7: #6494DA | C7: 0 | D7: 90
A8: LINE | B8: #BCC6FF | C8: 50 | D8: 90
A9: LINE | B9: #2F6EC7 | C9: 95 | D9: 90
B11: #2F6EC7 | C11: 0 | D11: 45
B12: #224E9F | C12: 85 | D12: 45
A13: LINE | B13: #6494DA | C13: 0 | D13: 90
A14: LINE | B14: #BCC6FF | C14: 75 | D14: 90
A15: LINE | B15: #2F6EC7 | C15: 100 | D15: 90
B17: #1C4285 | C17: 0 | D17: 45
B18: #132D64 | C18: 85 | D18: 45
A19: LINE | B19: #6494DA | C19: 0 | D19: 90
A20: LINE | B20: #BCC6FF | C20: 85 | D20: 90
A21: LINE | B21: #2F6EC7 | C21: 95 | D21: 90
B23: #15306A | C23: 0 | D23: 45
B24: #13295E | C24: 85 | D24: 45
A25: LINE | B25: #6494DA | C25: 0 | D25: 90
A26: LINE | B26: #BCC6FF | C26: 75 | D26: 90
A27: LINE | B27: #2F6EC7 | C27: 100 | D27: 90

Sheet 評估表
B2: LIFE評估表
C3: 目標 | D3: 公式 | F3: 平衡航道 | G3: 現況 | H3: 缺口 | L3: 細項說明
B4: LAUCH(啟動) | C4: 沒有壓榨性債務(利率>8%) | D4: 月收入* | E4: 0 | F4: ='現金流量表(連動)'!$E$5*E4 -> 0 | G4: =資產負債表!C33 -> 3435680 | H4: =G4-F4 -> 3435680 | J4: *3-5年達成 | K4: *債務利息不要超過通膨2% | L4: 其他個人財產
B5: 淨資產<年收入50% | C5: 現金準備(活期存款) | D5: 月收入* | E5: 1 | F5: ='現金流量表(連動)'!$E$5*E5 -> 76000 | G5: =資產負債表!C4 -> 10000 | H5: =G5-F5 -> -66000 | J5: *儲蓄率平均每年18% | K5: *儲蓄存款用於應急支出 | L5: 其他資產
B6: =資產負債表!K2/('現金流量表(連動)'!E5*12) -> 0.15350877 | C6: 投資收益 | D6: 月收入* | E6: 1 | F6: ='現金流量表(連動)'!$E$5*E6 -> 76000 | G6: =資產負債表!Q13+資產負債表!Q16 -> 20000 | H6: =G6-F6 -> -56000 | J6: *不要有購屋念頭 | K6: *活期存款用於日常支出 | L6: 生息資產
C7: 現金準備(儲蓄存款) | D7: 月收入* | E7: 2 | F7: ='現金流量表(連動)'!$E$5*E7 -> 152000 | G7: =資產負債表!C5 -> 0 | H7: =G7-F7 -> -152000 | J7: *通常佔據人生3-5年 | L7: 投資收益
B8: INDEPENDENCE(獨立) | C8: 沒有壓榨性債務(利率>10%) | D8: 月收入* | E8: 0 | F8: ='現金流量表(連動)'!$E$5*E8 -> 0 | G8: =資產負債表!C33 -> 3435680 | H8: =G8-F8 -> 3435680 | J8: *負債比<65% | L8: 外匯
B9: 淨資產=年收入50%-200% | C9: 現金準備(活期存款) | D9: 月收入* | E9: 3 | F9: ='現金流量表(連動)'!$E$5*E9 -> 228000 | G9: =資產負債表!C4 -> 10000 | H9: =G9-F9 -> -218000 | J9: *自住屋需考慮住至少7年 | L9: 期貨
B10: =資產負債表!K2/('現金流量表(連動)'!E5*12) -> 0.15350877 | C10: 現金準備(儲蓄存款) | D10: 月收入* | E10: 3 | F10: ='現金流量表(連動)'!$E$5*E10 -> 228000 | G10: =資產負債表!C5 -> 0 | H10: =G10-F10 -> -228000 | J10: *每個小孩增加儲蓄率2% | L10: 長期收益
C11: 投資收益 | D11: 月收入* | E11: 6 | F11: ='現金流量表(連動)'!$E$5*E11 -> 456000 | G11: =資產負債表!Q13+資產負債表!Q16 -> 20000 | H11: =G11-F11 -> -436000 | L11: 股票
C12: 改變人生(購屋頭期款、辭職準備金) | D12: 月收入* | E12: 9 | F12: ='現金流量表(連動)'!$E$5*E12 -> 684000 | G12: =資產負債表!C7 -> 0 | H12: =G12-F12 -> -684000 | L12: 基金
C13: 淨資產 | D13: 月收入* | E13: 21 | F13: ='現金流量表(連動)'!$E$5*E13 -> 1596000 | G13: =SUM(G9:G12) -> 30000 | H13: =G13-F13 -> -1566000 | L13: 債券
C14: 總負債 | D14: 月收入* | E14: 39 | F14: ='現金流量表(連動)'!$E$5*E14 -> 2964000 | G14: =資產負債表!K21 -> 3435680 | H14: =G14-F14 -> 471680 | L14: 事業股份
C15: 總資產 | D15: 月收入* | E15: 60 | F15: ='現金流量表(連動)'!$E$5*E15 -> 4560000 | G15: =資產負債表!K2 -> 140000 | H15: =G15-F15 -> -4420000 | L15: 投資不動產
B16: FREEDOM(自由) | C16: 沒有壓榨性債務(利率>10%) | D16: 月收入* | E16: 0 | F16: ='現金流量表(連動)'!$E$5*E16 -> 0 | G16: =資產負債表!C33 -> 3435680 | H16: =G16-F16 -> 3435680 | J16: *負債比<40% | L16: 改變人生
B17: 淨資產=年收入200%-500% | C17: 現金準備(活期存款+儲蓄存款) | D17: 月收入* | E17: 5 | F17: ='現金流量表(連動)'!$E$5*E17 -> 380000 | G17: =資產負債表!Q3 -> 10000 | H17: =G17-F17 -> -370000 | J17: *降低債務比例為主(增加資產) | L17: 銀行定存
B18: =資產負債表!K2/('現金流量表(連動)'!E5*12) -> 0.15350877 | C18: 其他個人財產 | D18: 月收入* | E18: 5 | F18: ='現金流量表(連動)'!$E$5*E18 -> 380000 | G18: =其他資產[[#Totals],[價值]]+資產負債表!M19 -> 110000 | H18: =G18-F18 -> -270000 | J18: *通常佔據人生10-15年 | L18: 壓榨性債務
C19: 投資收益 | D19: 月收入* | E19: 15 | F19: ='現金流量表(連動)'!$E$5*E19 -> 1140000 | G19: =資產負債表!Q13 -> 20000 | H19: =G19-F19 -> -1120000 | J19: *退休儲蓄:長期投資=6:4 | L19: 高利息貸款
C20: 長期收益 | D20: 月收入* | E20: 25 | F20: ='現金流量表(連動)'!$E$5*E20 -> 1900000 | G20: =資產負債表!Q16 -> 0 | H20: =G20-F20 -> -1900000 | J20: *淨財富超過月收入*60，再考慮清償債務 | L20: 信用卡
C21: 總負債 | D21: 月收入* | E21: 40 | F21: ='現金流量表(連動)'!$E$5*E21 -> 3040000 | G21: =資產負債表!K21 -> 3435680 | H21: =G21-F21 -> 395680 | L21: 功能性債務
C22: 淨財富 | D22: 月收入* | E22: 65 | F22: ='現金流量表(連動)'!$E$5*E22 -> 4940000 | G22: =G23-G21 -> -3295680 | H22: =G22-F22 -> -8235680 | L22: 車貸
C23: 總資產 | D23: 月收入* | E23: 105 | F23: ='現金流量表(連動)'!$E$5*E23 -> 7980000 | G23: =資產負債表!K2 -> 140000 | H23: =G23-F23 -> -7840000 | L23: 房貸
B24: EQUILIBRIUM(均衡) | C24: 沒有壓榨性債務(利率>10%) | D24: 月收入* | E24: 0 | F24: ='現金流量表(連動)'!$E$5*E24 -> 0 | G24: =資產負債表!C33 -> 3435680 | H24: =G24-F24 -> 3435680 | J24: 負債比<25% | L24: 致富性債務
B25: 淨資產=年收入500%- | C25: 現金準備(活期存款+儲蓄存款) | D25: 月收入* | E25: 7 | F25: ='現金流量表(連動)'!$E$5*E25 -> 532000 | G25: =資產負債表!Q3 -> 10000 | H25: =G25-F25 -> -522000 | J25: 是當持有債務，有利於未來發展 | L25: 自用不動產抵押貸款
B26: =資產負債表!K2/('現金流量表(連動)'!E5*12) -> 0.15350877 | C26: 其他個人財產 | D26: 月收入* | E26: 7 | F26: ='現金流量表(連動)'!$E$5*E26 -> 532000 | G26: =其他資產[[#Totals],[價值]]+資產負債表!M19 -> 110000 | H26: =G26-F26 -> -422000 | L26: 投資性不動產抵押貸款
C27: 總負債 | D27: 月收入* | E27: 35 | F27: ='現金流量表(連動)'!$E$5*E27 -> 2660000 | G27: =資產負債表!K21 -> 3435680 | H27: =G27-F27 -> 775680 | L27: 信用貸款
C28: 投資收益 | D28: 月收入* | E28: 56 | F28: ='現金流量表(連動)'!$E$5*E28 -> 4256000 | G28: =資產負債表!Q13 -> 20000 | H28: =G28-F28 -> -4236000 | L28: 分期付款
C29: 長期收益 | D29: 月收入* | E29: 91 | F29: ='現金流量表(連動)'!$E$5*E29 -> 6916000 | G29: =資產負債表!Q16 -> 0 | H29: =G29-F29 -> -6916000 | L29: 保單貸款
C30: 總投資資產 | D30: 月收入* | E30: 147 | F30: ='現金流量表(連動)'!$E$5*E30 -> 11172000 | G30: =G28+G29 -> 20000 | H30: =G30-F30 -> -11152000
B32: 總負債 | C32: =資產負債表!K21 -> 3435680
B33: 基準單位=總負債/8 | C33: =C32/8 -> 429460
B36: FREEDOM(自由) | C36: 沒有壓榨性債務(利率>10%) | D36: 基準單位* | E36: 0 | F36: =$C$33*E36 -> 0 | G36: =資產負債表!C49 -> 0 | H36: =G36-F36 -> 0
B37: 淨資產=年收入200%-500% | C37: 現金準備(活期存款+儲蓄存款) | D37: 基準單位* | E37: 1 | F37: =$C$33*E37 -> 429460 | G37: =資產負債表!Q19 -> 0 | H37: =G37-F37 -> -429460
B38: =資產負債表!K2/('現金流量表(連動)'!E5*12) -> 0.15350877 | C38: 其他個人財產 | D38: 基準單位* | E38: 1 | F38: =$C$33*E38 -> 429460 | G38: =其他資產[[#Totals],[價值]]+資產負債表!M35 -> 110000 | H38: =G38-F38 -> -319460
C39: 投資收益 | D39: 基準單位* | E39: 3 | F39: =$C$33*E39 -> 1288380 | G39: =資產負債表!Q29 -> 24.540571 | H39: =G39-F39 -> -1288355.5
C40: 長期收益 | D40: 基準單位* | E40: 5 | F40: =$C$33*E40 -> 2147300 | G40: =資產負債表!Q32 -> 0 | H40: =G40-F40 -> -2147300
C41: 總負債 | D41: 基準單位* | E41: 8 | F41: =$C$33*E41 -> 3435680 | G41: =資產負債表!K37 -> 0 | H41: =G41-F41 -> -3435680
C42: 淨財富 | D42: 基準單位* | E42: 13 | F42: =$C$33*E42 -> 5582980 | G42: =G43-G41 -> 0 | H42: =G42-F42 -> -5582980
C43: 總資產 | D43: 基準單位* | E43: 21 | F43: =$C$33*E43 -> 9018660 | G43: =資產負債表!K18 -> 0 | H43: =G43-F43 -> -9018660
B44: EQUILIBRIUM(均衡) | C44: 沒有壓榨性債務(利率>10%) | D44: 基準單位* | E44: 0 | F44: =$C$33*E44 -> 0 | G44: =資產負債表!C49 -> 0 | H44: =G44-F44 -> 0
B45: 淨資產=年收入500%- | C45: 現金準備(活期存款+儲蓄存款) | D45: 基準單位* | E45: 7 | F45: =$C$33*E45 -> 3006220 | G45: =資產負債表!Q19 -> 0 | H45: =G45-F45 -> -3006220
B46: =資產負債表!K2/('現金流量表(連動)'!E5*12) -> 0.15350877 | C46: 其他個人財產 | D46: 基準單位* | E46: 7 | F46: =$C$33*E46 -> 3006220 | G46: =其他資產[[#Totals],[價值]]+資產負債表!M35 -> 110000 | H46: =G46-F46 -> -2896220
C47: 總負債 | D47: 基準單位* | E47: 35 | F47: =$C$33*E47 -> 15031100 | G47: =資產負債表!K37 -> 0 | H47: =G47-F47 -> -15031100
C48: 投資收益 | D48: 基準單位* | E48: 56 | F48: =$C$33*E48 -> 24049760 | G48: =資產負債表!Q29 -> 24.540571 | H48: =G48-F48 -> -24049735
C49: 長期收益 | D49: 基準單位* | E49: 91 | F49: =$C$33*E49 -> 39080860 | G49: =資產負債表!Q32 -> 0 | H49: =G49-F49 -> -39080860
C50: 總投資資產 | D50: 基準單位* | E50: 147 | F50: =$C$33*E50 -> 63130620 | G50: =G48+G49 -> 24.540571 | H50: =G50-F50 -> -63130595

Sheet 收入規劃
B2: 預算規劃
B4: 概要 | D4: 1 | E4: 2 | F4: 3 | G4: 4 | H4: 5 | I4: 6 | J4: 7 | K4: 8 | L4: 9 | M4: 10 | N4: 11 | O4: 12 | P4: Total | Q4: Avg
B5: 總收入 | D5: =D10+D19+D26 -> 84505 | E5: =E10+E19+E26 -> 0 | F5: =F10+F19+F26 -> 0 | G5: =G10+G19+G26 -> 0 | H5: =H10+H19+H26 -> 0 | I5: =I10+I19+I26 -> 0 | J5: =J10+J19+J26 -> 0 | K5: =K10+K19+K26 -> 0 | ... O5: =O10+O19+O26 -> 0 | P5: =SUM(D5:O5) -> 84505 | Q5: =P5/COLUMNS(D5:O5) -> 7042.0833
B6: 總支出 | D6: =支出規劃!D6 -> 0 | E6: =支出規劃!E6 -> 0 | F6: =支出規劃!F6 -> 0 | G6: =支出規劃!G6 -> 0 | H6: =支出規劃!H6 -> 0 | I6: =支出規劃!I6 -> 0 | J6: =支出規劃!J6 -> 0 | K6: =支出規劃!K6 -> 0 | ... O6: =支出規劃!O6 -> 0 | P6: =SUM(D6:O6) -> 0 | Q6: =P6/COLUMNS(D6:O6) -> 0
B7: 淨額 | D7: =D5-D6 -> 84505 | E7: =E5-E6 -> 0 | F7: =F5-F6 -> 0 | G7: =G5-G6 -> 0 | H7: =H5-H6 -> 0 | I7: =I5-I6 -> 0 | J7: =J5-J6 -> 0 | K7: =K5-K6 -> 0 | ... O7: =O5-O6 -> 0 | P7: =SUM(D7:O7) -> 84505 | Q7: =P7/COLUMNS(D7:O7) -> 7042.0833
B9: 工資收入 | D9: =D$4 -> 1 | E9: =E$4 -> 2 | F9: =F$4 -> 3 | G9: =G$4 -> 4 | H9: =H$4 -> 5 | I9: =I$4 -> 6 | J9: =J$4 -> 7 | K9: =K$4 -> 8 | ... O9: =O$4 -> 12 | P9: Total | Q9: Avg
B10: 總 | D10: =SUM(D11:D16) -> 79000 | E10: =SUM(E11:E16) -> 0 | F10: =SUM(F11:F16) -> 0 | G10: =SUM(G11:G16) -> 0 | H10: =SUM(H11:H16) -> 0 | I10: =SUM(I11:I16) -> 0 | J10: =SUM(J11:J16) -> 0 | K10: =SUM(K11:K16) -> 0 | ... Q10: =SUM(Q11:Q16) -> 6583.3333
B11: 薪資 | D11: 60000 | P11: =SUM(D11:O11) -> 60000 | Q11: =P11/COLUMNS(D11:O11) -> 5000
B12: 加班費 | D12: 19000 | P12: =SUM(D12:O12) -> 19000 | Q12: =P12/COLUMNS(D12:O12) -> 1583.3333
B13: 佣金(考績獎金) | P13: =SUM(D13:O13) -> 0 | Q13: =P13/COLUMNS(D13:O13) -> 0
B14: 年終獎金 | P14: =SUM(D14:O14) -> 0 | Q14: =P14/COLUMNS(D14:O14) -> 0
B15: 兼職收入 | P15: =SUM(D15:O15) -> 0 | Q15: =P15/COLUMNS(D15:O15) -> 0
B16: 其他 | P16: =SUM(D16:O16) -> 0 | Q16: =P16/COLUMNS(D16:O16) -> 0
B18: 非工資收入 | D18: =D$4 -> 1 | E18: =E$4 -> 2 | F18: =F$4 -> 3 | G18: =G$4 -> 4 | H18: =H$4 -> 5 | I18: =I$4 -> 6 | J18: =J$4 -> 7 | K18: =K$4 -> 8 | ... O18: =O$4 -> 12 | P18: Total | Q18: Avg
B19: 總 | D19: =SUM(D20:D23) -> 5500 | E19: =SUM(E20:E23) -> 0 | F19: =SUM(F20:F23) -> 0 | G19: =SUM(G20:G23) -> 0 | H19: =SUM(H20:H23) -> 0 | I19: =SUM(I20:I23) -> 0 | J19: =SUM(J20:J23) -> 0 | K19: =SUM(K20:K23) -> 0 | ... Q19: =SUM(Q20:Q23) -> 458.33333
B20: 營利所得 | D20: 5500 | P20: =SUM(D20:O20) -> 5500 | Q20: =P20/COLUMNS(D20:O20) -> 458.33333
B21: 資本利得 | P21: =SUM(D21:O21) -> 0 | Q21: =P21/COLUMNS(D21:O21) -> 0
B22: 人情借款 | P22: =SUM(D22:O22) -> 0 | Q22: =P22/COLUMNS(D22:O22) -> 0
B23: 其他 | P23: =SUM(D23:O23) -> 0 | Q23: =P23/COLUMNS(D23:O23) -> 0
B25: 被動收入 | D25: =D$4 -> 1 | E25: =E$4 -> 2 | F25: =F$4 -> 3 | G25: =G$4 -> 4 | H25: =H$4 -> 5 | I25: =I$4 -> 6 | J25: =J$4 -> 7 | K25: =K$4 -> 8 | ... O25: =O$4 -> 12 | P25: Total | Q25: Avg
B26: 總 | D26: =SUM(D27:D33) -> 5 | E26: =SUM(E27:E33) -> 0 | F26: =SUM(F27:F33) -> 0 | G26: =SUM(G27:G33) -> 0 | H26: =SUM(H27:H33) -> 0 | I26: =SUM(I27:I33) -> 0 | J26: =SUM(J27:J33) -> 0 | K26: =SUM(K27:K33) -> 0 | ... Q26: =SUM(Q27:Q33) -> 0.41666667
B27: 退休金 | P27: =SUM(D27:O27) -> 0 | Q27: =P27/COLUMNS(D27:O27) -> 0
B28: 保險滿期金 | P28: =SUM(D28:O28) -> 0 | Q28: =P28/COLUMNS(D28:O28) -> 0
B29: 跟會到期 | P29: =SUM(D29:O29) -> 0 | Q29: =P29/COLUMNS(D29:O29) -> 0
B30: 利息收入 | D30: 5 | P30: =SUM(D30:O30) -> 5 | Q30: =P30/COLUMNS(D30:O30) -> 0.41666667
B31: 租金收入 | P31: =SUM(D31:O31) -> 0 | Q31: =P31/COLUMNS(D31:O31) -> 0
B32: 股利
B33: 其他 | P33: =SUM(D33:O33) -> 0 | Q33: =P33/COLUMNS(D33:O33) -> 0
B35: 蓄水池分配 | D35: =D$4 -> 1 | E35: =E$4 -> 2 | F35: =F$4 -> 3 | G35: =G$4 -> 4 | H35: =H$4 -> 5 | I35: =I$4 -> 6 | J35: =J$4 -> 7 | K35: =K$4 -> 8 | ... O35: =O$4 -> 12 | P35: Total | Q35: Avg | R35: 收入占比
B36: 現金池 | C36: 必要支出（NEC） | D36: =$D$5*R36 -> 46477.75 | E36: =$D$5*SUMPRODUCT(K64:N64,$K$63:$N$63) -> 8450.5 | F36: =$D$5*T36 -> 0 | G36: =$D$5*U36 -> 0 | H36: =$D$5*V36 -> 0 | I36: =$D$5*W36 -> 0 | J36: =$D$5*X36 -> 0 | K36: =$D$5*Y36 -> 0 | L36: =$D$5*Z36 -> 0 | M36: =$D$5*AA36 -> 0 | ... O36: =$D$5*AC36 -> 0 | P36: =SUM(D36:O36) -> 54928.25 | Q36: =P36/COLUMNS(D36:O36) -> 4577.3542 | R36: 0.55
B37: 預備金池 | C37: 長期儲蓄（LTS） | D37: =$D$5*R37 -> 8450.5 | E37: =$D$5*SUMPRODUCT(K65:N65,$K$63:$N$63) -> 21126.25 | F37: =$D$5*T38 -> 0 | G37: =$D$5*U38 -> 0 | H37: =$D$5*V38 -> 0 | I37: =$D$5*W38 -> 0 | J37: =$D$5*X38 -> 0 | K37: =$D$5*Y38 -> 0 | L37: =$D$5*Z38 -> 0 | M37: =$D$5*AA38 -> 0 | ... O37: =$D$5*AC38 -> 0 | P37: =SUM(D37:O38) -> 29576.75 | Q37: =P37/COLUMNS(D37:O38) -> 2464.7292 | R37: 0.1
B38: 夢想池
B39: 投資池 | C39: 財務自由（FFA） | D39: =$D$5*R39 -> 8450.5 | E39: =$D$5*SUMPRODUCT(K66:N66,$K$63:$N$63) -> 27886.65 | F39: =$D$5*T39 -> 0 | G39: =$D$5*U39 -> 0 | H39: =$D$5*V39 -> 0 | I39: =$D$5*W39 -> 0 | J39: =$D$5*X39 -> 0 | K39: =$D$5*Y39 -> 0 | L39: =$D$5*Z39 -> 0 | M39: =$D$5*AA39 -> 0 | ... O39: =$D$5*AC39 -> 0 | P39: =SUM(D39:O39) -> 36337.15 | Q39: =P39/COLUMNS(D39:O39) -> 3028.0958 | R39: 0.1
C40: 教育成長（EDU） | D40: =$D$5*R40 -> 8450.5 | E40: =$D$5*SUMPRODUCT(K67:N67,$K$63:$N$63) -> 3380.2 | F40: =$D$5*T40 -> 0 | G40: =$D$5*U40 -> 0 | H40: =$D$5*V40 -> 0 | I40: =$D$5*W40 -> 0 | J40: =$D$5*X40 -> 0 | K40: =$D$5*Y40 -> 0 | L40: =$D$5*Z40 -> 0 | M40: =$D$5*AA40 -> 0 | ... O40: =$D$5*AC40 -> 0 | P40: =SUM(D40:O40) -> 11830.7 | Q40: =P40/COLUMNS(D40:O40) -> 985.89167 | R40: 0.1
C41: 玩樂享受（PLY） | D41: =$D$5*R41 -> 8450.5 | E41: =$D$5*SUMPRODUCT(K68:N68,$K$63:$N$63) -> 3380.2 | F41: =$D$5*T41 -> 0 | G41: =$D$5*U41 -> 0 | H41: =$D$5*V41 -> 0 | I41: =$D$5*W41 -> 0 | J41: =$D$5*X41 -> 0 | K41: =$D$5*Y41 -> 0 | L41: =$D$5*Z41 -> 0 | M41: =$D$5*AA41 -> 0 | ... O41: =$D$5*AC41 -> 0 | P41: =SUM(D41:O41) -> 11830.7 | Q41: =P41/COLUMNS(D41:O41) -> 985.89167 | R41: 0.1
C42: 慈善（GIV） | D42: =$D$5*R42 -> 4225.25 | E42: =$D$5*SUMPRODUCT(K69:N69,$K$63:$N$63) -> 20281.2 | F42: =$D$5*T42 -> 0 | G42: =$D$5*U42 -> 0 | H42: =$D$5*V42 -> 0 | I42: =$D$5*W42 -> 0 | J42: =$D$5*X42 -> 0 | K42: =$D$5*Y42 -> 0 | L42: =$D$5*Z42 -> 0 | M42: =$D$5*AA42 -> 0 | ... O42: =$D$5*AC42 -> 0 | P42: =SUM(D42:O42) -> 24506.45 | Q42: =P42/COLUMNS(D42:O42) -> 2042.2042 | R42: 0.05
C43: 總 | D43: =SUM(D39:D42) -> 29576.75 | E43: =SUM(E39:E42) -> 54928.25 | F43: =SUM(F39:F42) -> 0 | G43: =SUM(G39:G42) -> 0 | H43: =SUM(H39:H42) -> 0 | I43: =SUM(I39:I42) -> 0 | J43: =SUM(J39:J42) -> 0 | K43: =SUM(K39:K42) -> 0 | ... O43: =SUM(O39:O42) -> 0 | P43: =SUM(D43:O43) -> 84505 | Q43: =P43/COLUMNS(D43:O43) -> 7042.0833 | R43: =SUM(R39:R42) -> 0.35
B44: 總 | D44: =SUM(D36:D42) -> 84505 | E44: =SUM(E36:E42) -> 84505 | F44: =SUM(F36:F42) -> 0 | G44: =SUM(G36:G42) -> 0 | H44: =SUM(H36:H42) -> 0 | I44: =SUM(I36:I42) -> 0 | J44: =SUM(J36:J42) -> 0 | K44: =SUM(K36:K42) -> 0 | ... R44: =SUM(R36:R42) -> 1
B46: 投資池分配 | D46: =D$4 -> 1 | E46: =E$4 -> 2 | F46: =F$4 -> 3 | G46: =G$4 -> 4 | H46: =H$4 -> 5 | I46: =I$4 -> 6 | J46: =J$4 -> 7 | K46: =K$4 -> 8 | ... O46: =O$4 -> 12 | P46: Total | Q46: Avg | R46: 資金占比
B47: 短期 | D47: =SUM(D$39:D$42)*$R47 -> 8873.025 | E47: =SUM(E$39:E$42)*$R47 -> 16478.475 | F47: =SUM(F$39:F$42)*$R47 -> 0 | G47: =SUM(G$39:G$42)*$R47 -> 0 | H47: =SUM(H$39:H$42)*$R47 -> 0 | I47: =SUM(I$39:I$42)*$R47 -> 0 | J47: =SUM(J$39:J$42)*$R47 -> 0 | K47: =SUM(K$39:K$42)*$R47 -> 0 | ... O47: =SUM(O$39:O$42)*$R47 -> 0 | P47: =SUM(D47:O47) -> 25351.5 | Q47: =P47/COLUMNS(D47:O47) -> 2112.625 | R47: 0.3
B48: 中期 | D48: =SUM(D$39:D$42)*$R48 -> 11830.7 | E48: =SUM(E$39:E$42)*$R48 -> 21971.3 | F48: =SUM(F$39:F$42)*$R48 -> 0 | G48: =SUM(G$39:G$42)*$R48 -> 0 | H48: =SUM(H$39:H$42)*$R48 -> 0 | I48: =SUM(I$39:I$42)*$R48 -> 0 | J48: =SUM(J$39:J$42)*$R48 -> 0 | K48: =SUM(K$39:K$42)*$R48 -> 0 | ... O48: =SUM(O$39:O$42)*$R48 -> 0 | P48: =SUM(D48:O48) -> 33802 | Q48: =P48/COLUMNS(D48:O48) -> 2816.8333 | R48: 0.4
B49: 長期 | D49: =SUM(D$39:D$42)*$R49 -> 8873.025 | E49: =SUM(E$39:E$42)*$R49 -> 16478.475 | F49: =SUM(F$39:F$42)*$R49 -> 0 | G49: =SUM(G$39:G$42)*$R49 -> 0 | H49: =SUM(H$39:H$42)*$R49 -> 0 | I49: =SUM(I$39:I$42)*$R49 -> 0 | J49: =SUM(J$39:J$42)*$R49 -> 0 | K49: =SUM(K$39:K$42)*$R49 -> 0 | ... O49: =SUM(O$39:O$42)*$R49 -> 0 | P49: =SUM(D49:O49) -> 25351.5 | Q49: =P49/COLUMNS(D49:O49) -> 2112.625 | R49: 0.3
B50: 總 | D50: =SUM(D47:D49) -> 29576.75 | E50: =SUM(E47:E49) -> 54928.25 | F50: =SUM(F47:F49) -> 0 | G50: =SUM(G47:G49) -> 0 | H50: =SUM(H47:H49) -> 0 | I50: =SUM(I47:I49) -> 0 | J50: =SUM(J47:J49) -> 0 | K50: =SUM(K47:K49) -> 0 | ... R50: =SUM(R47:R49) -> 1
B52: 投資池收入 | D52: =D$4 -> 1 | E52: =E$4 -> 2 | F52: =F$4 -> 3 | G52: =G$4 -> 4 | H52: =H$4 -> 5 | I52: =I$4 -> 6 | J52: =J$4 -> 7 | K52: =K$4 -> 8 | ... O52: =O$4 -> 12 | P52: Total | Q52: 預期報酬率
B53: 短期 | D53: 1000 | E53: 954 | F53: 1111 | P53: =SUM(D53:O53) -> 3065
B54: 中期 | D54: 2000 | E54: 1500 | P54: =SUM(D54:O54) -> 3500
B55: 長期 | D55: 1500 | E55: 1600 | P55: =SUM(D55:O55) -> 3100
B56: 總 | D56: =SUM(D53:D55) -> 4500 | E56: =SUM(E53:E55) -> 4054 | F56: =SUM(F53:F55) -> 1111 | G56: =SUM(G53:G55) -> 0 | H56: =SUM(H53:H55) -> 0 | I56: =SUM(I53:I55) -> 0 | J56: =SUM(J53:J55) -> 0 | K56: =SUM(K53:K55) -> 0 | ... Q56: =SUM(Q53:Q55) -> 0
B57: 累計 | D57: =D56 -> 4500 | E57: =SUM($D$56:E56) -> 8554 | F57: =SUM($D$56:F56) -> 9665 | G57: =SUM($D$56:G56) -> 9665 | H57: =SUM($D$56:H56) -> 9665 | I57: =SUM($D$56:I56) -> 9665 | J57: =SUM($D$56:J56) -> 9665 | K57: =SUM($D$56:K56) -> 9665 | L57: =SUM($D$56:L56) -> 9665 | ... O57: =SUM($D$56:O56) -> 9665 | Q57: =SUM(Q54:Q56) -> 0
B58: 總報酬率 | D58: =D56/(SUM($D$50:D50)) -> 0.15214653 | E58: =E56/(SUM($D$50:E50)) -> 0.047973493 | F58: =F56/(SUM($D$50:F50)) -> 0.013147151 | G58: =G56/(SUM($D$50:G50)) -> 0 | H58: =H56/(SUM($D$50:H50)) -> 0 | I58: =I56/(SUM($D$50:I50)) -> 0 | J58: =J56/(SUM($D$50:J50)) -> 0 | K58: =K56/(SUM($D$50:K50)) -> 0 | ... O58: =O56/(SUM($D$50:O50)) -> 0 | Q58: =SUM(Q55:Q58) -> 0
B59: 總累積報酬率 | D59: =D57/D50 -> 0.15214653 | E59: =E57/SUM($D$50:E50) -> 0.10122478 | F59: =F57/SUM($D$50:F50) -> 0.11437193 | G59: =G57/SUM($D$50:G50) -> 0.11437193 | H59: =H57/SUM($D$50:H50) -> 0.11437193 | I59: =I57/SUM($D$50:I50) -> 0.11437193 | J59: =J57/SUM($D$50:J50) -> 0.11437193 | K59: =K57/SUM($D$50:K50) -> 0.11437193 | L59: =L57/SUM($D$50:L50) -> 0.11437193 | ... O59: =O57/SUM($D$50:O50) -> 0.11437193 | Q59: =SUM(Q58:Q60) -> 0
B62: S&P → 六罐 映射 | C62: NEC | D62: FFA | E62: EDU | F62: PLY | G62: LTS | H62: GIV | K62: 要花 | L62: 保命 | M62: 生錢 | N62: 保本升值
J63: S&P | K63: 0.1 | L63: 0.2 | M63: 0.3 | N63: 0.4
B64: 要花 (10%) | C64: 1 | D64: 0 | E64: 0 | F64: 0 | G64: 0 | H64: 0 | J64: NEC | K64: 1 | L64: 0 | M64: 0 | N64: 0
B65: 保命 (20%) | C65: 0 | D65: 0 | E65: 0 | F65: 0 | G65: 0 | H65: 1 | J65: LTS | K65: 0 | L65: 0 | M65: 0.3 | N65: 0.4
B66: 生錢 (30%) | C66: 0 | D66: 0.7 | E66: 0 | F66: 0 | G66: 0.3 | H66: 0 | J66: FFA | K66: 0 | L66: 0 | M66: 0.7 | N66: 0.3
B67: 保本升值 (40%) | C67: 0 | D67: 0.3 | E67: 0.1 | F67: 0.1 | G67: 0.4 | H67: 0.1 | J67: EDU | K67: 0 | L67: 0 | M67: 0 | N67: 0.1
J68: PLY | K68: 0 | L68: 0 | M68: 0 | N68: 0.1
J69: GIV | K69: 0 | L69: 1 | M69: 0 | N69: 0.1

Sheet 支出規劃
B2: 預算規劃
B4: 概要 | D4: 1 | E4: 2 | F4: 3 | G4: 4 | H4: 5 | I4: 6 | J4: 7 | K4: 8 | L4: 9 | M4: 10 | N4: 11 | O4: 12 | P4: Total | Q4: Avg
B5: 總收入 | D5: =收入規劃!D5 -> 84505 | E5: =收入規劃!E5 -> 0 | F5: =收入規劃!F5 -> 0 | G5: =收入規劃!G5 -> 0 | H5: =收入規劃!H5 -> 0 | I5: =收入規劃!I5 -> 0 | J5: =收入規劃!J5 -> 0 | K5: =收入規劃!K5 -> 0 | ... O5: =收入規劃!O5 -> 0 | P5: =SUM(D5:O5) -> 84505 | Q5: =P5/COLUMNS(D5:O5) -> 7042.0833
B6: 總支出 | D6: =D10+D16+D23+D35+D69+D92+D101+D53+D77+D110+D118+D45+D62+D130 -> 0 | E6: =E10+E16+E23+E35+E69+E92+E101+E53+E77+E110+E118+E45+E62+E130 -> 0 | F6: =F10+F16+F23+F35+F69+F92+F101+F53+F77+F110+F118+F45+F62+F130 -> 0 | G6: =G10+G16+G23+G35+G69+G92+G101+G53+G77+G110+G118+G45+G62+G130 -> 0 | H6: =H10+H16+H23+H35+H69+H92+H101+H53+H77+H110+H118+H45+H62+H130 -> 0 | I6: =I10+I16+I23+I35+I69+I92+I101+I53+I77+I110+I118+I45+I62+I130 -> 0 | J6: =J10+J16+J23+J35+J69+J92+J101+J53+J77+J110+J118+J45+J62+J130 -> 0 | K6: =K10+K16+K23+K35+K69+K92+K101+K53+K77+K110+K118+K45+K62+K130 -> 0 | ... O6: =O10+O16+O23+O35+O69+O92+O101+O53+O77+O110+O118+O45+O62+O130 -> 0 | P6: =SUM(D6:O6) -> 0 | Q6: =P6/COLUMNS(D6:O6) -> 0
B7: 淨額 | D7: =D5-D6 -> 84505 | E7: =E5-E6 -> 0 | F7: =F5-F6 -> 0 | G7: =G5-G6 -> 0 | H7: =H5-H6 -> 0 | I7: =I5-I6 -> 0 | J7: =J5-J6 -> 0 | K7: =K5-K6 -> 0 | ... O7: =O5-O6 -> 0 | P7: =SUM(D7:O7) -> 84505 | Q7: =P7/COLUMNS(D7:O7) -> 7042.0833
B9: 食 | D9: =D$4 -> 1 | E9: =E$4 -> 2 | F9: =F$4 -> 3 | G9: =G$4 -> 4 | H9: =H$4 -> 5 | I9: =I$4 -> 6 | J9: =J$4 -> 7 | K9: =K$4 -> 8 | ... O9: =O$4 -> 12 | P9: Total | Q9: Avg
B10: 總 | D10: =SUM(D11:D12) -> 0 | E10: =SUM(E11:E12) -> 0 | F10: =SUM(F11:F12) -> 0 | G10: =SUM(G11:G12) -> 0 | H10: =SUM(H11:H12) -> 0 | I10: =SUM(I11:I12) -> 0 | J10: =SUM(J11:J12) -> 0 | K10: =SUM(K11:K12) -> 0 | ... Q10: =SUM(Q11:Q12) -> 0
B11: 外食 | P11: =SUM(D11:O11) -> 0 | Q11: =P11/COLUMNS(D11:O11) -> 0
B12: 食材
B13: 佔總支出百分比 | D13: =IF(D$6=0," - ",D10/D$6) -> - | E13: =IF(E$6=0," - ",E10/E$6) -> - | F13: =IF(F$6=0," - ",F10/F$6) -> - | G13: =IF(G$6=0," - ",G10/G$6) -> - | H13: =IF(H$6=0," - ",H10/H$6) -> - | I13: =IF(I$6=0," - ",I10/I$6) -> - | J13: =IF(J$6=0," - ",J10/J$6) -> - | K13: =IF(K$6=0," - ",K10/K$6) -> - | ... Q13: =IF(Q$6=0," - ",Q10/Q$6) -> -
B15: 衣 | D15: =D$4 -> 1 | E15: =E$4 -> 2 | F15: =F$4 -> 3 | G15: =G$4 -> 4 | H15: =H$4 -> 5 | I15: =I$4 -> 6 | J15: =J$4 -> 7 | K15: =K$4 -> 8 | ... O15: =O$4 -> 12 | P15: Total | Q15: Avg
B16: 總 | D16: =SUM(D17:D19) -> 0 | E16: =SUM(E17:E19) -> 0 | F16: =SUM(F17:F19) -> 0 | G16: =SUM(G17:G19) -> 0 | H16: =SUM(H17:H19) -> 0 | I16: =SUM(I17:I19) -> 0 | J16: =SUM(J17:J19) -> 0 | K16: =SUM(K17:K19) -> 0 | ... Q16: =SUM(Q17:Q19) -> 0
B17: 治裝 | P17: =SUM(D17:O17) -> 0 | Q17: =P17/COLUMNS(D17:O17) -> 0
B18: 美容美髮 | P18: =SUM(D18:O18) -> 0 | Q18: =P18/COLUMNS(D18:O18) -> 0
B19: 衣物送洗 | P19: =SUM(D19:O19) -> 0 | Q19: =P19/COLUMNS(D19:O19) -> 0
B20: 佔總支出百分比 | D20: =IF(D$6=0," - ",D16/D$6) -> - | E20: =IF(E$6=0," - ",E16/E$6) -> - | F20: =IF(F$6=0," - ",F16/F$6) -> - | G20: =IF(G$6=0," - ",G16/G$6) -> - | H20: =IF(H$6=0," - ",H16/H$6) -> - | I20: =IF(I$6=0," - ",I16/I$6) -> - | J20: =IF(J$6=0," - ",J16/J$6) -> - | K20: =IF(K$6=0," - ",K16/K$6) -> - | ... Q20: =IF(Q$6=0," - ",Q16/Q$6) -> -
B22: 住 | D22: =D$4 -> 1 | E22: =E$4 -> 2 | F22: =F$4 -> 3 | G22: =G$4 -> 4 | H22: =H$4 -> 5 | I22: =I$4 -> 6 | J22: =J$4 -> 7 | K22: =K$4 -> 8 | ... O22: =O$4 -> 12 | P22: Total | Q22: Avg
B23: 總 | D23: =SUM(D24:D31) -> 0 | E23: =SUM(E24:E31) -> 0 | F23: =SUM(F24:F31) -> 0 | G23: =SUM(G24:G31) -> 0 | H23: =SUM(H24:H31) -> 0 | I23: =SUM(I24:I31) -> 0 | J23: =SUM(J24:J31) -> 0 | K23: =SUM(K24:K31) -> 0 | ... Q23: =SUM(Q24:Q31) -> 0
B24: 抵押貸款/租金 | P24: =SUM(D24:O24) -> 0 | Q24: =P24/COLUMNS(D24:O24) -> 0
B25: 電 | P25: =SUM(D25:O25) -> 0 | Q25: =P25/COLUMNS(D25:O25) -> 0
B26: 天然氣/瓦斯 | P26: =SUM(D26:O26) -> 0 | Q26: =P26/COLUMNS(D26:O26) -> 0
B27: 水 | P27: =SUM(D27:O27) -> 0 | Q27: =P27/COLUMNS(D27:O27) -> 0
B28: 有線/衛星/網路 | P28: =SUM(D28:O28) -> 0 | Q28: =P28/COLUMNS(D28:O28) -> 0
B29: 家具/家電 | P29: =SUM(D29:O29) -> 0 | Q29: =P29/COLUMNS(D29:O29) -> 0
B30: 家居用品 | P30: =SUM(D30:O30) -> 0 | Q30: =P30/COLUMNS(D30:O30) -> 0
B31: 其他 | P31: =SUM(D31:O31) -> 0 | Q31: =P31/COLUMNS(D31:O31) -> 0
B32: 佔總支出百分比 | D32: =IF(D$6=0," - ",D23/D$6) -> - | E32: =IF(E$6=0," - ",E23/E$6) -> - | F32: =IF(F$6=0," - ",F23/F$6) -> - | G32: =IF(G$6=0," - ",G23/G$6) -> - | H32: =IF(H$6=0," - ",H23/H$6) -> - | I32: =IF(I$6=0," - ",I23/I$6) -> - | J32: =IF(J$6=0," - ",J23/J$6) -> - | K32: =IF(K$6=0," - ",K23/K$6) -> - | ... Q32: =IF(Q$6=0," - ",Q23/Q$6) -> -
B34: 行 | D34: =D$4 -> 1 | E34: =E$4 -> 2 | F34: =F$4 -> 3 | G34: =G$4 -> 4 | H34: =H$4 -> 5 | I34: =I$4 -> 6 | J34: =J$4 -> 7 | K34: =K$4 -> 8 | ... O34: =O$4 -> 12 | P34: Total | Q34: Avg
B35: 總 | D35: =SUM(D36:D41) -> 0 | E35: =SUM(E36:E41) -> 0 | F35: =SUM(F36:F41) -> 0 | G35: =SUM(G36:G41) -> 0 | H35: =SUM(H36:H41) -> 0 | I35: =SUM(I36:I41) -> 0 | J35: =SUM(J36:J41) -> 0 | K35: =SUM(K36:K41) -> 0 | ... Q35: =SUM(Q36:Q41) -> 0
B36: 停車費 | P36: =SUM(D36:O36) -> 0 | Q36: =P36/COLUMNS(D36:O36) -> 0
B37: 加油費 | P37: =SUM(D37:O37) -> 0 | Q37: =P37/COLUMNS(D37:O37) -> 0
B38: 過路費 | P38: =SUM(D38:O38) -> 0 | Q38: =P38/COLUMNS(D38:O38) -> 0
B39: 保養 | P39: =SUM(D39:O39) -> 0 | Q39: =P39/COLUMNS(D39:O39) -> 0
B40: 大眾交通 | P40: =SUM(D40:O40) -> 0 | Q40: =P40/COLUMNS(D40:O40) -> 0
B41: 其他 | P41: =SUM(D41:O41) -> 0 | Q41: =P41/COLUMNS(D41:O41) -> 0
B42: 佔總支出百分比 | D42: =IF(D$6=0," - ",D35/D$6) -> - | E42: =IF(E$6=0," - ",E35/E$6) -> - | F42: =IF(F$6=0," - ",F35/F$6) -> - | G42: =IF(G$6=0," - ",G35/G$6) -> - | H42: =IF(H$6=0," - ",H35/H$6) -> - | I42: =IF(I$6=0," - ",I35/I$6) -> - | J42: =IF(J$6=0," - ",J35/J$6) -> - | K42: =IF(K$6=0," - ",K35/K$6) -> - | ... Q42: =IF(Q$6=0," - ",Q35/Q$6) -> -
B44: 政府規費 | D44: =D$4 -> 1 | E44: =E$4 -> 2 | F44: =F$4 -> 3 | G44: =G$4 -> 4 | H44: =H$4 -> 5 | I44: =I$4 -> 6 | J44: =J$4 -> 7 | K44: =K$4 -> 8 | ... O44: =O$4 -> 12 | P44: Total | Q44: Avg
B45: 總 | D45: =SUM(D46:D49) -> 0 | E45: =SUM(E46:E49) -> 0 | F45: =SUM(F46:F49) -> 0 | G45: =SUM(G46:G49) -> 0 | H45: =SUM(H46:H49) -> 0 | I45: =SUM(I46:I49) -> 0 | J45: =SUM(J46:J49) -> 0 | K45: =SUM(K46:K49) -> 0 | ... Q45: =SUM(Q46:Q49) -> 0
B46: 所得稅 | P46: =SUM(D46:O46) -> 0 | Q46: =P46/COLUMNS(D46:O46) -> 0
B47: 牌照稅 | P47: =SUM(D47:O47) -> 0 | Q47: =P47/COLUMNS(D47:O47) -> 0
B48: 燃料稅 | P48: =SUM(D48:O48) -> 0 | Q48: =P48/COLUMNS(D48:O48) -> 0
B49: 勞健保 | P49: =SUM(D49:O49) -> 0 | Q49: =P49/COLUMNS(D49:O49) -> 0
B50: 佔總支出百分比 | D50: =IF(D$6=0," - ",D45/D$6) -> - | E50: =IF(E$6=0," - ",E45/E$6) -> - | F50: =IF(F$6=0," - ",F45/F$6) -> - | G50: =IF(G$6=0," - ",G45/G$6) -> - | H50: =IF(H$6=0," - ",H45/H$6) -> - | I50: =IF(I$6=0," - ",I45/I$6) -> - | J50: =IF(J$6=0," - ",J45/J$6) -> - | K50: =IF(K$6=0," - ",K45/K$6) -> - | ... Q50: =IF(Q$6=0," - ",Q45/Q$6) -> -
B52: 負債 | D52: =D$4 -> 1 | E52: =E$4 -> 2 | F52: =F$4 -> 3 | G52: =G$4 -> 4 | H52: =H$4 -> 5 | I52: =I$4 -> 6 | J52: =J$4 -> 7 | K52: =K$4 -> 8 | ... O52: =O$4 -> 12 | P52: Total | Q52: Avg
B53: 總 | D53: =SUM(D54:D58) -> 0 | E53: =SUM(E54:E58) -> 0 | F53: =SUM(F54:F58) -> 0 | G53: =SUM(G54:G58) -> 0 | H53: =SUM(H54:H58) -> 0 | I53: =SUM(I54:I58) -> 0 | J53: =SUM(J54:J58) -> 0 | K53: =SUM(K54:K58) -> 0 | ... Q53: =SUM(Q54:Q58) -> 0
B54: 學費 | P54: =SUM(D54:O54) -> 0 | Q54: =P54/COLUMNS(D54:O54) -> 0
B55: 信用卡債務 | P55: =SUM(D55:O55) -> 0 | Q55: =P55/COLUMNS(D55:O55) -> 0
B56: 其他負債 | P56: =SUM(D56:O56) -> 0 | Q56: =P56/COLUMNS(D56:O56) -> 0
B57: 贍養費/子女扶養費 | P57: =SUM(D57:O57) -> 0 | Q57: =P57/COLUMNS(D57:O57) -> 0
B58: 稅 | P58: =SUM(D58:O58) -> 0 | Q58: =P58/COLUMNS(D58:O58) -> 0
B59: 佔總支出百分比 | D59: =IF(D$6=0," - ",D53/D$6) -> - | E59: =IF(E$6=0," - ",E53/E$6) -> - | F59: =IF(F$6=0," - ",F53/F$6) -> - | G59: =IF(G$6=0," - ",G53/G$6) -> - | H59: =IF(H$6=0," - ",H53/H$6) -> - | I59: =IF(I$6=0," - ",I53/I$6) -> - | J59: =IF(J$6=0," - ",J53/J$6) -> - | K59: =IF(K$6=0," - ",K53/K$6) -> - | ... Q59: =IF(Q$6=0," - ",Q53/Q$6) -> -
B61: 醫療 | D61: =D$4 -> 1 | E61: =E$4 -> 2 | F61: =F$4 -> 3 | G61: =G$4 -> 4 | H61: =H$4 -> 5 | I61: =I$4 -> 6 | J61: =J$4 -> 7 | K61: =K$4 -> 8 | ... O61: =O$4 -> 12 | P61: Total | Q61: Avg
B62: 總 | D62: =SUM(D63:D65) -> 0 | E62: =SUM(E63:E65) -> 0 | F62: =SUM(F63:F65) -> 0 | G62: =SUM(G63:G65) -> 0 | H62: =SUM(H63:H65) -> 0 | I62: =SUM(I63:I65) -> 0 | J62: =SUM(J63:J65) -> 0 | K62: =SUM(K63:K65) -> 0 | ... Q62: =SUM(Q63:Q65) -> 0
B63: 醫生 | P63: =SUM(D63:O63) -> 0 | Q63: =P63/COLUMNS(D63:O63) -> 0
B64: 藥物 | P64: =SUM(D64:O64) -> 0 | Q64: =P64/COLUMNS(D64:O64) -> 0
B65: 其他 | P65: =SUM(D65:O65) -> 0 | Q65: =P65/COLUMNS(D65:O65) -> 0
B66: 佔總支出百分比 | D66: =IF(D$6=0," - ",D62/D$6) -> - | E66: =IF(E$6=0," - ",E62/E$6) -> - | F66: =IF(F$6=0," - ",F62/F$6) -> - | G66: =IF(G$6=0," - ",G62/G$6) -> - | H66: =IF(H$6=0," - ",H62/H$6) -> - | I66: =IF(I$6=0," - ",I62/I$6) -> - | J66: =IF(J$6=0," - ",J62/J$6) -> - | K66: =IF(K$6=0," - ",K62/K$6) -> - | ... Q66: =IF(Q$6=0," - ",Q62/Q$6) -> -
B68: 育 | D68: =D$4 -> 1 | E68: =E$4 -> 2 | F68: =F$4 -> 3 | G68: =G$4 -> 4 | H68: =H$4 -> 5 | I68: =I$4 -> 6 | J68: =J$4 -> 7 | K68: =K$4 -> 8 | ... O68: =O$4 -> 12 | P68: Total | Q68: Avg
B69: 總 | D69: =SUM(D70:D73) -> 0 | E69: =SUM(E70:E73) -> 0 | F69: =SUM(F70:F73) -> 0 | G69: =SUM(G70:G73) -> 0 | H69: =SUM(H70:H73) -> 0 | I69: =SUM(I70:I73) -> 0 | J69: =SUM(J70:J73) -> 0 | K69: =SUM(K70:K73) -> 0 | ... Q69: =SUM(Q70:Q73) -> 0
B70: 學費 | P70: =SUM(D70:O70) -> 0 | Q70: =P70/COLUMNS(D70:O70) -> 0
B71: 書籍 | P71: =SUM(D71:O71) -> 0 | Q71: =P71/COLUMNS(D71:O71) -> 0
B72: 課程 | P72: =SUM(D72:O72) -> 0 | Q72: =P72/COLUMNS(D72:O72) -> 0
B73: 其他 | P73: =SUM(D73:O73) -> 0 | Q73: =P73/COLUMNS(D73:O73) -> 0
B74: 佔總支出百分比 | D74: =IF(D$6=0," - ",D69/D$6) -> - | E74: =IF(E$6=0," - ",E69/E$6) -> - | F74: =IF(F$6=0," - ",F69/F$6) -> - | G74: =IF(G$6=0," - ",G69/G$6) -> - | H74: =IF(H$6=0," - ",H69/H$6) -> - | I74: =IF(I$6=0," - ",I69/I$6) -> - | J74: =IF(J$6=0," - ",J69/J$6) -> - | K74: =IF(K$6=0," - ",K69/K$6) -> - | ... Q74: =IF(Q$6=0," - ",Q69/Q$6) -> -
B76: 樂 | D76: =D$4 -> 1 | E76: =E$4 -> 2 | F76: =F$4 -> 3 | G76: =G$4 -> 4 | H76: =H$4 -> 5 | I76: =I$4 -> 6 | J76: =J$4 -> 7 | K76: =K$4 -> 8 | ... O76: =O$4 -> 12 | P76: Total | Q76: Avg
B77: 總 | D77: =SUM(D78:D88) -> 0 | E77: =SUM(E78:E88) -> 0 | F77: =SUM(F78:F88) -> 0 | G77: =SUM(G78:G88) -> 0 | H77: =SUM(H78:H88) -> 0 | I77: =SUM(I78:I88) -> 0 | J77: =SUM(J78:J88) -> 0 | K77: =SUM(K78:K88) -> 0 | ... Q77: =SUM(Q78:Q88) -> 0
B78: 活動 | P78: =SUM(D78:O78) -> 0 | Q78: =P78/COLUMNS(D78:O78) -> 0
B79: 書籍 | P79: =SUM(D79:O79) -> 0 | Q79: =P79/COLUMNS(D79:O79) -> 0
B80: 遊戲 | P80: =SUM(D80:O80) -> 0 | Q80: =P80/COLUMNS(D80:O80) -> 0
B81: 趣味用品 | P81: =SUM(D81:O81) -> 0 | Q81: =P81/COLUMNS(D81:O81) -> 0
B82: 嗜好 | P82: =SUM(D82:O82) -> 0 | Q82: =P82/COLUMNS(D82:O82) -> 0
B83: 媒體 | P83: =SUM(D83:O83) -> 0 | Q83: =P83/COLUMNS(D83:O83) -> 0
B84: 戶外娛樂 | P84: =SUM(D84:O84) -> 0 | Q84: =P84/COLUMNS(D84:O84) -> 0
B85: 運動 | P85: =SUM(D85:O85) -> 0 | Q85: =P85/COLUMNS(D85:O85) -> 0
B86: 玩具/小工具 | P86: =SUM(D86:O86) -> 0 | Q86: =P86/COLUMNS(D86:O86) -> 0
B87: 假期/旅行 | P87: =SUM(D87:O87) -> 0 | Q87: =P87/COLUMNS(D87:O87) -> 0
B88: 其他 | P88: =SUM(D88:O88) -> 0 | Q88: =P88/COLUMNS(D88:O88) -> 0
B89: 佔總支出百分比 | D89: =IF(D$6=0," - ",D77/D$6) -> - | E89: =IF(E$6=0," - ",E77/E$6) -> - | F89: =IF(F$6=0," - ",F77/F$6) -> - | G89: =IF(G$6=0," - ",G77/G$6) -> - | H89: =IF(H$6=0," - ",H77/H$6) -> - | I89: =IF(I$6=0," - ",I77/I$6) -> - | J89: =IF(J$6=0," - ",J77/J$6) -> - | K89: =IF(K$6=0," - ",K77/K$6) -> - | ... Q89: =IF(Q$6=0," - ",Q77/Q$6) -> -
B91: 保險 | D91: =D$4 -> 1 | E91: =E$4 -> 2 | F91: =F$4 -> 3 | G91: =G$4 -> 4 | H91: =H$4 -> 5 | I91: =I$4 -> 6 | J91: =J$4 -> 7 | K91: =K$4 -> 8 | ... O91: =O$4 -> 12 | P91: Total | Q91: Avg
B92: 總 | D92: =SUM(D93:D96) -> 0 | E92: =SUM(E93:E96) -> 0 | F92: =SUM(F93:F96) -> 0 | G92: =SUM(G93:G96) -> 0 | H92: =SUM(H93:H96) -> 0 | I92: =SUM(I93:I96) -> 0 | J92: =SUM(J93:J96) -> 0 | K92: =SUM(K93:K96) -> 0 | ... Q92: =SUM(Q93:Q96) -> 0
B93: 車輛 | P93: =SUM(D93:O93) -> 0 | Q93: =P93/COLUMNS(D93:O93) -> 0
B94: 健康 | P94: =SUM(D94:O94) -> 0 | Q94: =P94/COLUMNS(D94:O94) -> 0
B95: 住家/租賃 | P95: =SUM(D95:O95) -> 0 | Q95: =P95/COLUMNS(D95:O95) -> 0
B96: 其他 | P96: =SUM(D96:O96) -> 0 | Q96: =P96/COLUMNS(D96:O96) -> 0
B97: 佔總支出百分比 | D97: =IF(D$6=0," - ",D92/D$6) -> - | E97: =IF(E$6=0," - ",E92/E$6) -> - | F97: =IF(F$6=0," - ",F92/F$6) -> - | G97: =IF(G$6=0," - ",G92/G$6) -> - | H97: =IF(H$6=0," - ",H92/H$6) -> - | I97: =IF(I$6=0," - ",I92/I$6) -> - | J97: =IF(J$6=0," - ",J92/J$6) -> - | K97: =IF(K$6=0," - ",K92/K$6) -> - | ... Q97: =IF(Q$6=0," - ",Q92/Q$6) -> -
B100: 給予 | D100: =D$4 -> 1 | E100: =E$4 -> 2 | F100: =F$4 -> 3 | G100: =G$4 -> 4 | H100: =H$4 -> 5 | I100: =I$4 -> 6 | J100: =J$4 -> 7 | K100: =K$4 -> 8 | ... O100: =O$4 -> 12 | P100: Total | Q100: Avg
B101: 總 | D101: =SUM(D102:D106) -> 0 | E101: =SUM(E102:E106) -> 0 | F101: =SUM(F102:F106) -> 0 | G101: =SUM(G102:G106) -> 0 | H101: =SUM(H102:H106) -> 0 | I101: =SUM(I102:I106) -> 0 | J101: =SUM(J102:J106) -> 0 | K101: =SUM(K102:K106) -> 0 | ... Q101: =SUM(Q102:Q106) -> 0
B102: 贈送的禮物 | P102: =SUM(D102:O102) -> 0 | Q102: =P102/COLUMNS(D102:O102) -> 0
B103: 慈善捐款 | P103: =SUM(D103:O103) -> 0 | Q103: =P103/COLUMNS(D103:O103) -> 0
B104: 紅白包 | P104: =SUM(D104:O104) -> 0 | Q104: =P104/COLUMNS(D104:O104) -> 0
B105: 孝親
B106: 其他 | P106: =SUM(D106:O106) -> 0 | Q106: =P106/COLUMNS(D106:O106) -> 0
B107: 佔總支出百分比 | D107: =IF(D$6=0," - ",D101/D$6) -> - | E107: =IF(E$6=0," - ",E101/E$6) -> - | F107: =IF(F$6=0," - ",F101/F$6) -> - | G107: =IF(G$6=0," - ",G101/G$6) -> - | H107: =IF(H$6=0," - ",H101/H$6) -> - | I107: =IF(I$6=0," - ",I101/I$6) -> - | J107: =IF(J$6=0," - ",J101/J$6) -> - | K107: =IF(K$6=0," - ",K101/K$6) -> - | ... Q107: =IF(Q$6=0," - ",Q101/Q$6) -> -
B109: 寵物 | D109: =D$4 -> 1 | E109: =E$4 -> 2 | F109: =F$4 -> 3 | G109: =G$4 -> 4 | H109: =H$4 -> 5 | I109: =I$4 -> 6 | J109: =J$4 -> 7 | K109: =K$4 -> 8 | ... O109: =O$4 -> 12 | P109: Total | Q109: Avg
B110: 總 | D110: =SUM(D111:D114) -> 0 | E110: =SUM(E111:E114) -> 0 | F110: =SUM(F111:F114) -> 0 | G110: =SUM(G111:G114) -> 0 | H110: =SUM(H111:H114) -> 0 | I110: =SUM(I111:I114) -> 0 | J110: =SUM(J111:J114) -> 0 | K110: =SUM(K111:K114) -> 0 | ... Q110: =SUM(Q111:Q114) -> 0
B111: 食物 | P111: =SUM(D111:O111) -> 0 | Q111: =P111/COLUMNS(D111:O111) -> 0
B112: 醫療 | P112: =SUM(D112:O112) -> 0 | Q112: =P112/COLUMNS(D112:O112) -> 0
B113: 玩具 | P113: =SUM(D113:O113) -> 0 | Q113: =P113/COLUMNS(D113:O113) -> 0
B114: 用品 | P114: =SUM(D114:O114) -> 0 | Q114: =P114/COLUMNS(D114:O114) -> 0
B115: 佔總支出百分比 | D115: =IF(D$6=0," - ",D110/D$6) -> - | E115: =IF(E$6=0," - ",E110/E$6) -> - | F115: =IF(F$6=0," - ",F110/F$6) -> - | G115: =IF(G$6=0," - ",G110/G$6) -> - | H115: =IF(H$6=0," - ",H110/H$6) -> - | I115: =IF(I$6=0," - ",I110/I$6) -> - | J115: =IF(J$6=0," - ",J110/J$6) -> - | K115: =IF(K$6=0," - ",K110/K$6) -> - | ... Q115: =IF(Q$6=0," - ",Q110/Q$6) -> -
...

Sheet 記帳區
A1: 帳戶 | B1: 幣種 | C1: 記錄類型 | D1: 主類別 | E1: 子類別 | F1: 金額 | G1: 手續費 | H1: 折扣 | I1: 名稱 | J1: 商家 | K1: 日期 | L1: 時間 | M1: 專案 | N1: 描述 | O1: 標籤 | P1: 對象
A2: 錢包 | B2: TWD | C2: 收入 | D2: 工資收入 | E2: 薪資 | F2: 71244 | G2: 0 | H2: 0 | K2: 45839 | L2: 0.775
A3: 錢包 | B3: TWD | C3: 支出 | D3: 理財支出 | E3: 活期存款 | F3: -10000 | G3: 0 | H3: 0 | K3: 45839 | L3: 0.775
A4: 錢包 | B4: TWD | C4: 支出 | D4: 食 | E4: 外食 | F4: -250 | G4: 0 | H4: 0 | K4: 45841 | L4: 0.62430556 | M4: 生活開銷
A5: 錢包 | B5: TWD | C5: 支出 | D5: 貸款 | E5: 功能性債務 | F5: -6000 | G5: 0 | H5: 0 | K5: 45842 | L5: 0.45625 | M5: 生活開銷
A6: 錢包 | B6: TWD | C6: 支出 | D6: 貸款 | E6: 功能性債務 | F6: -3000 | G6: 0 | H6: 0 | K6: 45843 | L6: 0.41458333 | M6: 生活開銷
A7: 錢包 | B7: TWD | C7: 支出 | D7: 行 | E7: 加油費 | F7: -1340 | G7: 0 | H7: 0 | K7: 45844 | L7: 0.62222222 | M7: 生活開銷
A8: 錢包 | B8: TWD | C8: 支出 | D8: 貸款 | E8: 壓榨性債務 | F8: -5177 | G8: 0 | H8: 0 | K8: 45845 | L8: 0.25763889
A9: 錢包 | B9: TWD | C9: 支出 | D9: 貸款 | E9: 壓榨性債務 | F9: -29911 | G9: 0 | H9: 0 | K9: 45846 | L9: 0.775
A10: 錢包 | B10: TWD | C10: 支出 | D10: 貸款 | E10: 壓榨性債務 | F10: -1456 | G10: 0 | H10: 0 | K10: 45847 | L10: 0.13611111 | M10: 生活開銷
A11: 錢包 | B11: TWD | C11: 支出 | D11: 貸款 | E11: 壓榨性債務 | F11: -2937 | G11: 0 | H11: 0 | K11: 45848 | L11: 0.25763889 | M11: 生活開銷
A12: 錢包 | B12: TWD | C12: 支出 | D12: 貸款 | E12: 壓榨性債務 | F12: -7800 | G12: 0 | H12: 0 | K12: 45849 | L12: 0.13680556 | M12: 生活開銷
A13: 錢包 | B13: TWD | C13: 支出 | D13: 貸款 | E13: 壓榨性債務 | F13: -23128 | G13: 0 | H13: 0 | K13: 45850 | L13: 0.64375 | M13: 生活開銷
A14: 錢包 | B14: TWD | C14: 支出 | D14: 貸款 | E14: 壓榨性債務 | F14: -7260 | G14: 0 | H14: 0 | K14: 45851 | L14: 0.41944444 | M14: 生活開銷
A15: 錢包 | B15: TWD | C15: 支出 | D15: 住 | E15: 日常用品 | F15: -130 | G15: 0 | H15: 0 | I15: 名片冊 | K15: 45852 | L15: 0.55833333 | M15: 生活開銷
A16: 錢包 | B16: TWD | C16: 支出 | D16: 食 | E16: 食材 | F16: -50 | G16: 0 | H16: 0 | K16: 45853 | L16: 0.55902778 | M16: 生活開銷
A17: 錢包 | B17: TWD | C17: 支出 | D17: 行 | E17: 火車 | F17: -1190 | G17: 0 | H17: 0 | K17: 45854 | L17: 0.13888889 | M17: 生活開銷
A18: 錢包 | B18: TWD | C18: 支出 | D18: 食 | E18: 食材 | F18: -124 | G18: 0 | H18: 0 | K18: 45855 | L18: 0.13680556 | M18: 生活開銷
A19: 錢包 | B19: TWD | C19: 收入 | D19: 工資收入 | E19: 加班費 | F19: 15000 | G19: 0 | H19: 0 | K19: 45866 | L19: 0.13819444 | M19: 生活開銷
A20: 錢包 | B20: TWD | C20: 收入 | D20: 工資收入 | E20: 薪資 | F20: 71244 | G20: 0 | H20: 0 | K20: 45870 | L20: 0.775
A21: 錢包 | B21: TWD | C21: 支出 | D21: 貸款 | E21: 功能性債務 | F21: -6000 | G21: 0 | H21: 0 | K21: 45871 | L21: 0.13611111 | M21: 生活開銷
A22: 錢包 | B22: TWD | C22: 支出 | D22: 貸款 | E22: 功能性債務 | F22: -3000 | G22: 0 | H22: 0 | K22: 45872 | L22: 0.13680556 | M22: 生活開銷
A23: 錢包 | B23: TWD | C23: 支出 | D23: 貸款 | E23: 壓榨性債務 | F23: -5177 | G23: 0 | H23: 0 | K23: 45873 | L23: 0.70902778 | M23: 生活開銷
A24: 錢包 | B24: TWD | C24: 支出 | D24: 貸款 | E24: 壓榨性債務 | F24: -29911 | G24: 0 | H24: 0 | K24: 45874 | L24: 0.71180556 | M24: 生活開銷
A25: 錢包 | B25: TWD | C25: 支出 | D25: 貸款 | E25: 壓榨性債務 | F25: -1456 | G25: 0 | H25: 0 | K25: 45875 | L25: 0.46527778 | M25: 生活開銷
A26: 錢包 | B26: TWD | C26: 支出 | D26: 貸款 | E26: 壓榨性債務 | F26: -2937 | G26: 0 | H26: 0 | K26: 45876 | L26: 0.71041667 | M26: 生活開銷
A27: 錢包 | B27: TWD | C27: 支出 | D27: 貸款 | E27: 壓榨性債務 | F27: -7800 | G27: 0 | H27: 0 | K27: 45877 | L27: 0.71041667 | M27: 生活開銷
A28: 錢包 | B28: TWD | C28: 支出 | D28: 貸款 | E28: 壓榨性債務 | F28: -23128 | G28: 0 | H28: 0 | K28: 45878 | L28: 0.775
A29: 錢包 | B29: TWD | C29: 收入 | D29: 人情 | E29: 借款 | F29: 20000 | G29: 0 | H29: 0 | K29: 45879 | L29: 0.39166667 | M29: 生活開銷
A30: 錢包 | B30: TWD | C30: 支出 | D30: 貸款 | E30: 壓榨性債務 | F30: -7260 | G30: 0 | H30: 0 | K30: 45880 | L30: 0.43333333 | M30: 生活開銷
A31: 錢包 | B31: TWD | C31: 支出 | D31: 投資 | E31: 外匯 | F31: -20000 | G31: 0 | H31: 0 | K31: 45880 | L31: 0.39583333
A32: 錢包 | B32: TWD | C32: 支出 | D32: 食 | E32: 外食 | F32: -45 | G32: 0 | H32: 0 | K32: 45881 | L32: 0.56041667 | M32: 生活開銷
A33: 錢包 | B33: TWD | C33: 支出 | D33: 食 | E33: 外食 | F33: -349 | G33: 0 | H33: 0 | K33: 45882 | L33: 0.74513889 | M33: 生活開銷
A34: 錢包 | B34: TWD | C34: 支出 | D34: 醫療 | E34: 醫療保健 | F34: -1450 | G34: 0 | H34: 0 | K34: 45883 | L34: 0.39444444 | M34: 生活開銷
A35: 錢包 | B35: TWD | C35: 支出 | D35: 食 | E35: 外食 | F35: -114 | G35: 0 | H35: 0 | K35: 45884 | L35: 0.29652778 | M35: 生活開銷
A36: 錢包 | B36: TWD | C36: 收入 | D36: 工資收入 | E36: 加班費 | F36: 15000 | G36: 0 | H36: 0 | K36: 45885 | L36: 0.29652778 | M36: 生活開銷
A37: 錢包 | B37: TWD | C37: 收入 | D37: 工資收入 | E37: 薪資 | F37: 71244 | G37: 0 | H37: 0 | K37: 45536 | L37: 0.4625 | M37: 生活開銷
A38: 錢包 | B38: TWD | C38: 支出 | D38: 貸款 | E38: 功能性債務 | F38: -6000 | G38: 0 | H38: 0 | K38: 45537 | L38: 0.46319444 | M38: 生活開銷
A39: 錢包 | B39: TWD | C39: 支出 | D39: 貸款 | E39: 功能性債務 | F39: -3000 | G39: 0 | H39: 0 | K39: 45538 | L39: 0.13611111 | M39: 生活開銷
A40: 錢包 | B40: TWD | C40: 支出 | D40: 貸款 | E40: 壓榨性債務 | F40: -5177 | G40: 0 | H40: 0 | K40: 45539 | L40: 0.13680556 | M40: 生活開銷
A41: 錢包 | B41: TWD | C41: 支出 | D41: 貸款 | E41: 壓榨性債務 | F41: -29911 | G41: 0 | H41: 0 | K41: 45540 | L41: 0.70902778 | M41: 生活開銷
A42: 錢包 | B42: TWD | C42: 支出 | D42: 貸款 | E42: 壓榨性債務 | F42: -1456 | G42: 0 | H42: 0 | K42: 45541 | L42: 0.71180556 | M42: 生活開銷
A43: 錢包 | B43: TWD | C43: 支出 | D43: 貸款 | E43: 壓榨性債務 | F43: -2937 | G43: 0 | H43: 0 | K43: 45542 | L43: 0.46527778 | M43: 生活開銷
... A46: 錢包 | B46: TWD | C46: 支出 | D46: 貸款 | E46: 壓榨性債務 | F46: -7260 | G46: 0 | H46: 0 | K46: 45545 | L46: 0.46319444 | M46: 生活開銷

Sheet 資產負債表
B2: 資產 | J2: 總值 | K2: =流動性資產[[#Totals],[價值]]+流動性投資[[#Totals],[價值]]+非流動性投資[[#Totals],[價值]]+自用不動產[[#Totals],[價值]]+其他資產[[#Totals],[價值]]+M19 -> 140000 | P2: 資產結構
B3: 流動性資產 | C3: 價值 | D3: 佔比 | F3: 流動性投資 | G3: 價值 | H3: 佔比 | J3: 其他資產 | K3: 價值 | L3: 佔比 | P3: 日常消費(10%) | Q3: =C4+C5 -> 10000
B4: 活期存款 | C4: =-SUMIFS(記帳區!$F:$F,記帳區!$E:$E,$B4) -> 10000 | D4: =IFERROR(流動性資產[[#This Row],[價值]]/流動性資產[[#Totals],[價值]],0) -> 1 | F4: 期貨 | G4: =-SUMIFS(記帳區!$F:$F,記帳區!$E:$E,$F4) -> 0 | H4: =IFERROR(流動性投資[[#This Row],[價值]]/流動性投資[[#Totals],[價值]],0) -> 0 | J4: 車輛 | K4: 110000 | L4: =IFERROR(其他資產[[#This Row],[價值]]/其他資產[[#Totals],[價值]],0) -> 1 | P4: 活期存款
B5: 儲蓄存款 | C5: =-SUMIFS(記帳區!$F:$F,記帳區!$E:$E,$B5) -> 0 | D5: =IFERROR(流動性資產[[#This Row],[價值]]/流動性資產[[#Totals],[價值]],0) -> 0 | F5: 外匯 | G5: =-SUMIFS(記帳區!$F:$F,記帳區!$E:$E,$F5) -> 20000 | H5: =IFERROR(流動性投資[[#This Row],[價值]]/流動性投資[[#Totals],[價值]],0) -> 1 | J5: 黃金 | K5: 0 | L5: =IFERROR(其他資產[[#This Row],[價值]]/其他資產[[#Totals],[價值]],0) -> 0 | P5: 儲蓄存款
B6: 壽險 | C6: =-SUMIFS(記帳區!$F:$F,記帳區!$E:$E,$B6) -> 0 | D6: =IFERROR(流動性資產[[#This Row],[價值]]/流動性資產[[#Totals],[價值]],0) -> 0 | F6: 基金 | G6: =-SUMIFS(記帳區!$F:$F,記帳區!$E:$E,$F6) -> 0 | H6: =IFERROR(流動性投資[[#This Row],[價值]]/流動性投資[[#Totals],[價值]],0) -> 0 | J6: 收藏品 | K6: 0 | L6: =IFERROR(其他資產[[#This Row],[價值]]/其他資產[[#Totals],[價值]],0) -> 0 | P6: 保障帳戶(20％) | Q6: =C6++C7+C8+K8 -> 0
B7: 銀行定存 | C7: =-SUMIFS(記帳區!$F:$F,記帳區!$E:$E,$B7) -> 0 | D7: =IFERROR(流動性資產[[#This Row],[價值]]/流動性資產[[#Totals],[價值]],0) -> 0 | F7: 債券 | G7: =-SUMIFS(記帳區!$F:$F,記帳區!$E:$E,$F7) -> 0 | H7: =IFERROR(流動性投資[[#This Row],[價值]]/流動性投資[[#Totals],[價值]],0) -> 0 | J7: 珠寶 | K7: 0 | L7: =IFERROR(其他資產[[#This Row],[價值]]/其他資產[[#Totals],[價值]],0) -> 0 | P7: 壽險
B8: 儲蓄險 | C8: =-SUMIFS(記帳區!$F:$F,記帳區!$E:$E,$B8) -> 0 | D8: =IFERROR(流動性資產[[#This Row],[價值]]/流動性資產[[#Totals],[價值]],0) -> 0 | F8: 股票 | G8: =-SUMIFS(記帳區!$F:$F,記帳區!$E:$E,$F8) -> 0 | H8: =IFERROR(流動性投資[[#This Row],[價值]]/流動性投資[[#Totals],[價值]],0) -> 0 | J8: 保險 | K8: 0 | L8: =IFERROR(其他資產[[#This Row],[價值]]/其他資產[[#Totals],[價值]],0) -> 0 | P8: 銀行定存
B9: 其他 | C9: =-SUMIFS(記帳區!$F:$F,記帳區!$E:$E,$B9) -> 0 | D9: =IFERROR(流動性資產[[#This Row],[價值]]/流動性資產[[#Totals],[價值]],0) -> 0 | F9: 其他 | G9: =-SUMIFS(記帳區!$F:$F,記帳區!$E:$E,$F9) -> 0 | H9: =IFERROR(流動性投資[[#This Row],[價值]]/流動性投資[[#Totals],[價值]],0) -> 0 | J9: 其他 | K9: 0 | L9: =IFERROR(其他資產[[#This Row],[價值]]/其他資產[[#Totals],[價值]],0) -> 0 | P9: 儲蓄險
B10: 合計 | C10: =SUBTOTAL(109,[價值]) -> 10000 | F10: 合計 | G10: =SUBTOTAL(109,[價值]) -> 20000 | J10: 合計 | K10: =SUBTOTAL(109,[價值]) -> 110000
P12: 保險
B13: 自用不動產 | C13: 價值 | D13: 佔比 | F13: 非流動性投資 | G13: 價值 | H13: 佔比 | J13: 升息資產 | K13: 價值 | L13: 佔比 | P13: 投資收益帳戶(30%) | Q13: =G4+G5 -> 20000
B14: 住宅 | C14: 0 | D14: =IFERROR(自用不動產[[#This Row],[價值]]/自用不動產[[#Totals],[價值]],0) -> 0 | F14: 事業股份 | G14: 0 | H14: =IFERROR(非流動性投資[[#This Row],[價值]]/非流動性投資[[#Totals],[價值]],0) -> 0 | J14: 存貨 | K14: 0 | L14: =IFERROR(升息資產[[#This Row],[價值]]/升息資產[[#Totals],[價值]],0) -> 0 | P14: 外匯
B15: 辦公室 | C15: 0 | D15: =IFERROR(自用不動產[[#This Row],[價值]]/自用不動產[[#Totals],[價值]],0) -> 0 | F15: 投資不動產 | G15: 0 | H15: =IFERROR(非流動性投資[[#This Row],[價值]]/非流動性投資[[#Totals],[價值]],0) -> 0 | J15: 其他 | K15: 0 | L15: =IFERROR(升息資產[[#This Row],[價值]]/升息資產[[#Totals],[價值]],0) -> 0 | P15: 期貨
B16: 工廠 | C16: 0 | D16: =IFERROR(自用不動產[[#This Row],[價值]]/自用不動產[[#Totals],[價值]],0) -> 0 | F16: 股票(未上市) | G16: 0 | H16: =IFERROR(非流動性投資[[#This Row],[價值]]/非流動性投資[[#Totals],[價值]],0) -> 0 | L16: =IFERROR(升息資產[[#This Row],[價值]]/升息資產[[#Totals],[價值]],0) -> 0 | P16: 長期收益帳戶(40%) | Q16: =G6+G7+G8+G14+G15 -> 0
B17: 其他 | C17: 0 | D17: =IFERROR(自用不動產[[#This Row],[價值]]/自用不動產[[#Totals],[價值]],0) -> 0 | F17: 其他 | G17: 0 | H17: =IFERROR(非流動性投資[[#This Row],[價值]]/非流動性投資[[#Totals],[價值]],0) -> 0 | L17: =IFERROR(升息資產[[#This Row],[價值]]/升息資產[[#Totals],[價值]],0) -> 0 | P17: 股票
C18: 0 | D18: =IFERROR(自用不動產[[#This Row],[價值]]/自用不動產[[#Totals],[價值]],0) -> 0 | H18: =IFERROR(非流動性投資[[#This Row],[價值]]/非流動性投資[[#Totals],[價值]],0) -> 0 | L18: =IFERROR(升息資產[[#This Row],[價值]]/升息資產[[#Totals],[價值]],0) -> 0 | P18: 基金
B19: 合計 | C19: =SUBTOTAL(109,[價值]) -> 0 | F19: 合計 | G19: =SUBTOTAL(109,[價值]) -> 0 | J19: 合計 | K19: =SUBTOTAL(109,[價值]) -> 0 | P19: 債券
P20: 事業股份
B21: 負債 | J21: 總值 | K21: =壓榨性債務[[#Totals],[價值]]+功能性債務[[#Totals],[價值]] -> 3435680 | P21: 投資不動產
B22: 壓榨性債務 | C22: 價值 | D22: 佔比 | E22: 月繳 | F22: 到期日 | J22: 功能性債務 | K22: 價值 | L22: 佔比
B23: 聯邦信用卡(16.07%) | C23: 72230 | D23: =IFERROR(壓榨性債務[[#This Row],[價值]]/壓榨性債務[[#Totals],[價值]],0) -> 0.021023495 | E23: 6000 | J23: 車貸 | K23: 0 | L23: =IFERROR(功能性債務[[#This Row],[價值]]/功能性債務[[#Totals],[價值]],0) -> 0 | R23: 理想值
B24: 星展信用卡(15.89%) | C24: 7887 | D24: =IFERROR(壓榨性債務[[#This Row],[價值]]/壓榨性債務[[#Totals],[價值]],0) -> 0.0022956154 | E24: 3000 | J24: 房貸 | K24: 0 | L24: =IFERROR(功能性債務[[#This Row],[價值]]/功能性債務[[#Totals],[價值]],0) -> 0 | P24: ●短期償債能力強弱： | Q24: =流動性資產[[#Totals],[價值]]/壓榨性債務[[#Totals],[價值]] -> 0.002910632 | R24: ≧100%
B25: 中信信貸(14.78%) | C25: 252574 | D25: =IFERROR(壓榨性債務[[#This Row],[價值]]/壓榨性債務[[#Totals],[價值]],0) -> 0.073514996 | E25: 5177 | F25: 48111 | J25: 商品分期 | K25: 0 | L25: =IFERROR(功能性債務[[#This Row],[價值]]/功能性債務[[#Totals],[價值]],0) -> 0 | P25: 1.若數據<100%，生活容易陷入
B26: 中信信貸(14.78%) | C26: 1459626 | D26: =IFERROR(壓榨性債務[[#This Row],[價值]]/壓榨性債務[[#Totals],[價值]],0) -> 0.42484341 | E26: 29911 | F26: 48111 | L26: =IFERROR(功能性債務[[#This Row],[價值]]/功能性債務[[#Totals],[價值]],0) -> 0 | P26: 週轉不靈的窘境。
B27: 星展信貸(5.99%) | C27: 31553 | D27: =IFERROR(壓榨性債務[[#This Row],[價值]]/壓榨性債務[[#Totals],[價值]],0) -> 0.009183917 | E27: 1456 | F27: 46568 | L27: =IFERROR(功能性債務[[#This Row],[價值]]/功能性債務[[#Totals],[價值]],0) -> 0 | P27: 2.歐美的數據設定為≧1.5
B28: 樂分期 | C28: 17622 | D28: =IFERROR(壓榨性債務[[#This Row],[價值]]/壓榨性債務[[#Totals],[價值]],0) -> 0.0051291156 | E28: 2937 | F28: 46016 | J28: 合計 | K28: =SUBTOTAL(109,[價值]) -> 0
B29: 裕富分期 | C29: 66700 | D29: =IFERROR(壓榨性債務[[#This Row],[價值]]/壓榨性債務[[#Totals],[價值]],0) -> 0.019413915 | E29: 7800 | F29: 46104 | P29: ●負債比例大小： | Q29: =K21/K2 -> 24.540571 | R29: ≦50%
B30: 車貸 | C30: 1295168 | D30: =IFERROR(壓榨性債務[[#This Row],[價值]]/壓榨性債務[[#Totals],[價值]],0) -> 0.37697574 | E30: 23128 | F30: 47547 | J30: 致富性債務 | K30: 價值 | L30: 佔比 | P30: 1.若數據>50%，容易造成生
B31: 和潤機車 | C31: 232320 | D31: =IFERROR(壓榨性債務[[#This Row],[價值]]/壓榨性債務[[#Totals],[價值]],0) -> 0.067619802 | E31: 7260 | F31: 46693 | J31: 自用不動產抵押貸款 | K31: 0 | L31: =IFERROR(致富性債務[[#This Row],[價值]]/致富性債務[[#Totals],[價值]],0) -> 0 | P31: 活壓力過大。
D32: =IFERROR(壓榨性債務[[#This Row],[價值]]/壓榨性債務[[#Totals],[價值]],0) -> 0 | J32: 投資性不動產抵押貸款 | K32: 0 | L32: =IFERROR(致富性債務[[#This Row],[價值]]/致富性債務[[#Totals],[價值]],0) -> 0 | P32: 2.若數據>50%，顯示出資產
B33: 合計 | C33: =SUBTOTAL(109,[價值]) -> 3435680 | E33: =SUBTOTAL(109,[月繳]) -> 86669 | J33: 信用貸款 | K33: 0 | L33: =IFERROR(致富性債務[[#This Row],[價值]]/致富性債務[[#Totals],[價值]],0) -> 0 | P33: 大部份是舉債購得的。
J34: 分期付款 | K34: 0 | L34: =IFERROR(致富性債務[[#This Row],[價值]]/致富性債務[[#Totals],[價值]],0) -> 0
J35: 保單貸款 | K35: 0 | L35: =IFERROR(致富性債務[[#This Row],[價值]]/致富性債務[[#Totals],[價值]],0) -> 0 | P35: ●生活週轉金充裕度 | Q35: =流動性資產[[#Totals],[價值]]/'現金流量表 (手打、整合)'!E7 -> #NAME? | R35: ≧300%
J36: 合計 | K36: =SUBTOTAL(109,[價值]) -> 0 | P36: 1.數據<300%，太冒險；數據>600%
P37: 又太保守，建議年輕者以300%為佳
P38: ，年長者或退休者以6為佳。
P40: 2.數據>3時，建議可將多餘資金挪做
P41: 其他相對安全的投資工具(例如債券..等)

Sheet 現金流量表(連動)
D2: 年份 | E2: 估值 | F2: 初始 | G2: 45839 | H2: =EDATE(G2,1) -> 45870 | I2: =EDATE(H2,1) -> 45901 | J2: =EDATE(I2,1) -> 45931 | K2: =EDATE(J2,1) -> 45962 | L2: =EDATE(K2,1) -> 45992 | M2: =EDATE(L2,1) -> 46023 | N2: =EDATE(M2,1) -> 46054 | O2: =EDATE(N2,1) -> 46082 | ... S2: =EDATE(R2,1) -> 46204
D3: 持有資金 | F3: 0 | G3: =F3+G4 -> -89753 | H3: =G3+H4 -> -176930 | I3: =H3+I4 -> -176930 | J3: =I3+J4 -> -176930 | K3: =J3+K4 -> -176930 | L3: =K3+L4 -> -176930 | M3: =L3+M4 -> -176930 | N3: =M3+N4 -> -176930 | ... S3: =R3+S4 -> -176930
D4: 現金流 | G4: =G5+G70+G22 -> -89753 | H4: =H5+H70+H22 -> -87177 | I4: =I5+I70+I22 -> 0 | J4: =J5+J70+J22 -> 0 | K4: =K5+K70+K22 -> 0 | L4: =L5+L70+L22 -> 0 | M4: =M5+M70+M22 -> 0 | N4: =N5+N70+N22 -> 0 | ... S4: =S5+S70+S22 -> 0
B5: 收入 | D5: 總計 | E5: =SUM(E6+E9+E12+E15+E20) -> 76000 | G5: =SUM(G6+G9+G12+G15+G20) -> 0 | H5: =SUM(H6+H9+H12+H15+H20) -> 20000 | I5: =SUM(I6+I9+I12+I15+I20) -> 0 | J5: =SUM(J6+J9+J12+J15+J20) -> 0 | K5: =SUM(K6+K9+K12+K15+K20) -> 0 | L5: =SUM(L6+L9+L12+L15+L20) -> 0 | M5: =SUM(M6+M9+M12+M15+M20) -> 0 | N5: =SUM(N6+N9+N12+N15+N20) -> 0 | ... S5: =SUM(S6+S9+S12+S15+S20) -> 0
D6: 本業 | E6: 76000 | G6: =SUMIFS(記帳區!$F:$F,記帳區!$K:$K,">=" & EOMONTH(G2,-1) + 1,記帳區!$K:$K,"<=" & EOMONTH(G2, 0),記帳區!$D:$D,$D6) -> 0 | H6: =SUMIFS(記帳區!$F:$F,記帳區!$K:$K,">=" & EOMONTH(H2,-1) + 1,記帳區!$K:$K,"<=" & EOMONTH(H2, 0),記帳區!$D:$D,$D6) -> 0 | I6: =SUMIFS(記帳區!$F:$F,記帳區!$K:$K,">=" & EOMONTH(I2,-1) + 1,記帳區!$K:$K,"<=" & EOMONTH(I2, 0),記帳區!$D:$D,$D6) -> 0 | J6: =SUMIFS(記帳區!$F:$F,記帳區!$K:$K,">=" & EOMONTH(J2,-1) + 1,記帳區!$K:$K,"<=" & EOMONTH(J2, 0),記帳區!$D:$D,$D6) -> 0 | K6: =SUMIFS(記帳區!$F:$F,記帳區!$K:$K,">=" & EOMONTH(K2,-1) + 1,記帳區!$K:$K,"<=" & EOMONTH(K2, 0),記帳區!$D:$D,$D6) -> 0 | L6: =SUMIFS(記帳區!$F:$F,記帳區!$K:$K,">=" & EOMONTH(L2,-1) + 1,記帳區!$K:$K,"<=" & EOMONTH(L2, 0),記帳區!$D:$D,$D6) -> 0 | M6: =SUMIFS(記帳區!$F:$F,記帳區!$K:$K,">=" & EOMONTH(M2,-1) + 1,記帳區!$K:$K,"<=" & EOMONTH(M2, 0),記帳區!$D:$D,$D6) -> 0 | N6: =SUMIFS(記帳區!$F:$F,記帳區!$K:$K,">=" & EOMONTH(N2,-1) + 1,記帳區!$K:$K,"<=" & EOMONTH(N2, 0),記帳區!$D:$D,$D6) -> 0 | ... S6: =SUMIFS(記帳區!$F:$F,記帳區!$K:$K,">=" & EOMONTH(S2,-1) + 1,記帳區!$K:$K,"<=" & EOMONTH(S2, 0),記帳區!$D:$D,$D6) -> 0
D7: 薪資 | G7: =SUMIFS(記帳區!$F:$F,記帳區!$K:$K,">=" & EOMONTH(G2,-1) + 1,記帳區!$K:$K,"<=" & EOMONTH(G2, 0),記帳區!$E:$E,$D7) -> 71244 | H7: =SUMIFS(記帳區!$F:$F,記帳區!$K:$K,">=" & EOMONTH(H$2,-1) + 1,記帳區!$K:$K,"<=" & EOMONTH(H$2, 0),記帳區!$E:$E,$D7) -> 71244 | I7: =SUMIFS(記帳區!$F:$F,記帳區!$K:$K,">=" & EOMONTH(I$2,-1) + 1,記帳區!$K:$K,"<=" & EOMONTH(I$2, 0),記帳區!$E:$E,$D7) -> 0 | J7: =SUMIFS(記帳區!$F:$F,記帳區!$K:$K,">=" & EOMONTH(J$2,-1) + 1,記帳區!$K:$K,"<=" & EOMONTH(J$2, 0),記帳區!$E:$E,$D7) -> 0 | K7: =SUMIFS(記帳區!$F:$F,記帳區!$K:$K,">=" & EOMONTH(K$2,-1) + 1,記帳區!$K:$K,"<=" & EOMONTH(K$2, 0),記帳區!$E:$E,$D7) -> 0 | L7: =SUMIFS(記帳區!$F:$F,記帳區!$K:$K,">=" & EOMONTH(L$2,-1) + 1,記帳區!$K:$K,"<=" & EOMONTH(L$2, 0),記帳區!$E:$E,$D7) -> 0 | M7: =SUMIFS(記帳區!$F:$F,記帳區!$K:$K,">=" & EOMONTH(M$2,-1) + 1,記帳區!$K:$K,"<=" & EOMONTH(M$2, 0),記帳區!$E:$E,$D7) -> 0 | N7: =SUMIFS(記帳區!$F:$F,記帳區!$K:$K,">=" & EOMONTH(N$2,-1) + 1,記帳區!$K:$K,"<=" & EOMONTH(N$2, 0),記帳區!$E:$E,$D7) -> 0 | O7: =SUMIFS(記帳區!$F:$F,記帳區!$K:$K,">=" & EOMONTH(O$2,-1) + 1,記帳區!$K:$K,"<=" & EOMONTH(O$2, 0),記帳區!$E:$E,$D7) -> 0 | ... S7: =SUMIFS(記帳區!$F:$F,記帳區!$K:$K,">=" & EOMONTH(S$2,-1) + 1,記帳區!$K:$K,"<=" & EOMONTH(S$2, 0),記帳區!$E:$E,$D7) -> 0
D8: 加班費 | G8: =SUMIFS(記帳區!$F:$F,記帳區!$K:$K,">=" & EOMONTH($G$2,-1) + 1,記帳區!$K:$K,"<=" & EOMONTH($G$2, 0),記帳區!$E:$E,$D8) -> 15000 | H8: =SUMIFS(記帳區!$F:$F,記帳區!$K:$K,">=" & EOMONTH(H$2,-1) + 1,記帳區!$K:$K,"<=" & EOMONTH(H$2, 0),記帳區!$E:$E,$D8) -> 15000 | I8: =SUMIFS(記帳區!$F:$F,記帳區!$K:$K,">=" & EOMONTH(I$2,-1) + 1,記帳區!$K:$K,"<=" & EOMONTH(I$2, 0),記帳區!$E:$E,$D8) -> 0 | J8: =SUMIFS(記帳區!$F:$F,記帳區!$K:$K,">=" & EOMONTH(J$2,-1) + 1,記帳區!$K:$K,"<=" & EOMONTH(J$2, 0),記帳區!$E:$E,$D8) -> 0 | K8: =SUMIFS(記帳區!$F:$F,記帳區!$K:$K,">=" & EOMONTH(K$2,-1) + 1,記帳區!$K:$K,"<=" & EOMONTH(K$2, 0),記帳區!$E:$E,$D8) -> 0 | L8: =SUMIFS(記帳區!$F:$F,記帳區!$K:$K,">=" & EOMONTH(L$2,-1) + 1,記帳區!$K:$K,"<=" & EOMONTH(L$2, 0),記帳區!$E:$E,$D8) -> 0 | M8: =SUMIFS(記帳區!$F:$F,記帳區!$K:$K,">=" & EOMONTH(M$2,-1) + 1,記帳區!$K:$K,"<=" & EOMONTH(M$2, 0),記帳區!$E:$E,$D8) -> 0 | N8: =SUMIFS(記帳區!$F:$F,記帳區!$K:$K,">=" & EOMONTH(N$2,-1) + 1,記帳區!$K:$K,"<=" & EOMONTH(N$2, 0),記帳區!$E:$E,$D8) -> 0 | O8: =SUMIFS(記帳區!$F:$F,記帳區!$K:$K,">=" & EOMONTH(O$2,-1) + 1,記帳區!$K:$K,"<=" & EOMONTH(O$2, 0),記帳區!$E:$E,$D8) -> 0 | ... S8: =SUMIFS(記帳區!$F:$F,記帳區!$K:$K,">=" & EOMONTH(S$2,-1) + 1,記帳區!$K:$K,"<=" & EOMONTH(S$2, 0),記帳區!$E:$E,$D8) -> 0
D9: 副業 | G9: =SUMIFS(記帳區!$F:$F,記帳區!$K:$K,">=" & EOMONTH(G2,-1) + 1,記帳區!$K:$K,"<=" & EOMONTH(G2, 0),記帳區!$D:$D,$D9) -> 0 | H9: =SUMIFS(記帳區!$F:$F,記帳區!$K:$K,">=" & EOMONTH(H2,-1) + 1,記帳區!$K:$K,"<=" & EOMONTH(H2, 0),記帳區!$D:$D,$D9) -> 0 | I9: =SUMIFS(記帳區!$F:$F,記帳區!$K:$K,">=" & EOMONTH(I2,-1) + 1,記帳區!$K:$K,"<=" & EOMONTH(I2, 0),記帳區!$D:$D,$D9) -> 0 | J9: =SUMIFS(記帳區!$F:$F,記帳區!$K:$K,">=" & EOMONTH(J2,-1) + 1,記帳區!$K:$K,"<=" & EOMONTH(J2, 0),記帳區!$D:$D,$D9) -> 0 | K9: =SUMIFS(記帳區!$F:$F,記帳區!$K:$K,">=" & EOMONTH(K2,-1) + 1,記帳區!$K:$K,"<=" & EOMONTH(K2, 0),記帳區!$D:$D,$D9) -> 0 | L9: =SUMIFS(記帳區!$F:$F,記帳區!$K:$K,">=" & EOMONTH(L2,-1) + 1,記帳區!$K:$K,"<=" & EOMONTH(L2, 0),記帳區!$D:$D,$D9) -> 0 | M9: =SUMIFS(記帳區!$F:$F,記帳區!$K:$K,">=" & EOMONTH(M2,-1) + 1,記帳區!$K:$K,"<=" & EOMONTH(M2, 0),記帳區!$D:$D,$D9) -> 0 | N9: =SUMIFS(記帳區!$F:$F,記帳區!$K:$K,">=" & EOMONTH(N2,-1) + 1,記帳區!$K:$K,"<=" & EOMONTH(N2, 0),記帳區!$D:$D,$D9) -> 0 | ... S9: =SUMIFS(記帳區!$F:$F,記帳區!$K:$K,">=" & EOMONTH(S2,-1) + 1,記帳區!$K:$K,"<=" & EOMONTH(S2, 0),記帳區!$D:$D,$D9) -> 0
G10: =SUMIFS(記帳區!$F:$F,記帳區!$K:$K,">=" & EOMONTH($G$2,-1) + 1,記帳區!$K:$K,"<=" & EOMONTH($G$2, 0),記帳區!$E:$E,$D10) -> 0 | H10: =SUMIFS(記帳區!$F:$F,記帳區!$K:$K,">=" & EOMONTH(H$2,-1) + 1,記帳區!$K:$K,"<=" & EOMONTH(H$2, 0),記帳區!$E:$E,$D10) -> 0 | I10: =SUMIFS(記帳區!$F:$F,記帳區!$K:$K,">=" & EOMONTH(I$2,-1) + 1,記帳區!$K:$K,"<=" & EOMONTH(I$2, 0),記帳區!$E:$E,$D10) -> 0 | J10: =SUMIFS(記帳區!$F:$F,記帳區!$K:$K,">=" & EOMONTH(J$2,-1) + 1,記帳區!$K:$K,"<=" & EOMONTH(J$2, 0),記帳區!$E:$E,$D10) -> 0 | K10: =SUMIFS(記帳區!$F:$F,記帳區!$K:$K,">=" & EOMONTH(K$2,-1) + 1,記帳區!$K:$K,"<=" & EOMONTH(K$2, 0),記帳區!$E:$E,$D10) -> 0 | L10: =SUMIFS(記帳區!$F:$F,記帳區!$K:$K,">=" & EOMONTH(L$2,-1) + 1,記帳區!$K:$K,"<=" & EOMONTH(L$2, 0),記帳區!$E:$E,$D10) -> 0 | M10: =SUMIFS(記帳區!$F:$F,記帳區!$K:$K,">=" & EOMONTH(M$2,-1) + 1,記帳區!$K:$K,"<=" & EOMONTH(M$2, 0),記帳區!$E:$E,$D10) -> 0 | N10: =SUMIFS(記帳區!$F:$F,記帳區!$K:$K,">=" & EOMONTH(N$2,-1) + 1,記帳區!$K:$K,"<=" & EOMONTH(N$2, 0),記帳區!$E:$E,$D10) -> 0 | O10: =SUMIFS(記帳區!$F:$F,記帳區!$K:$K,">=" & EOMONTH(O$2,-1) + 1,記帳區!$K:$K,"<=" & EOMONTH(O$2, 0),記帳區!$E:$E,$D10) -> 0 | ... S10: =SUMIFS(記帳區!$F:$F,記帳區!$K:$K,">=" & EOMONTH(S$2,-1) + 1,記帳區!$K:$K,"<=" & EOMONTH(S$2, 0),記帳區!$E:$E,$D10) -> 0
G11: =SUMIFS(記帳區!$F:$F,記帳區!$K:$K,">=" & EOMONTH($G$2,-1) + 1,記帳區!$K:$K,"<=" & EOMONTH($G$2, 0),記帳區!$E:$E,$D11) -> 0 | H11: =SUMIFS(記帳區!$F:$F,記帳區!$K:$K,">=" & EOMONTH(H$2,-1) + 1,記帳區!$K:$K,"<=" & EOMONTH(H$2, 0),記帳區!$E:$E,$D11) -> 0 | I11: =SUMIFS(記帳區!$F:$F,記帳區!$K:$K,">=" & EOMONTH(I$2,-1) + 1,記帳區!$K:$K,"<=" & EOMONTH(I$2, 0),記帳區!$E:$E,$D11) -> 0 | J11: =SUMIFS(記帳區!$F:$F,記帳區!$K:$K,">=" & EOMONTH(J$2,-1) + 1,記帳區!$K:$K,"<=" & EOMONTH(J$2, 0),記帳區!$E:$E,$D11) -> 0 | K11: =SUMIFS(記帳區!$F:$F,記帳區!$K:$K,">=" & EOMONTH(K$2,-1) + 1,記帳區!$K:$K,"<=" & EOMONTH(K$2, 0),記帳區!$E:$E,$D11) -> 0 | L11: =SUMIFS(記帳區!$F:$F,記帳區!$K:$K,">=" & EOMONTH(L$2,-1) + 1,記帳區!$K:$K,"<=" & EOMONTH(L$2, 0),記帳區!$E:$E,$D11) -> 0 | M11: =SUMIFS(記帳區!$F:$F,記帳區!$K:$K,">=" & EOMONTH(M$2,-1) + 1,記帳區!$K:$K,"<=" & EOMONTH(M$2, 0),記帳區!$E:$E,$D11) -> 0 | N11: =SUMIFS(記帳區!$F:$F,記帳區!$K:$K,">=" & EOMONTH(N$2,-1) + 1,記帳區!$K:$K,"<=" & EOMONTH(N$2, 0),記帳區!$E:$E,$D11) -> 0 | O11: =SUMIFS(記帳區!$F:$F,記帳區!$K:$K,">=" & EOMONTH(O$2,-1) + 1,記帳區!$K:$K,"<=" & EOMONTH(O$2, 0),記帳區!$E:$E,$D11) -> 0 | ... S11: =SUMIFS(記帳區!$F:$F,記帳區!$K:$K,">=" & EOMONTH(S$2,-1) + 1,記帳區!$K:$K,"<=" & EOMONTH(S$2, 0),記帳區!$E:$E,$D11) -> 0
D12: 投資盈利 | G12: =SUMIFS(記帳區!$F:$F,記帳區!$K:$K,">=" & EOMONTH(G2,-1) + 1,記帳區!$K:$K,"<=" & EOMONTH(G2, 0),記帳區!$D:$D,$D12) -> 0 | H12: =SUMIFS(記帳區!$F:$F,記帳區!$K:$K,">=" & EOMONTH(H2,-1) + 1,記帳區!$K:$K,"<=" & EOMONTH(H2, 0),記帳區!$D:$D,$D12) -> 0 | I12: =SUMIFS(記帳區!$F:$F,記帳區!$K:$K,">=" & EOMONTH(I2,-1) + 1,記帳區!$K:$K,"<=" & EOMONTH(I2, 0),記帳區!$D:$D,$D12) -> 0 | J12: =SUMIFS(記帳區!$F:$F,記帳區!$K:$K,">=" & EOMONTH(J2,-1) + 1,記帳區!$K:$K,"<=" & EOMONTH(J2, 0),記帳區!$D:$D,$D12) -> 0 | K12: =SUMIFS(記帳區!$F:$F,記帳區!$K:$K,">=" & EOMONTH(K2,-1) + 1,記帳區!$K:$K,"<=" & EOMONTH(K2, 0),記帳區!$D:$D,$D12) -> 0 | L12: =SUMIFS(記帳區!$F:$F,記帳區!$K:$K,">=" & EOMONTH(L2,-1) + 1,記帳區!$K:$K,"<=" & EOMONTH(L2, 0),記帳區!$D:$D,$D12) -> 0 | M12: =SUMIFS(記帳區!$F:$F,記帳區!$K:$K,">=" & EOMONTH(M2,-1) + 1,記帳區!$K:$K,"<=" & EOMONTH(M2, 0),記帳區!$D:$D,$D12) -> 0 | N12: =SUMIFS(記帳區!$F:$F,記帳區!$K:$K,">=" & EOMONTH(N2,-1) + 1,記帳區!$K:$K,"<=" & EOMONTH(N2, 0),記帳區!$D:$D,$D12) -> 0 | ... S12: =SUMIFS(記帳區!$F:$F,記帳區!$K:$K,">=" & EOMONTH(S2,-1) + 1,記帳區!$K:$K,"<=" & EOMONTH(S2, 0),記帳區!$D:$D,$D12) -> 0
D13: 外匯盈利 | G13: =SUMIFS(記帳區!$F:$F,記帳區!$K:$K,">=" & EOMONTH($G$2,-1) + 1,記帳區!$K:$K,"<=" & EOMONTH($G$2, 0),記帳區!$E:$E,$D13) -> 0 | H13: =SUMIFS(記帳區!$F:$F,記帳區!$K:$K,">=" & EOMONTH(H$2,-1) + 1,記帳區!$K:$K,"<=" & EOMONTH(H$2, 0),記帳區!$E:$E,$D13) -> 0 | I13: =SUMIFS(記帳區!$F:$F,記帳區!$K:$K,">=" & EOMONTH(I$2,-1) + 1,記帳區!$K:$K,"<=" & EOMONTH(I$2, 0),記帳區!$E:$E,$D13) -> 0 | J13: =SUMIFS(記帳區!$F:$F,記帳區!$K:$K,">=" & EOMONTH(J$2,-1) + 1,記帳區!$K:$K,"<=" & EOMONTH(J$2, 0),記帳區!$E:$E,$D13) -> 0 | K13: =SUMIFS(記帳區!$F:$F,記帳區!$K:$K,">=" & EOMONTH(K$2,-1) + 1,記帳區!$K:$K,"<=" & EOMONTH(K$2, 0),記帳區!$E:$E,$D13) -> 0 | L13: =SUMIFS(記帳區!$F:$F,記帳區!$K:$K,">=" & EOMONTH(L$2,-1) + 1,記帳區!$K:$K,"<=" & EOMONTH(L$2, 0),記帳區!$E:$E,$D13) -> 0 | M13: =SUMIFS(記帳區!$F:$F,記帳區!$K:$K,">=" & EOMONTH(M$2,-1) + 1,記帳區!$K:$K,"<=" & EOMONTH(M$2, 0),記帳區!$E:$E,$D13) -> 0 | N13: =SUMIFS(記帳區!$F:$F,記帳區!$K:$K,">=" & EOMONTH(N$2,-1) + 1,記帳區!$K:$K,"<=" & EOMONTH(N$2, 0),記帳區!$E:$E,$D13) -> 0 | O13: =SUMIFS(記帳區!$F:$F,記帳區!$K:$K,">=" & EOMONTH(O$2,-1) + 1,記帳區!$K:$K,"<=" & EOMONTH(O$2, 0),記帳區!$E:$E,$D13) -> 0 | ... S13: =SUMIFS(記帳區!$F:$F,記帳區!$K:$K,">=" & EOMONTH(S$2,-1) + 1,記帳區!$K:$K,"<=" & EOMONTH(S$2, 0),記帳區!$E:$E,$D13) -> 0
G14: =SUMIFS(記帳區!$F:$F,記帳區!$K:$K,">=" & EOMONTH($G$2,-1) + 1,記帳區!$K:$K,"<=" & EOMONTH($G$2, 0),記帳區!$E:$E,$D14) -> 0 | H14: =SUMIFS(記帳區!$F:$F,記帳區!$K:$K,">=" & EOMONTH(H$2,-1) + 1,記帳區!$K:$K,"<=" & EOMONTH(H$2, 0),記帳區!$E:$E,$D14) -> 0 | I14: =SUMIFS(記帳區!$F:$F,記帳區!$K:$K,">=" & EOMONTH(I$2,-1) + 1,記帳區!$K:$K,"<=" & EOMONTH(I$2, 0),記帳區!$E:$E,$D14) -> 0 | J14: =SUMIFS(記帳區!$F:$F,記帳區!$K:$K,">=" & EOMONTH(J$2,-1) + 1,記帳區!$K:$K,"<=" & EOMONTH(J$2, 0),記帳區!$E:$E,$D14) -> 0 | K14: =SUMIFS(記帳區!$F:$F,記帳區!$K:$K,">=" & EOMONTH(K$2,-1) + 1,記帳區!$K:$K,"<=" & EOMONTH(K$2, 0),記帳區!$E:$E,$D14) -> 0 | L14: =SUMIFS(記帳區!$F:$F,記帳區!$K:$K,">=" & EOMONTH(L$2,-1) + 1,記帳區!$K:$K,"<=" & EOMONTH(L$2, 0),記帳區!$E:$E,$D14) -> 0 | M14: =SUMIFS(記帳區!$F:$F,記帳區!$K:$K,">=" & EOMONTH(M$2,-1) + 1,記帳區!$K:$K,"<=" & EOMONTH(M$2, 0),記帳區!$E:$E,$D14) -> 0 | N14: =SUMIFS(記帳區!$F:$F,記帳區!$K:$K,">=" & EOMONTH(N$2,-1) + 1,記帳區!$K:$K,"<=" & EOMONTH(N$2, 0),記帳區!$E:$E,$D14) -> 0 | O14: =SUMIFS(記帳區!$F:$F,記帳區!$K:$K,">=" & EOMONTH(O$2,-1) + 1,記帳區!$K:$K,"<=" & EOMONTH(O$2, 0),記帳區!$E:$E,$D14) -> 0 | ... S14: =SUMIFS(記帳區!$F:$F,記帳區!$K:$K,">=" & EOMONTH(S$2,-1) + 1,記帳區!$K:$K,"<=" & EOMONTH(S$2, 0),記帳區!$E:$E,$D14) -> 0
D15: 被動 | G15: =SUMIFS(記帳區!$F:$F,記帳區!$K:$K,">=" & EOMONTH(G2,-1) + 1,記帳區!$K:$K,"<=" & EOMONTH(G2, 0),記帳區!$D:$D,$D15) -> 0 | H15: =SUMIFS(記帳區!$F:$F,記帳區!$K:$K,">=" & EOMONTH(H2,-1) + 1,記帳區!$K:$K,"<=" & EOMONTH(H2, 0),記帳區!$D:$D,$D15) -> 0 | I15: =SUMIFS(記帳區!$F:$F,記帳區!$K:$K,">=" & EOMONTH(I2,-1) + 1,記帳區!$K:$K,"<=" & EOMONTH(I2, 0),記帳區!$D:$D,$D15) -> 0 | J15: =SUMIFS(記帳區!$F:$F,記帳區!$K:$K,">=" & EOMONTH(J2,-1) + 1,記帳區!$K:$K,"<=" & EOMONTH(J2, 0),記帳區!$D:$D,$D15) -> 0 | K15: =SUMIFS(記帳區!$F:$F,記帳區!$K:$K,">=" & EOMONTH(K2,-1) + 1,記帳區!$K:$K,"<=" & EOMONTH(K2, 0),記帳區!$D:$D,$D15) -> 0 | L15: =SUMIFS(記帳區!$F:$F,記帳區!$K:$K,">=" & EOMONTH(L2,-1) + 1,記帳區!$K:$K,"<=" & EOMONTH(L2, 0),記帳區!$D:$D,$D15) -> 0 | M15: =SUMIFS(記帳區!$F:$F,記帳區!$K:$K,">=" & EOMONTH(M2,-1) + 1,記帳區!$K:$K,"<=" & EOMONTH(M2, 0),記帳區!$D:$D,$D15) -> 0 | N15: =SUMIFS(記帳區!$F:$F,記帳區!$K:$K,">=" & EOMONTH(N2,-1) + 1,記帳區!$K:$K,"<=" & EOMONTH(N2, 0),記帳區!$D:$D,$D15) -> 0 | ... S15: =SUMIFS(記帳區!$F:$F,記帳區!$K:$K,">=" & EOMONTH(S2,-1) + 1,記帳區!$K:$K,"<=" & EOMONTH(S2, 0),記帳區!$D:$D,$D15) -> 0
G16: =SUMIFS(記帳區!$F:$F,記帳區!$K:$K,">=" & EOMONTH(G$2,-1) + 1,記帳區!$K:$K,"<=" & EOMONTH(G$2, 0),記帳區!$E:$E,$D16) -> 0 | H16: =SUMIFS(記帳區!$F:$F,記帳區!$K:$K,">=" & EOMONTH(H$2,-1) + 1,記帳區!$K:$K,"<=" & EOMONTH(H$2, 0),記帳區!$E:$E,$D16) -> 0 | I16: =SUMIFS(記帳區!$F:$F,記帳區!$K:$K,">=" & EOMONTH(I$2,-1) + 1,記帳區!$K:$K,"<=" & EOMONTH(I$2, 0),記帳區!$E:$E,$D16) -> 0 | J16: =SUMIFS(記帳區!$F:$F,記帳區!$K:$K,">=" & EOMONTH(J$2,-1) + 1,記帳區!$K:$K,"<=" & EOMONTH(J$2, 0),記帳區!$E:$E,$D16) -> 0 | K16: =SUMIFS(記帳區!$F:$F,記帳區!$K:$K,">=" & EOMONTH(K$2,-1) + 1,記帳區!$K:$K,"<=" & EOMONTH(K$2, 0),記帳區!$E:$E,$D16) -> 0 | L16: =SUMIFS(記帳區!$F:$F,記帳區!$K:$K,">=" & EOMONTH(L$2,-1) + 1,記帳區!$K:$K,"<=" & EOMONTH(L$2, 0),記帳區!$E:$E,$D16) -> 0 | M16: =SUMIFS(記帳區!$F:$F,記帳區!$K:$K,">=" & EOMONTH(M$2,-1) + 1,記帳區!$K:$K,"<=" & EOMONTH(M$2, 0),記帳區!$E:$E,$D16) -> 0 | N16: =SUMIFS(記帳區!$F:$F,記帳區!$K:$K,">=" & EOMONTH(N$2,-1) + 1,記帳區!$K:$K,"<=" & EOMONTH(N$2, 0),記帳區!$E:$E,$D16) -> 0 | ... S16: =SUMIFS(記帳區!$F:$F,記帳區!$K:$K,">=" & EOMONTH(S$2,-1) + 1,記帳區!$K:$K,"<=" & EOMONTH(S$2, 0),記帳區!$E:$E,$D16) -> 0
G17: =SUMIFS(記帳區!$F:$F,記帳區!$K:$K,">=" & EOMONTH($G$2,-1) + 1,記帳區!$K:$K,"<=" & EOMONTH($G$2, 0),記帳區!$E:$E,$D17) -> 0 | H17: =SUMIFS(記帳區!$F:$F,記帳區!$K:$K,">=" & EOMONTH(H$2,-1) + 1,記帳區!$K:$K,"<=" & EOMONTH(H$2, 0),記帳區!$E:$E,$D17) -> 0 | I17: =SUMIFS(記帳區!$F:$F,記帳區!$K:$K,">=" & EOMONTH(I$2,-1) + 1,記帳區!$K:$K,"<=" & EOMONTH(I$2, 0),記帳區!$E:$E,$D17) -> 0 | J17: =SUMIFS(記帳區!$F:$F,記帳區!$K:$K,">=" & EOMONTH(J$2,-1) + 1,記帳區!$K:$K,"<=" & EOMONTH(J$2, 0),記帳區!$E:$E,$D17) -> 0 | K17: =SUMIFS(記帳區!$F:$F,記帳區!$K:$K,">=" & EOMONTH(K$2,-1) + 1,記帳區!$K:$K,"<=" & EOMONTH(K$2, 0),記帳區!$E:$E,$D17) -> 0 | L17: =SUMIFS(記帳區!$F:$F,記帳區!$K:$K,">=" & EOMONTH(L$2,-1) + 1,記帳區!$K:$K,"<=" & EOMONTH(L$2, 0),記帳區!$E:$E,$D17) -> 0 | M17: =SUMIFS(記帳區!$F:$F,記帳區!$K:$K,">=" & EOMONTH(M$2,-1) + 1,記帳區!$K:$K,"<=" & EOMONTH(M$2, 0),記帳區!$E:$E,$D17) -> 0 | N17: =SUMIFS(記帳區!$F:$F,記帳區!$K:$K,">=" & EOMONTH(N$2,-1) + 1,記帳區!$K:$K,"<=" & EOMONTH(N$2, 0),記帳區!$E:$E,$D17) -> 0 | O17: =SUMIFS(記帳區!$F:$F,記帳區!$K:$K,">=" & EOMONTH(O$2,-1) + 1,記帳區!$K:$K,"<=" & EOMONTH(O$2, 0),記帳區!$E:$E,$D17) -> 0 | ... S17: =SUMIFS(記帳區!$F:$F,記帳區!$K:$K,">=" & EOMONTH(S$2,-1) + 1,記帳區!$K:$K,"<=" & EOMONTH(S$2, 0),記帳區!$E:$E,$D17) -> 0
G18: =SUMIFS(記帳區!$F:$F,記帳區!$K:$K,">=" & EOMONTH($G$2,-1) + 1,記帳區!$K:$K,"<=" & EOMONTH($G$2, 0),記帳區!$E:$E,$D18) -> 0 | H18: =SUMIFS(記帳區!$F:$F,記帳區!$K:$K,">=" & EOMONTH(H$2,-1) + 1,記帳區!$K:$K,"<=" & EOMONTH(H$2, 0),記帳區!$E:$E,$D18) -> 0 | I18: =SUMIFS(記帳區!$F:$F,記帳區!$K:$K,">=" & EOMONTH(I$2,-1) + 1,記帳區!$K:$K,"<=" & EOMONTH(I$2, 0),記帳區!$E:$E,$D18) -> 0 | J18: =SUMIFS(記帳區!$F:$F,記帳區!$K:$K,">=" & EOMONTH(J$2,-1) + 1,記帳區!$K:$K,"<=" & EOMONTH(J$2, 0),記帳區!$E:$E,$D18) -> 0 | K18: =SUMIFS(記帳區!$F:$F,記帳區!$K:$K,">=" & EOMONTH(K$2,-1) + 1,記帳區!$K:$K,"<=" & EOMONTH(K$2, 0),記帳區!$E:$E,$D18) -> 0 | L18: =SUMIFS(記帳區!$F:$F,記帳區!$K:$K,">=" & EOMONTH(L$2,-1) + 1,記帳區!$K:$K,"<=" & EOMONTH(L$2, 0),記帳區!$E:$E,$D18) -> 0 | M18: =SUMIFS(記帳區!$F:$F,記帳區!$K:$K,">=" & EOMONTH(M$2,-1) + 1,記帳區!$K:$K,"<=" & EOMONTH(M$2, 0),記帳區!$E:$E,$D18) -> 0 | N18: =SUMIFS(記帳區!$F:$F,記帳區!$K:$K,">=" & EOMONTH(N$2,-1) + 1,記帳區!$K:$K,"<=" & EOMONTH(N$2, 0),記帳區!$E:$E,$D18) -> 0 | O18: =SUMIFS(記帳區!$F:$F,記帳區!$K:$K,">=" & EOMONTH(O$2,-1) + 1,記帳區!$K:$K,"<=" & EOMONTH(O$2, 0),記帳區!$E:$E,$D18) -> 0 | ... S18: =SUMIFS(記帳區!$F:$F,記帳區!$K:$K,">=" & EOMONTH(S$2,-1) + 1,記帳區!$K:$K,"<=" & EOMONTH(S$2, 0),記帳區!$E:$E,$D18) -> 0
G19: =SUMIFS(記帳區!$F:$F,記帳區!$K:$K,">=" & EOMONTH($G$2,-1) + 1,記帳區!$K:$K,"<=" & EOMONTH($G$2, 0),記帳區!$E:$E,$D19) -> 0 | H19: =SUMIFS(記帳區!$F:$F,記帳區!$K:$K,">=" & EOMONTH(H$2,-1) + 1,記帳區!$K:$K,"<=" & EOMONTH(H$2, 0),記帳區!$E:$E,$D19) -> 0 | I19: =SUMIFS(記帳區!$F:$F,記帳區!$K:$K,">=" & EOMONTH(I$2,-1) + 1,記帳區!$K:$K,"<=" & EOMONTH(I$2, 0),記帳區!$E:$E,$D19) -> 0 | J19: =SUMIFS(記帳區!$F:$F,記帳區!$K:$K,">=" & EOMONTH(J$2,-1) + 1,記帳區!$K:$K,"<=" & EOMONTH(J$2, 0),記帳區!$E:$E,$D19) -> 0 | K19: =SUMIFS(記帳區!$F:$F,記帳區!$K:$K,">=" & EOMONTH(K$2,-1) + 1,記帳區!$K:$K,"<=" & EOMONTH(K$2, 0),記帳區!$E:$E,$D19) -> 0 | L19: =SUMIFS(記帳區!$F:$F,記帳區!$K:$K,">=" & EOMONTH(L$2,-1) + 1,記帳區!$K:$K,"<=" & EOMONTH(L$2, 0),記帳區!$E:$E,$D19) -> 0 | M19: =SUMIFS(記帳區!$F:$F,記帳區!$K:$K,">=" & EOMONTH(M$2,-1) + 1,記帳區!$K:$K,"<=" & EOMONTH(M$2, 0),記帳區!$E:$E,$D19) -> 0 | N19: =SUMIFS(記帳區!$F:$F,記帳區!$K:$K,">=" & EOMONTH(N$2,-1) + 1,記帳區!$K:$K,"<=" & EOMONTH(N$2, 0),記帳區!$E:$E,$D19) -> 0 | O19: =SUMIFS(記帳區!$F:$F,記帳區!$K:$K,">=" & EOMONTH(O$2,-1) + 1,記帳區!$K:$K,"<=" & EOMONTH(O$2, 0),記帳區!$E:$E,$D19) -> 0 | ... S19: =SUMIFS(記帳區!$F:$F,記帳區!$K:$K,">=" & EOMONTH(S$2,-1) + 1,記帳區!$K:$K,"<=" & EOMONTH(S$2, 0),記帳區!$E:$E,$D19) -> 0
D20: 人情 | G20: =SUMIFS(記帳區!$F:$F,記帳區!$K:$K,">=" & EOMONTH(G2,-1) + 1,記帳區!$K:$K,"<=" & EOMONTH(G2, 0),記帳區!$D:$D,$D20) -> 0 | H20: =SUMIFS(記帳區!$F:$F,記帳區!$K:$K,">=" & EOMONTH(H2,-1) + 1,記帳區!$K:$K,"<=" & EOMONTH(H2, 0),記帳區!$D:$D,$D20) -> 20000 | I20: =SUMIFS(記帳區!$F:$F,記帳區!$K:$K,">=" & EOMONTH(I2,-1) + 1,記帳區!$K:$K,"<=" & EOMONTH(I2, 0),記帳區!$D:$D,$D20) -> 0 | J20: =SUMIFS(記帳區!$F:$F,記帳區!$K:$K,">=" & EOMONTH(J2,-1) + 1,記帳區!$K:$K,"<=" & EOMONTH(J2, 0),記帳區!$D:$D,$D20) -> 0 | K20: =SUMIFS(記帳區!$F:$F,記帳區!$K:$K,">=" & EOMONTH(K2,-1) + 1,記帳區!$K:$K,"<=" & EOMONTH(K2, 0),記帳區!$D:$D,$D20) -> 0 | L20: =SUMIFS(記帳區!$F:$F,記帳區!$K:$K,">=" & EOMONTH(L2,-1) + 1,記帳區!$K:$K,"<=" & EOMONTH(L2, 0),記帳區!$D:$D,$D20) -> 0 | M20: =SUMIFS(記帳區!$F:$F,記帳區!$K:$K,">=" & EOMONTH(M2,-1) + 1,記帳區!$K:$K,"<=" & EOMONTH(M2, 0),記帳區!$D:$D,$D20) -> 0 | N20: =SUMIFS(記帳區!$F:$F,記帳區!$K:$K,">=" & EOMONTH(N2,-1) + 1,記帳區!$K:$K,"<=" & EOMONTH(N2, 0),記帳區!$D:$D,$D20) -> 0 | ... S20: =SUMIFS(記帳區!$F:$F,記帳區!$K:$K,">=" & EOMONTH(S2,-1) + 1,記帳區!$K:$K,"<=" & EOMONTH(S2, 0),記帳區!$D:$D,$D20) -> 0
D21: 借款 | G21: =SUMIFS(記帳區!$F:$F,記帳區!$K:$K,">=" & EOMONTH($G$2,-1) + 1,記帳區!$K:$K,"<=" & EOMONTH($G$2, 0),記帳區!$E:$E,$D21) -> 0 | H21: =SUMIFS(記帳區!$F:$F,記帳區!$K:$K,">=" & EOMONTH(H$2,-1) + 1,記帳區!$K:$K,"<=" & EOMONTH(H$2, 0),記帳區!$E:$E,$D21) -> 20000 | I21: =SUMIFS(記帳區!$F:$F,記帳區!$K:$K,">=" & EOMONTH(I$2,-1) + 1,記帳區!$K:$K,"<=" & EOMONTH(I$2, 0),記帳區!$E:$E,$D21) -> 0 | J21: =SUMIFS(記帳區!$F:$F,記帳區!$K:$K,">=" & EOMONTH(J$2,-1) + 1,記帳區!$K:$K,"<=" & EOMONTH(J$2, 0),記帳區!$E:$E,$D21) -> 0 | K21: =SUMIFS(記帳區!$F:$F,記帳區!$K:$K,">=" & EOMONTH(K$2,-1) + 1,記帳區!$K:$K,"<=" & EOMONTH(K$2, 0),記帳區!$E:$E,$D21) -> 0 | L21: =SUMIFS(記帳區!$F:$F,記帳區!$K:$K,">=" & EOMONTH(L$2,-1) + 1,記帳區!$K:$K,"<=" & EOMONTH(L$2, 0),記帳區!$E:$E,$D21) -> 0 | M21: =SUMIFS(記帳區!$F:$F,記帳區!$K:$K,">=" & EOMONTH(M$2,-1) + 1,記帳區!$K:$K,"<=" & EOMONTH(M$2, 0),記帳區!$E:$E,$D21) -> 0 | N21: =SUMIFS(記帳區!$F:$F,記帳區!$K:$K,">=" & EOMONTH(N$2,-1) + 1,記帳區!$K:$K,"<=" & EOMONTH(N$2, 0),記帳區!$E:$E,$D21) -> 0 | O21: =SUMIFS(記帳區!$F:$F,記帳區!$K:$K,">=" & EOMONTH(O$2,-1) + 1,記帳區!$K:$K,"<=" & EOMONTH(O$2, 0),記帳區!$E:$E,$D21) -> 0 | ... S21: =SUMIFS(記帳區!$F:$F,記帳區!$K:$K,">=" & EOMONTH(S$2,-1) + 1,記帳區!$K:$K,"<=" & EOMONTH(S$2, 0),記帳區!$E:$E,$D21) -> 0
D22: 總計 | E22: =SUM(E23+E26+E29+E37+E43+E48+E52+E55+E58+E61+E64+E67) -> 0 | G22: =SUM(G23+G26+G29+G37+G43+G48+G52+G55+G58+G61+G64+G67) -> -89753 | H22: =SUM(H23+H26+H29+H37+H43+H48+H52+H55+H58+H61+H64+H67) -> -87177 | I22: =SUM(I23+I26+I29+I37+I43+I48+I52+I55+I58+I61+I64+I67) -> 0 | J22: =SUM(J23+J26+J29+J37+J43+J48+J52+J55+J58+J61+J64+J67) -> 0 | K22: =SUM(K23+K26+K29+K37+K43+K48+K52+K55+K58+K61+K64+K67) -> 0 | L22: =SUM(L23+L26+L29+L37+L43+L48+L52+L55+L58+L61+L64+L67) -> 0 | M22: =SUM(M23+M26+M29+M37+M43+M48+M52+M55+M58+M61+M64+M67) -> 0 | N22: =SUM(N23+N26+N29+N37+N43+N48+N52+N55+N58+N61+N64+N67) -> 0 | ... S22: =SUM(S23+S26+S29+S37+S43+S48+S52+S55+S58+S61+S64+S67) -> 0
B23: 支出 | C23: 必要支出 | D23: 食 | G23: =SUMIFS(記帳區!$F:$F,記帳區!$K:$K,">=" & EOMONTH(G$2,-1) + 1,記帳區!$K:$K,"<=" & EOMONTH(G$2, 0),記帳區!$D:$D,$D23) -> -424 | H23: =SUMIFS(記帳區!$F:$F,記帳區!$K:$K,">=" & EOMONTH(H$2,-1) + 1,記帳區!$K:$K,"<=" & EOMONTH(H$2, 0),記帳區!$D:$D,$D23) -> -508 | I23: =SUMIFS(記帳區!$F:$F,記帳區!$K:$K,">=" & EOMONTH(I$2,-1) + 1,記帳區!$K:$K,"<=" & EOMONTH(I$2, 0),記帳區!$D:$D,$D23) -> 0 | J23: =SUMIFS(記帳區!$F:$F,記帳區!$K:$K,">=" & EOMONTH(J$2,-1) + 1,記帳區!$K:$K,"<=" & EOMONTH(J$2, 0),記帳區!$D:$D,$D23) -> 0 | K23: =SUMIFS(記帳區!$F:$F,記帳區!$K:$K,">=" & EOMONTH(K$2,-1) + 1,記帳區!$K:$K,"<=" & EOMONTH(K$2, 0),記帳區!$D:$D,$D23) -> 0 | L23: =SUMIFS(記帳區!$F:$F,記帳區!$K:$K,">=" & EOMONTH(L$2,-1) + 1,記帳區!$K:$K,"<=" & EOMONTH(L$2, 0),記帳區!$D:$D,$D23) -> 0 | M23: =SUMIFS(記帳區!$F:$F,記帳區!$K:$K,">=" & EOMONTH(M$2,-1) + 1,記帳區!$K:$K,"<=" & EOMONTH(M$2, 0),記帳區!$D:$D,$D23) -> 0 | N23: =SUMIFS(記帳區!$F:$F,記帳區!$K:$K,">=" & EOMONTH(N$2,-1) + 1,記帳區!$K:$K,"<=" & EOMONTH(N$2, 0),記帳區!$D:$D,$D23) -> 0 | ... S23: =SUMIFS(記帳區!$F:$F,記帳區!$K:$K,">=" & EOMONTH(S$2,-1) + 1,記帳區!$K:$K,"<=" & EOMONTH(S$2, 0),記帳區!$D:$D,$D23) -> 0
D24: 外食 | G24: =SUMIFS(記帳區!$F:$F,記帳區!$K:$K,">=" & EOMONTH(G$2,-1) + 1,記帳區!$K:$K,"<=" & EOMONTH(G$2, 0),記帳區!$E:$E,$D24) -> -250 | H24: =SUMIFS(記帳區!$F:$F,記帳區!$K:$K,">=" & EOMONTH(H$2,-1) + 1,記帳區!$K:$K,"<=" & EOMONTH(H$2, 0),記帳區!$E:$E,$D24) -> -508 | I24: =SUMIFS(記帳區!$F:$F,記帳區!$K:$K,">=" & EOMONTH(I$2,-1) + 1,記帳區!$K:$K,"<=" & EOMONTH(I$2, 0),記帳區!$E:$E,$D24) -> 0 | J24: =SUMIFS(記帳區!$F:$F,記帳區!$K:$K,">=" & EOMONTH(J$2,-1) + 1,記帳區!$K:$K,"<=" & EOMONTH(J$2, 0),記帳區!$E:$E,$D24) -> 0 | K24: =SUMIFS(記帳區!$F:$F,記帳區!$K:$K,">=" & EOMONTH(K$2,-1) + 1,記帳區!$K:$K,"<=" & EOMONTH(K$2, 0),記帳區!$E:$E,$D24) -> 0 | L24: =SUMIFS(記帳區!$F:$F,記帳區!$K:$K,">=" & EOMONTH(L$2,-1) + 1,記帳區!$K:$K,"<=" & EOMONTH(L$2, 0),記帳區!$E:$E,$D24) -> 0 | M24: =SUMIFS(記帳區!$F:$F,記帳區!$K:$K,">=" & EOMONTH(M$2,-1) + 1,記帳區!$K:$K,"<=" & EOMONTH(M$2, 0),記帳區!$E:$E,$D24) -> 0 | N24: =SUMIFS(記帳區!$F:$F,記帳區!$K:$K,">=" & EOMONTH(N$2,-1) + 1,記帳區!$K:$K,"<=" & EOMONTH(N$2, 0),記帳區!$E:$E,$D24) -> 0 | ... S24: =SUMIFS(記帳區!$F:$F,記帳區!$K:$K,">=" & EOMONTH(S$2,-1) + 1,記帳區!$K:$K,"<=" & EOMONTH(S$2, 0),記帳區!$E:$E,$D24) -> 0
D25: 食材 | G25: =SUMIFS(記帳區!$F:$F,記帳區!$K:$K,">=" & EOMONTH(G$2,-1) + 1,記帳區!$K:$K,"<=" & EOMONTH(G$2, 0),記帳區!$E:$E,$D25) -> -174 | H25: =SUMIFS(記帳區!$F:$F,記帳區!$K:$K,">=" & EOMONTH(H$2,-1) + 1,記帳區!$K:$K,"<=" & EOMONTH(H$2, 0),記帳區!$E:$E,$D25) -> 0 | I25: =SUMIFS(記帳區!$F:$F,記帳區!$K:$K,">=" & EOMONTH(I$2,-1) + 1,記帳區!$K:$K,"<=" & EOMONTH(I$2, 0),記帳區!$E:$E,$D25) -> 0 | J25: =SUMIFS(記帳區!$F:$F,記帳區!$K:$K,">=" & EOMONTH(J$2,-1) + 1,記帳區!$K:$K,"<=" & EOMONTH(J$2, 0),記帳區!$E:$E,$D25) -> 0 | K25: =SUMIFS(記帳區!$F:$F,記帳區!$K:$K,">=" & EOMONTH(K$2,-1) + 1,記帳區!$K:$K,"<=" & EOMONTH(K$2, 0),記帳區!$E:$E,$D25) -> 0 | L25: =SUMIFS(記帳區!$F:$F,記帳區!$K:$K,">=" & EOMONTH(L$2,-1) + 1,記帳區!$K:$K,"<=" & EOMONTH(L$2, 0),記帳區!$E:$E,$D25) -> 0 | M25: =SUMIFS(記帳區!$F:$F,記帳區!$K:$K,">=" & EOMONTH(M$2,-1) + 1,記帳區!$K:$K,"<=" & EOMONTH(M$2, 0),記帳區!$E:$E,$D25) -> 0 | N25: =SUMIFS(記帳區!$F:$F,記帳區!$K:$K,">=" & EOMONTH(N$2,-1) + 1,記帳區!$K:$K,"<=" & EOMONTH(N$2, 0),記帳區!$E:$E,$D25) -> 0 | ... S25: =SUMIFS(記帳區!$F:$F,記帳區!$K:$K,">=" & EOMONTH(S$2,-1) + 1,記帳區!$K:$K,"<=" & EOMONTH(S$2, 0),記帳區!$E:$E,$D25) -> 0
D26: 衣 | G26: =SUMIFS(記帳區!$F:$F,記帳區!$K:$K,">=" & EOMONTH(G$2,-1) + 1,記帳區!$K:$K,"<=" & EOMONTH(G$2, 0),記帳區!$D:$D,$D26) -> 0 | H26: =SUMIFS(記帳區!$F:$F,記帳區!$K:$K,">=" & EOMONTH(H$2,-1) + 1,記帳區!$K:$K,"<=" & EOMONTH(H$2, 0),記帳區!$D:$D,$D26) -> 0 | I26: =SUMIFS(記帳區!$F:$F,記帳區!$K:$K,">=" & EOMONTH(I$2,-1) + 1,記帳區!$K:$K,"<=" & EOMONTH(I$2, 0),記帳區!$D:$D,$D26) -> 0 | J26: =SUMIFS(記帳區!$F:$F,記帳區!$K:$K,">=" & EOMONTH(J$2,-1) + 1,記帳區!$K:$K,"<=" & EOMONTH(J$2, 0),記帳區!$D:$D,$D26) -> 0 | K26: =SUMIFS(記帳區!$F:$F,記帳區!$K:$K,">=" & EOMONTH(K$2,-1) + 1,記帳區!$K:$K,"<=" & EOMONTH(K$2, 0),記帳區!$D:$D,$D26) -> 0 | L26: =SUMIFS(記帳區!$F:$F,記帳區!$K:$K,">=" & EOMONTH(L$2,-1) + 1,記帳區!$K:$K,"<=" & EOMONTH(L$2, 0),記帳區!$D:$D,$D26) -> 0 | M26: =SUMIFS(記帳區!$F:$F,記帳區!$K:$K,">=" & EOMONTH(M$2,-1) + 1,記帳區!$K:$K,"<=" & EOMONTH(M$2, 0),記帳區!$D:$D,$D26) -> 0 | N26: =SUMIFS(記帳區!$F:$F,記帳區!$K:$K,">=" & EOMONTH(N$2,-1) + 1,記帳區!$K:$K,"<=" & EOMONTH(N$2, 0),記帳區!$D:$D,$D26) -> 0 | ... S26: =SUMIFS(記帳區!$F:$F,記帳區!$K:$K,">=" & EOMONTH(S$2,-1) + 1,記帳區!$K:$K,"<=" & EOMONTH(S$2, 0),記帳區!$D:$D,$D26) -> 0
D27: 治裝 | G27: =SUMIFS(記帳區!$F:$F,記帳區!$K:$K,">=" & EOMONTH(G$2,-1) + 1,記帳區!$K:$K,"<=" & EOMONTH(G$2, 0),記帳區!$E:$E,$D27) -> 0 | H27: =SUMIFS(記帳區!$F:$F,記帳區!$K:$K,">=" & EOMONTH(H$2,-1) + 1,記帳區!$K:$K,"<=" & EOMONTH(H$2, 0),記帳區!$E:$E,$D27) -> 0 | I27: =SUMIFS(記帳區!$F:$F,記帳區!$K:$K,">=" & EOMONTH(I$2,-1) + 1,記帳區!$K:$K,"<=" & EOMONTH(I$2, 0),記帳區!$E:$E,$D27) -> 0 | J27: =SUMIFS(記帳區!$F:$F,記帳區!$K:$K,">=" & EOMONTH(J$2,-1) + 1,記帳區!$K:$K,"<=" & EOMONTH(J$2, 0),記帳區!$E:$E,$D27) -> 0 | K27: =SUMIFS(記帳區!$F:$F,記帳區!$K:$K,">=" & EOMONTH(K$2,-1) + 1,記帳區!$K:$K,"<=" & EOMONTH(K$2, 0),記帳區!$E:$E,$D27) -> 0 | L27: =SUMIFS(記帳區!$F:$F,記帳區!$K:$K,">=" & EOMONTH(L$2,-1) + 1,記帳區!$K:$K,"<=" & EOMONTH(L$2, 0),記帳區!$E:$E,$D27) -> 0 | M27: =SUMIFS(記帳區!$F:$F,記帳區!$K:$K,">=" & EOMONTH(M$2,-1) + 1,記帳區!$K:$K,"<=" & EOMONTH(M$2, 0),記帳區!$E:$E,$D27) -> 0 | N27: =SUMIFS(記帳區!$F:$F,記帳區!$K:$K,">=" & EOMONTH(N$2,-1) + 1,記帳區!$K:$K,"<=" & EOMONTH(N$2, 0),記帳區!$E:$E,$D27) -> 0 | ... S27: =SUMIFS(記帳區!$F:$F,記帳區!$K:$K,">=" & EOMONTH(S$2,-1) + 1,記帳區!$K:$K,"<=" & EOMONTH(S$2, 0),記帳區!$E:$E,$D27) -> 0
D28: 美容美髮 | G28: =SUMIFS(記帳區!$F:$F,記帳區!$K:$K,">=" & EOMONTH(G$2,-1) + 1,記帳區!$K:$K,"<=" & EOMONTH(G$2, 0),記帳區!$E:$E,$D28) -> 0 | H28: =SUMIFS(記帳區!$F:$F,記帳區!$K:$K,">=" & EOMONTH(H$2,-1) + 1,記帳區!$K:$K,"<=" & EOMONTH(H$2, 0),記帳區!$E:$E,$D28) -> 0 | I28: =SUMIFS(記帳區!$F:$F,記帳區!$K:$K,">=" & EOMONTH(I$2,-1) + 1,記帳區!$K:$K,"<=" & EOMONTH(I$2, 0),記帳區!$E:$E,$D28) -> 0 | J28: =SUMIFS(記帳區!$F:$F,記帳區!$K:$K,">=" & EOMONTH(J$2,-1) + 1,記帳區!$K:$K,"<=" & EOMONTH(J$2, 0),記帳區!$E:$E,$D28) -> 0 | K28: =SUMIFS(記帳區!$F:$F,記帳區!$K:$K,">=" & EOMONTH(K$2,-1) + 1,記帳區!$K:$K,"<=" & EOMONTH(K$2, 0),記帳區!$E:$E,$D28) -> 0 | L28: =SUMIFS(記帳區!$F:$F,記帳區!$K:$K,">=" & EOMONTH(L$2,-1) + 1,記帳區!$K:$K,"<=" & EOMONTH(L$2, 0),記帳區!$E:$E,$D28) -> 0 | M28: =SUMIFS(記帳區!$F:$F,記帳區!$K:$K,">=" & EOMONTH(M$2,-1) + 1,記帳區!$K:$K,"<=" & EOMONTH(M$2, 0),記帳區!$E:$E,$D28) -> 0 | N28: =SUMIFS(記帳區!$F:$F,記帳區!$K:$K,">=" & EOMONTH(N$2,-1) + 1,記帳區!$K:$K,"<=" & EOMONTH(N$2, 0),記帳區!$E:$E,$D28) -> 0 | ... S28: =SUMIFS(記帳區!$F:$F,記帳區!$K:$K,">=" & EOMONTH(S$2,-1) + 1,記帳區!$K:$K,"<=" & EOMONTH(S$2, 0),記帳區!$E:$E,$D28) -> 0
D29: 住 | G29: =SUMIFS(記帳區!$F:$F,記帳區!$K:$K,">=" & EOMONTH(G$2,-1) + 1,記帳區!$K:$K,"<=" & EOMONTH(G$2, 0),記帳區!$D:$D,$D29) -> -130 | H29: =SUMIFS(記帳區!$F:$F,記帳區!$K:$K,">=" & EOMONTH(H$2,-1) + 1,記帳區!$K:$K,"<=" & EOMONTH(H$2, 0),記帳區!$D:$D,$D29) -> 0 | I29: =SUMIFS(記帳區!$F:$F,記帳區!$K:$K,">=" & EOMONTH(I$2,-1) + 1,記帳區!$K:$K,"<=" & EOMONTH(I$2, 0),記帳區!$D:$D,$D29) -> 0 | J29: =SUMIFS(記帳區!$F:$F,記帳區!$K:$K,">=" & EOMONTH(J$2,-1) + 1,記帳區!$K:$K,"<=" & EOMONTH(J$2, 0),記帳區!$D:$D,$D29) -> 0 | K29: =SUMIFS(記帳區!$F:$F,記帳區!$K:$K,">=" & EOMONTH(K$2,-1) + 1,記帳區!$K:$K,"<=" & EOMONTH(K$2, 0),記帳區!$D:$D,$D29) -> 0 | L29: =SUMIFS(記帳區!$F:$F,記帳區!$K:$K,">=" & EOMONTH(L$2,-1) + 1,記帳區!$K:$K,"<=" & EOMONTH(L$2, 0),記帳區!$D:$D,$D29) -> 0 | M29: =SUMIFS(記帳區!$F:$F,記帳區!$K:$K,">=" & EOMONTH(M$2,-1) + 1,記帳區!$K:$K,"<=" & EOMONTH(M$2, 0),記帳區!$D:$D,$D29) -> 0 | N29: =SUMIFS(記帳區!$F:$F,記帳區!$K:$K,">=" & EOMONTH(N$2,-1) + 1,記帳區!$K:$K,"<=" & EOMONTH(N$2, 0),記帳區!$D:$D,$D29) -> 0 | ... S29: =SUMIFS(記帳區!$F:$F,記帳區!$K:$K,">=" & EOMONTH(S$2,-1) + 1,記帳區!$K:$K,"<=" & EOMONTH(S$2, 0),記帳區!$D:$D,$D29) -> 0
D30: 日常用品 | G30: =SUMIFS(記帳區!$F:$F,記帳區!$K:$K,">=" & EOMONTH(G$2,-1) + 1,記帳區!$K:$K,"<=" & EOMONTH(G$2, 0),記帳區!$E:$E,$D30) -> -130 | H30: =SUMIFS(記帳區!$F:$F,記帳區!$K:$K,">=" & EOMONTH(H$2,-1) + 1,記帳區!$K:$K,"<=" & EOMONTH(H$2, 0),記帳區!$E:$E,$D30) -> 0 | I30: =SUMIFS(記帳區!$F:$F,記帳區!$K:$K,">=" & EOMONTH(I$2,-1) + 1,記帳區!$K:$K,"<=" & EOMONTH(I$2, 0),記帳區!$E:$E,$D30) -> 0 | J30: =SUMIFS(記帳區!$F:$F,記帳區!$K:$K,">=" & EOMONTH(J$2,-1) + 1,記帳區!$K:$K,"<=" & EOMONTH(J$2, 0),記帳區!$E:$E,$D30) -> 0 | K30: =SUMIFS(記帳區!$F:$F,記帳區!$K:$K,">=" & EOMONTH(K$2,-1) + 1,記帳區!$K:$K,"<=" & EOMONTH(K$2, 0),記帳區!$E:$E,$D30) -> 0 | L30: =SUMIFS(記帳區!$F:$F,記帳區!$K:$K,">=" & EOMONTH(L$2,-1) + 1,記帳區!$K:$K,"<=" & EOMONTH(L$2, 0),記帳區!$E:$E,$D30) -> 0 | M30: =SUMIFS(記帳區!$F:$F,記帳區!$K:$K,">=" & EOMONTH(M$2,-1) + 1,記帳區!$K:$K,"<=" & EOMONTH(M$2, 0),記帳區!$E:$E,$D30) -> 0 | N30: =SUMIFS(記帳區!$F:$F,記帳區!$K:$K,">=" & EOMONTH(N$2,-1) + 1,記帳區!$K:$K,"<=" & EOMONTH(N$2, 0),記帳區!$E:$E,$D30) -> 0 | ... S30: =SUMIFS(記帳區!$F:$F,記帳區!$K:$K,">=" & EOMONTH(S$2,-1) + 1,記帳區!$K:$K,"<=" & EOMONTH(S$2, 0),記帳區!$E:$E,$D30) -> 0
D31: 兔子 | G31: =SUMIFS(記帳區!$F:$F,記帳區!$K:$K,">=" & EOMONTH(G$2,-1) + 1,記帳區!$K:$K,"<=" & EOMONTH(G$2, 0),記帳區!$E:$E,$D31) -> 0 | H31: =SUMIFS(記帳區!$F:$F,記帳區!$K:$K,">=" & EOMONTH(H$2,-1) + 1,記帳區!$K:$K,"<=" & EOMONTH(H$2, 0),記帳區!$E:$E,$D31) -> 0 | I31: =SUMIFS(記帳區!$F:$F,記帳區!$K:$K,">=" & EOMONTH(I$2,-1) + 1,記帳區!$K:$K,"<=" & EOMONTH(I$2, 0),記帳區!$E:$E,$D31) -> 0 | J31: =SUMIFS(記帳區!$F:$F,記帳區!$K:$K,">=" & EOMONTH(J$2,-1) + 1,記帳區!$K:$K,"<=" & EOMONTH(J$2, 0),記帳區!$E:$E,$D31) -> 0 | K31: =SUMIFS(記帳區!$F:$F,記帳區!$K:$K,">=" & EOMONTH(K$2,-1) + 1,記帳區!$K:$K,"<=" & EOMONTH(K$2, 0),記帳區!$E:$E,$D31) -> 0 | L31: =SUMIFS(記帳區!$F:$F,記帳區!$K:$K,">=" & EOMONTH(L$2,-1) + 1,記帳區!$K:$K,"<=" & EOMONTH(L$2, 0),記帳區!$E:$E,$D31) -> 0 | M31: =SUMIFS(記帳區!$F:$F,記帳區!$K:$K,">=" & EOMONTH(M$2,-1) + 1,記帳區!$K:$K,"<=" & EOMONTH(M$2, 0),記帳區!$E:$E,$D31) -> 0 | N31: =SUMIFS(記帳區!$F:$F,記帳區!$K:$K,">=" & EOMONTH(N$2,-1) + 1,記帳區!$K:$K,"<=" & EOMONTH(N$2, 0),記帳區!$E:$E,$D31) -> 0 | ... S31: =SUMIFS(記帳區!$F:$F,記帳區!$K:$K,">=" & EOMONTH(S$2,-1) + 1,記帳區!$K:$K,"<=" & EOMONTH(S$2, 0),記帳區!$E:$E,$D31) -> 0
D32: 通話 | G32: =SUMIFS(記帳區!$F:$F,記帳區!$K:$K,">=" & EOMONTH(G$2,-1) + 1,記帳區!$K:$K,"<=" & EOMONTH(G$2, 0),記帳區!$E:$E,$D32) -> 0 | H32: =SUMIFS(記帳區!$F:$F,記帳區!$K:$K,">=" & EOMONTH(H$2,-1) + 1,記帳區!$K:$K,"<=" & EOMONTH(H$2, 0),記帳區!$E:$E,$D32) -> 0 | I32: =SUMIFS(記帳區!$F:$F,記帳區!$K:$K,">=" & EOMONTH(I$2,-1) + 1,記帳區!$K:$K,"<=" & EOMONTH(I$2, 0),記帳區!$E:$E,$D32) -> 0 | J32: =SUMIFS(記帳區!$F:$F,記帳區!$K:$K,">=" & EOMONTH(J$2,-1) + 1,記帳區!$K:$K,"<=" & EOMONTH(J$2, 0),記帳區!$E:$E,$D32) -> 0 | K32: =SUMIFS(記帳區!$F:$F,記帳區!$K:$K,">=" & EOMONTH(K$2,-1) + 1,記帳區!$K:$K,"<=" & EOMONTH(K$2, 0),記帳區!$E:$E,$D32) -> 0 | L32: =SUMIFS(記帳區!$F:$F,記帳區!$K:$K,">=" & EOMONTH(L$2,-1) + 1,記帳區!$K:$K,"<=" & EOMONTH(L$2, 0),記帳區!$E:$E,$D32) -> 0 | M32: =SUMIFS(記帳區!$F:$F,記帳區!$K:$K,">=" & EOMONTH(M$2,-1) + 1,記帳區!$K:$K,"<=" & EOMONTH(M$2, 0),記帳區!$E:$E,$D32) -> 0 | N32: =SUMIFS(記帳區!$F:$F,記帳區!$K:$K,">=" & EOMONTH(N$2,-1) + 1,記帳區!$K:$K,"<=" & EOMONTH(N$2, 0),記帳區!$E:$E,$D32) -> 0 | ... S32: =SUMIFS(記帳區!$F:$F,記帳區!$K:$K,">=" & EOMONTH(S$2,-1) + 1,記帳區!$K:$K,"<=" & EOMONTH(S$2, 0),記帳區!$E:$E,$D32) -> 0
D33: 網路費 | G33: =SUMIFS(記帳區!$F:$F,記帳區!$K:$K,">=" & EOMONTH(G$2,-1) + 1,記帳區!$K:$K,"<=" & EOMONTH(G$2, 0),記帳區!$E:$E,$D33) -> 0 | H33: =SUMIFS(記帳區!$F:$F,記帳區!$K:$K,">=" & EOMONTH(H$2,-1) + 1,記帳區!$K:$K,"<=" & EOMONTH(H$2, 0),記帳區!$E:$E,$D33) -> 0 | I33: =SUMIFS(記帳區!$F:$F,記帳區!$K:$K,">=" & EOMONTH(I$2,-1) + 1,記帳區!$K:$K,"<=" & EOMONTH(I$2, 0),記帳區!$E:$E,$D33) -> 0 | J33: =SUMIFS(記帳區!$F:$F,記帳區!$K:$K,">=" & EOMONTH(J$2,-1) + 1,記帳區!$K:$K,"<=" & EOMONTH(J$2, 0),記帳區!$E:$E,$D33) -> 0 | K33: =SUMIFS(記帳區!$F:$F,記帳區!$K:$K,">=" & EOMONTH(K$2,-1) + 1,記帳區!$K:$K,"<=" & EOMONTH(K$2, 0),記帳區!$E:$E,$D33) -> 0 | L33: =SUMIFS(記帳區!$F:$F,記帳區!$K:$K,">=" & EOMONTH(L$2,-1) + 1,記帳區!$K:$K,"<=" & EOMONTH(L$2, 0),記帳區!$E:$E,$D33) -> 0 | M33: =SUMIFS(記帳區!$F:$F,記帳區!$K:$K,">=" & EOMONTH(M$2,-1) + 1,記帳區!$K:$K,"<=" & EOMONTH(M$2, 0),記帳區!$E:$E,$D33) -> 0 | N33: =SUMIFS(記帳區!$F:$F,記帳區!$K:$K,">=" & EOMONTH(N$2,-1) + 1,記帳區!$K:$K,"<=" & EOMONTH(N$2, 0),記帳區!$E:$E,$D33) -> 0 | ... S33: =SUMIFS(記帳區!$F:$F,記帳區!$K:$K,">=" & EOMONTH(S$2,-1) + 1,記帳區!$K:$K,"<=" & EOMONTH(S$2, 0),記帳區!$E:$E,$D33) -> 0
D34: 水 | G34: =SUMIFS(記帳區!$F:$F,記帳區!$K:$K,">=" & EOMONTH(G$2,-1) + 1,記帳區!$K:$K,"<=" & EOMONTH(G$2, 0),記帳區!$E:$E,$D34) -> 0 | H34: =SUMIFS(記帳區!$F:$F,記帳區!$K:$K,">=" & EOMONTH(H$2,-1) + 1,記帳區!$K:$K,"<=" & EOMONTH(H$2, 0),記帳區!$E:$E,$D34) -> 0 | I34: =SUMIFS(記帳區!$F:$F,記帳區!$K:$K,">=" & EOMONTH(I$2,-1) + 1,記帳區!$K:$K,"<=" & EOMONTH(I$2, 0),記帳區!$E:$E,$D34) -> 0 | J34: =SUMIFS(記帳區!$F:$F,記帳區!$K:$K,">=" & EOMONTH(J$2,-1) + 1,記帳區!$K:$K,"<=" & EOMONTH(J$2, 0),記帳區!$E:$E,$D34) -> 0 | K34: =SUMIFS(記帳區!$F:$F,記帳區!$K:$K,">=" & EOMONTH(K$2,-1) + 1,記帳區!$K:$K,"<=" & EOMONTH(K$2, 0),記帳區!$E:$E,$D34) -> 0 | L34: =SUMIFS(記帳區!$F:$F,記帳區!$K:$K,">=" & EOMONTH(L$2,-1) + 1,記帳區!$K:$K,"<=" & EOMONTH(L$2, 0),記帳區!$E:$E,$D34) -> 0 | M34: =SUMIFS(記帳區!$F:$F,記帳區!$K:$K,">=" & EOMONTH(M$2,-1) + 1,記帳區!$K:$K,"<=" & EOMONTH(M$2, 0),記帳區!$E:$E,$D34) -> 0 | N34: =SUMIFS(記帳區!$F:$F,記帳區!$K:$K,">=" & EOMONTH(N$2,-1) + 1,記帳區!$K:$K,"<=" & EOMONTH(N$2, 0),記帳區!$E:$E,$D34) -> 0 | ... S34: =SUMIFS(記帳區!$F:$F,記帳區!$K:$K,">=" & EOMONTH(S$2,-1) + 1,記帳區!$K:$K,"<=" & EOMONTH(S$2, 0),記帳區!$E:$E,$D34) -> 0
D35: 電 | G35: =SUMIFS(記帳區!$F:$F,記帳區!$K:$K,">=" & EOMONTH(G$2,-1) + 1,記帳區!$K:$K,"<=" & EOMONTH(G$2, 0),記帳區!$E:$E,$D35) -> 0 | H35: =SUMIFS(記帳區!$F:$F,記帳區!$K:$K,">=" & EOMONTH(H$2,-1) + 1,記帳區!$K:$K,"<=" & EOMONTH(H$2, 0),記帳區!$E:$E,$D35) -> 0 | I35: =SUMIFS(記帳區!$F:$F,記帳區!$K:$K,">=" & EOMONTH(I$2,-1) + 1,記帳區!$K:$K,"<=" & EOMONTH(I$2, 0),記帳區!$E:$E,$D35) -> 0 | J35: =SUMIFS(記帳區!$F:$F,記帳區!$K:$K,">=" & EOMONTH(J$2,-1) + 1,記帳區!$K:$K,"<=" & EOMONTH(J$2, 0),記帳區!$E:$E,$D35) -> 0 | K35: =SUMIFS(記帳區!$F:$F,記帳區!$K:$K,">=" & EOMONTH(K$2,-1) + 1,記帳區!$K:$K,"<=" & EOMONTH(K$2, 0),記帳區!$E:$E,$D35) -> 0 | L35: =SUMIFS(記帳區!$F:$F,記帳區!$K:$K,">=" & EOMONTH(L$2,-1) + 1,記帳區!$K:$K,"<=" & EOMONTH(L$2, 0),記帳區!$E:$E,$D35) -> 0 | M35: =SUMIFS(記帳區!$F:$F,記帳區!$K:$K,">=" & EOMONTH(M$2,-1) + 1,記帳區!$K:$K,"<=" & EOMONTH(M$2, 0),記帳區!$E:$E,$D35) -> 0 | N35: =SUMIFS(記帳區!$F:$F,記帳區!$K:$K,">=" & EOMONTH(N$2,-1) + 1,記帳區!$K:$K,"<=" & EOMONTH(N$2, 0),記帳區!$E:$E,$D35) -> 0 | ... S35: =SUMIFS(記帳區!$F:$F,記帳區!$K:$K,">=" & EOMONTH(S$2,-1) + 1,記帳區!$K:$K,"<=" & EOMONTH(S$2, 0),記帳區!$E:$E,$D35) -> 0
D36: 瓦斯 | G36: =SUMIFS(記帳區!$F:$F,記帳區!$K:$K,">=" & EOMONTH(G$2,-1) + 1,記帳區!$K:$K,"<=" & EOMONTH(G$2, 0),記帳區!$E:$E,$D36) -> 0 | H36: =SUMIFS(記帳區!$F:$F,記帳區!$K:$K,">=" & EOMONTH(H$2,-1) + 1,記帳區!$K:$K,"<=" & EOMONTH(H$2, 0),記帳區!$E:$E,$D36) -> 0 | I36: =SUMIFS(記帳區!$F:$F,記帳區!$K:$K,">=" & EOMONTH(I$2,-1) + 1,記帳區!$K:$K,"<=" & EOMONTH(I$2, 0),記帳區!$E:$E,$D36) -> 0 | J36: =SUMIFS(記帳區!$F:$F,記帳區!$K:$K,">=" & EOMONTH(J$2,-1) + 1,記帳區!$K:$K,"<=" & EOMONTH(J$2, 0),記帳區!$E:$E,$D36) -> 0 | K36: =SUMIFS(記帳區!$F:$F,記帳區!$K:$K,">=" & EOMONTH(K$2,-1) + 1,記帳區!$K:$K,"<=" & EOMONTH(K$2, 0),記帳區!$E:$E,$D36) -> 0 | L36: =SUMIFS(記帳區!$F:$F,記帳區!$K:$K,">=" & EOMONTH(L$2,-1) + 1,記帳區!$K:$K,"<=" & EOMONTH(L$2, 0),記帳區!$E:$E,$D36) -> 0 | M36: =SUMIFS(記帳區!$F:$F,記帳區!$K:$K,">=" & EOMONTH(M$2,-1) + 1,記帳區!$K:$K,"<=" & EOMONTH(M$2, 0),記帳區!$E:$E,$D36) -> 0 | N36: =SUMIFS(記帳區!$F:$F,記帳區!$K:$K,">=" & EOMONTH(N$2,-1) + 1,記帳區!$K:$K,"<=" & EOMONTH(N$2, 0),記帳區!$E:$E,$D36) -> 0 | ... S36: =SUMIFS(記帳區!$F:$F,記帳區!$K:$K,">=" & EOMONTH(S$2,-1) + 1,記帳區!$K:$K,"<=" & EOMONTH(S$2, 0),記帳區!$E:$E,$D36) -> 0
D37: 行 | G37: =SUMIFS(記帳區!$F:$F,記帳區!$K:$K,">=" & EOMONTH(G$2,-1) + 1,記帳區!$K:$K,"<=" & EOMONTH(G$2, 0),記帳區!$D:$D,$D37) -> -2530 | H37: =SUMIFS(記帳區!$F:$F,記帳區!$K:$K,">=" & EOMONTH(H$2,-1) + 1,記帳區!$K:$K,"<=" & EOMONTH(H$2, 0),記帳區!$D:$D,$D37) -> 0 | I37: =SUMIFS(記帳區!$F:$F,記帳區!$K:$K,">=" & EOMONTH(I$2,-1) + 1,記帳區!$K:$K,"<=" & EOMONTH(I$2, 0),記帳區!$D:$D,$D37) -> 0 | J37: =SUMIFS(記帳區!$F:$F,記帳區!$K:$K,">=" & EOMONTH(J$2,-1) + 1,記帳區!$K:$K,"<=" & EOMONTH(J$2, 0),記帳區!$D:$D,$D37) -> 0 | K37: =SUMIFS(記帳區!$F:$F,記帳區!$K:$K,">=" & EOMONTH(K$2,-1) + 1,記帳區!$K:$K,"<=" & EOMONTH(K$2, 0),記帳區!$D:$D,$D37) -> 0 | L37: =SUMIFS(記帳區!$F:$F,記帳區!$K:$K,">=" & EOMONTH(L$2,-1) + 1,記帳區!$K:$K,"<=" & EOMONTH(L$2, 0),記帳區!$D:$D,$D37) -> 0 | M37: =SUMIFS(記帳區!$F:$F,記帳區!$K:$K,">=" & EOMONTH(M$2,-1) + 1,記帳區!$K:$K,"<=" & EOMONTH(M$2, 0),記帳區!$D:$D,$D37) -> 0 | N37: =SUMIFS(記帳區!$F:$F,記帳區!$K:$K,">=" & EOMONTH(N$2,-1) + 1,記帳區!$K:$K,"<=" & EOMONTH(N$2, 0),記帳區!$D:$D,$D37) -> 0 | ... S37: =SUMIFS(記帳區!$F:$F,記帳區!$K:$K,">=" & EOMONTH(S$2,-1) + 1,記帳區!$K:$K,"<=" & EOMONTH(S$2, 0),記帳區!$D:$D,$D37) -> 0
D38: 停車費 | G38: =SUMIFS(記帳區!$F:$F,記帳區!$K:$K,">=" & EOMONTH(G$2,-1) + 1,記帳區!$K:$K,"<=" & EOMONTH(G$2, 0),記帳區!$E:$E,$D38) -> 0 | H38: =SUMIFS(記帳區!$F:$F,記帳區!$K:$K,">=" & EOMONTH(H$2,-1) + 1,記帳區!$K:$K,"<=" & EOMONTH(H$2, 0),記帳區!$E:$E,$D38) -> 0 | I38: =SUMIFS(記帳區!$F:$F,記帳區!$K:$K,">=" & EOMONTH(I$2,-1) + 1,記帳區!$K:$K,"<=" & EOMONTH(I$2, 0),記帳區!$E:$E,$D38) -> 0 | J38: =SUMIFS(記帳區!$F:$F,記帳區!$K:$K,">=" & EOMONTH(J$2,-1) + 1,記帳區!$K:$K,"<=" & EOMONTH(J$2, 0),記帳區!$E:$E,$D38) -> 0 | K38: =SUMIFS(記帳區!$F:$F,記帳區!$K:$K,">=" & EOMONTH(K$2,-1) + 1,記帳區!$K:$K,"<=" & EOMONTH(K$2, 0),記帳區!$E:$E,$D38) -> 0 | L38: =SUMIFS(記帳區!$F:$F,記帳區!$K:$K,">=" & EOMONTH(L$2,-1) + 1,記帳區!$K:$K,"<=" & EOMONTH(L$2, 0),記帳區!$E:$E,$D38) -> 0 | M38: =SUMIFS(記帳區!$F:$F,記帳區!$K:$K,">=" & EOMONTH(M$2,-1) + 1,記帳區!$K:$K,"<=" & EOMONTH(M$2, 0),記帳區!$E:$E,$D38) -> 0 | N38: =SUMIFS(記帳區!$F:$F,記帳區!$K:$K,">=" & EOMONTH(N$2,-1) + 1,記帳區!$K:$K,"<=" & EOMONTH(N$2, 0),記帳區!$E:$E,$D38) -> 0 | ... S38: =SUMIFS(記帳區!$F:$F,記帳區!$K:$K,">=" & EOMONTH(S$2,-1) + 1,記帳區!$K:$K,"<=" & EOMONTH(S$2, 0),記帳區!$E:$E,$D38) -> 0
D39: 加油費 | G39: =SUMIFS(記帳區!$F:$F,記帳區!$K:$K,">=" & EOMONTH(G$2,-1) + 1,記帳區!$K:$K,"<=" & EOMONTH(G$2, 0),記帳區!$E:$E,$D39) -> -1340 | H39: =SUMIFS(記帳區!$F:$F,記帳區!$K:$K,">=" & EOMONTH(H$2,-1) + 1,記帳區!$K:$K,"<=" & EOMONTH(H$2, 0),記帳區!$E:$E,$D39) -> 0 | I39: =SUMIFS(記帳區!$F:$F,記帳區!$K:$K,">=" & EOMONTH(I$2,-1) + 1,記帳區!$K:$K,"<=" & EOMONTH(I$2, 0),記帳區!$E:$E,$D39) -> 0 | J39: =SUMIFS(記帳區!$F:$F,記帳區!$K:$K,">=" & EOMONTH(J$2,-1) + 1,記帳區!$K:$K,"<=" & EOMONTH(J$2, 0),記帳區!$E:$E,$D39) -> 0 | K39: =SUMIFS(記帳區!$F:$F,記帳區!$K:$K,">=" & EOMONTH(K$2,-1) + 1,記帳區!$K:$K,"<=" & EOMONTH(K$2, 0),記帳區!$E:$E,$D39) -> 0 | L39: =SUMIFS(記帳區!$F:$F,記帳區!$K:$K,">=" & EOMONTH(L$2,-1) + 1,記帳區!$K:$K,"<=" & EOMONTH(L$2, 0),記帳區!$E:$E,$D39) -> 0 | M39: =SUMIFS(記帳區!$F:$F,記帳區!$K:$K,">=" & EOMONTH(M$2,-1) + 1,記帳區!$K:$K,"<=" & EOMONTH(M$2, 0),記帳區!$E:$E,$D39) -> 0 | N39: =SUMIFS(記帳區!$F:$F,記帳區!$K:$K,">=" & EOMONTH(N$2,-1) + 1,記帳區!$K:$K,"<=" & EOMONTH(N$2, 0),記帳區!$E:$E,$D39) -> 0 | ... S39: =SUMIFS(記帳區!$F:$F,記帳區!$K:$K,">=" & EOMONTH(S$2,-1) + 1,記帳區!$K:$K,"<=" & EOMONTH(S$2, 0),記帳區!$E:$E,$D39) -> 0
D40: 過路費 | G40: =SUMIFS(記帳區!$F:$F,記帳區!$K:$K,">=" & EOMONTH(G$2,-1) + 1,記帳區!$K:$K,"<=" & EOMONTH(G$2, 0),記帳區!$E:$E,$D40) -> 0 | H40: =SUMIFS(記帳區!$F:$F,記帳區!$K:$K,">=" & EOMONTH(H$2,-1) + 1,記帳區!$K:$K,"<=" & EOMONTH(H$2, 0),記帳區!$E:$E,$D40) -> 0 | I40: =SUMIFS(記帳區!$F:$F,記帳區!$K:$K,">=" & EOMONTH(I$2,-1) + 1,記帳區!$K:$K,"<=" & EOMONTH(I$2, 0),記帳區!$E:$E,$D40) -> 0 | J40: =SUMIFS(記帳區!$F:$F,記帳區!$K:$K,">=" & EOMONTH(J$2,-1) + 1,記帳區!$K:$K,"<=" & EOMONTH(J$2, 0),記帳區!$E:$E,$D40) -> 0 | K40: =SUMIFS(記帳區!$F:$F,記帳區!$K:$K,">=" & EOMONTH(K$2,-1) + 1,記帳區!$K:$K,"<=" & EOMONTH(K$2, 0),記帳區!$E:$E,$D40) -> 0 | L40: =SUMIFS(記帳區!$F:$F,記帳區!$K:$K,">=" & EOMONTH(L$2,-1) + 1,記帳區!$K:$K,"<=" & EOMONTH(L$2, 0),記帳區!$E:$E,$D40) -> 0 | M40: =SUMIFS(記帳區!$F:$F,記帳區!$K:$K,">=" & EOMONTH(M$2,-1) + 1,記帳區!$K:$K,"<=" & EOMONTH(M$2, 0),記帳區!$E:$E,$D40) -> 0 | N40: =SUMIFS(記帳區!$F:$F,記帳區!$K:$K,">=" & EOMONTH(N$2,-1) + 1,記帳區!$K:$K,"<=" & EOMONTH(N$2, 0),記帳區!$E:$E,$D40) -> 0 | ... S40: =SUMIFS(記帳區!$F:$F,記帳區!$K:$K,">=" & EOMONTH(S$2,-1) + 1,記帳區!$K:$K,"<=" & EOMONTH(S$2, 0),記帳區!$E:$E,$D40) -> 0
D41: 保養 | G41: =SUMIFS(記帳區!$F:$F,記帳區!$K:$K,">=" & EOMONTH(G$2,-1) + 1,記帳區!$K:$K,"<=" & EOMONTH(G$2, 0),記帳區!$E:$E,$D41) -> 0 | H41: =SUMIFS(記帳區!$F:$F,記帳區!$K:$K,">=" & EOMONTH(H$2,-1) + 1,記帳區!$K:$K,"<=" & EOMONTH(H$2, 0),記帳區!$E:$E,$D41) -> 0 | I41: =SUMIFS(記帳區!$F:$F,記帳區!$K:$K,">=" & EOMONTH(I$2,-1) + 1,記帳區!$K:$K,"<=" & EOMONTH(I$2, 0),記帳區!$E:$E,$D41) -> 0 | J41: =SUMIFS(記帳區!$F:$F,記帳區!$K:$K,">=" & EOMONTH(J$2,-1) + 1,記帳區!$K:$K,"<=" & EOMONTH(J$2, 0),記帳區!$E:$E,$D41) -> 0 | K41: =SUMIFS(記帳區!$F:$F,記帳區!$K:$K,">=" & EOMONTH(K$2,-1) + 1,記帳區!$K:$K,"<=" & EOMONTH(K$2, 0),記帳區!$E:$E,$D41) -> 0 | L41: =SUMIFS(記帳區!$F:$F,記帳區!$K:$K,">=" & EOMONTH(L$2,-1) + 1,記帳區!$K:$K,"<=" & EOMONTH(L$2, 0),記帳區!$E:$E,$D41) -> 0 | M41: =SUMIFS(記帳區!$F:$F,記帳區!$K:$K,">=" & EOMONTH(M$2,-1) + 1,記帳區!$K:$K,"<=" & EOMONTH(M$2, 0),記帳區!$E:$E,$D41) -> 0 | N41: =SUMIFS(記帳區!$F:$F,記帳區!$K:$K,">=" & EOMONTH(N$2,-1) + 1,記帳區!$K:$K,"<=" & EOMONTH(N$2, 0),記帳區!$E:$E,$D41) -> 0 | ... S41: =SUMIFS(記帳區!$F:$F,記帳區!$K:$K,">=" & EOMONTH(S$2,-1) + 1,記帳區!$K:$K,"<=" & EOMONTH(S$2, 0),記帳區!$E:$E,$D41) -> 0
D42: 大眾交通 | G42: =SUMIFS(記帳區!$F:$F,記帳區!$K:$K,">=" & EOMONTH(G$2,-1) + 1,記帳區!$K:$K,"<=" & EOMONTH(G$2, 0),記帳區!$E:$E,$D42) -> 0 | H42: =SUMIFS(記帳區!$F:$F,記帳區!$K:$K,">=" & EOMONTH(H$2,-1) + 1,記帳區!$K:$K,"<=" & EOMONTH(H$2, 0),記帳區!$E:$E,$D42) -> 0 | I42: =SUMIFS(記帳區!$F:$F,記帳區!$K:$K,">=" & EOMONTH(I$2,-1) + 1,記帳區!$K:$K,"<=" & EOMONTH(I$2, 0),記帳區!$E:$E,$D42) -> 0 | J42: =SUMIFS(記帳區!$F:$F,記帳區!$K:$K,">=" & EOMONTH(J$2,-1) + 1,記帳區!$K:$K,"<=" & EOMONTH(J$2, 0),記帳區!$E:$E,$D42) -> 0 | K42: =SUMIFS(記帳區!$F:$F,記帳區!$K:$K,">=" & EOMONTH(K$2,-1) + 1,記帳區!$K:$K,"<=" & EOMONTH(K$2, 0),記帳區!$E:$E,$D42) -> 0 | L42: =SUMIFS(記帳區!$F:$F,記帳區!$K:$K,">=" & EOMONTH(L$2,-1) + 1,記帳區!$K:$K,"<=" & EOMONTH(L$2, 0),記帳區!$E:$E,$D42) -> 0 | M42: =SUMIFS(記帳區!$F:$F,記帳區!$K:$K,">=" & EOMONTH(M$2,-1) + 1,記帳區!$K:$K,"<=" & EOMONTH(M$2, 0),記帳區!$E:$E,$D42) -> 0 | N42: =SUMIFS(記帳區!$F:$F,記帳區!$K:$K,">=" & EOMONTH(N$2,-1) + 1,記帳區!$K:$K,"<=" & EOMONTH(N$2, 0),記帳區!$E:$E,$D42) -> 0 | ... S42: =SUMIFS(記帳區!$F:$F,記帳區!$K:$K,">=" & EOMONTH(S$2,-1) + 1,記帳區!$K:$K,"<=" & EOMONTH(S$2, 0),記帳區!$E:$E,$D42) -> 0
D43: 政府規費 | G43: =SUMIFS(記帳區!$F:$F,記帳區!$K:$K,">=" & EOMONTH(G$2,-1) + 1,記帳區!$K:$K,"<=" & EOMONTH(G$2, 0),記帳區!$D:$D,$D43) -> 0 | H43: =SUMIFS(記帳區!$F:$F,記帳區!$K:$K,">=" & EOMONTH(H$2,-1) + 1,記帳區!$K:$K,"<=" & EOMONTH(H$2, 0),記帳區!$D:$D,$D43) -> 0 | I43: =SUMIFS(記帳區!$F:$F,記帳區!$K:$K,">=" & EOMONTH(I$2,-1) + 1,記帳區!$K:$K,"<=" & EOMONTH(I$2, 0),記帳區!$D:$D,$D43) -> 0 | J43: =SUMIFS(記帳區!$F:$F,記帳區!$K:$K,">=" & EOMONTH(J$2,-1) + 1,記帳區!$K:$K,"<=" & EOMONTH(J$2, 0),記帳區!$D:$D,$D43) -> 0 | K43: =SUMIFS(記帳區!$F:$F,記帳區!$K:$K,">=" & EOMONTH(K$2,-1) + 1,記帳區!$K:$K,"<=" & EOMONTH(K$2, 0),記帳區!$D:$D,$D43) -> 0 | L43: =SUMIFS(記帳區!$F:$F,記帳區!$K:$K,">=" & EOMONTH(L$2,-1) + 1,記帳區!$K:$K,"<=" & EOMONTH(L$2, 0),記帳區!$D:$D,$D43) -> 0 | M43: =SUMIFS(記帳區!$F:$F,記帳區!$K:$K,">=" & EOMONTH(M$2,-1) + 1,記帳區!$K:$K,"<=" & EOMONTH(M$2, 0),記帳區!$D:$D,$D43) -> 0 | N43: =SUMIFS(記帳區!$F:$F,記帳區!$K:$K,">=" & EOMONTH(N$2,-1) + 1,記帳區!$K:$K,"<=" & EOMONTH(N$2, 0),記帳區!$D:$D,$D43) -> 0 | ... S43: =SUMIFS(記帳區!$F:$F,記帳區!$K:$K,">=" & EOMONTH(S$2,-1) + 1,記帳區!$K:$K,"<=" & EOMONTH(S$2, 0),記帳區!$D:$D,$D43) -> 0
D44: 所得稅 | G44: =SUMIFS(記帳區!$F:$F,記帳區!$K:$K,">=" & EOMONTH(G$2,-1) + 1,記帳區!$K:$K,"<=" & EOMONTH(G$2, 0),記帳區!$E:$E,$D44) -> 0 | H44: =SUMIFS(記帳區!$F:$F,記帳區!$K:$K,">=" & EOMONTH(H$2,-1) + 1,記帳區!$K:$K,"<=" & EOMONTH(H$2, 0),記帳區!$E:$E,$D44) -> 0 | I44: =SUMIFS(記帳區!$F:$F,記帳區!$K:$K,">=" & EOMONTH(I$2,-1) + 1,記帳區!$K:$K,"<=" & EOMONTH(I$2, 0),記帳區!$E:$E,$D44) -> 0 | J44: =SUMIFS(記帳區!$F:$F,記帳區!$K:$K,">=" & EOMONTH(J$2,-1) + 1,記帳區!$K:$K,"<=" & EOMONTH(J$2, 0),記帳區!$E:$E,$D44) -> 0 | K44: =SUMIFS(記帳區!$F:$F,記帳區!$K:$K,">=" & EOMONTH(K$2,-1) + 1,記帳區!$K:$K,"<=" & EOMONTH(K$2, 0),記帳區!$E:$E,$D44) -> 0 | L44: =SUMIFS(記帳區!$F:$F,記帳區!$K:$K,">=" & EOMONTH(L$2,-1) + 1,記帳區!$K:$K,"<=" & EOMONTH(L$2, 0),記帳區!$E:$E,$D44) -> 0 | M44: =SUMIFS(記帳區!$F:$F,記帳區!$K:$K,">=" & EOMONTH(M$2,-1) + 1,記帳區!$K:$K,"<=" & EOMONTH(M$2, 0),記帳區!$E:$E,$D44) -> 0 | N44: =SUMIFS(記帳區!$F:$F,記帳區!$K:$K,">=" & EOMONTH(N$2,-1) + 1,記帳區!$K:$K,"<=" & EOMONTH(N$2, 0),記帳區!$E:$E,$D44) -> 0 | ... S44: =SUMIFS(記帳區!$F:$F,記帳區!$K:$K,">=" & EOMONTH(S$2,-1) + 1,記帳區!$K:$K,"<=" & EOMONTH(S$2, 0),記帳區!$E:$E,$D44) -> 0
D45: 牌照稅 | G45: =SUMIFS(記帳區!$F:$F,記帳區!$K:$K,">=" & EOMONTH(G$2,-1) + 1,記帳區!$K:$K,"<=" & EOMONTH(G$2, 0),記帳區!$E:$E,$D45) -> 0 | H45: =SUMIFS(記帳區!$F:$F,記帳區!$K:$K,">=" & EOMONTH(H$2,-1) + 1,記帳區!$K:$K,"<=" & EOMONTH(H$2, 0),記帳區!$E:$E,$D45) -> 0 | I45: =SUMIFS(記帳區!$F:$F,記帳區!$K:$K,">=" & EOMONTH(I$2,-1) + 1,記帳區!$K:$K,"<=" & EOMONTH(I$2, 0),記帳區!$E:$E,$D45) -> 0 | J45: =SUMIFS(記帳區!$F:$F,記帳區!$K:$K,">=" & EOMONTH(J$2,-1) + 1,記帳區!$K:$K,"<=" & EOMONTH(J$2, 0),記帳區!$E:$E,$D45) -> 0 | K45: =SUMIFS(記帳區!$F:$F,記帳區!$K:$K,">=" & EOMONTH(K$2,-1) + 1,記帳區!$K:$K,"<=" & EOMONTH(K$2, 0),記帳區!$E:$E,$D45) -> 0 | L45: =SUMIFS(記帳區!$F:$F,記帳區!$K:$K,">=" & EOMONTH(L$2,-1) + 1,記帳區!$K:$K,"<=" & EOMONTH(L$2, 0),記帳區!$E:$E,$D45) -> 0 | M45: =SUMIFS(記帳區!$F:$F,記帳區!$K:$K,">=" & EOMONTH(M$2,-1) + 1,記帳區!$K:$K,"<=" & EOMONTH(M$2, 0),記帳區!$E:$E,$D45) -> 0 | N45: =SUMIFS(記帳區!$F:$F,記帳區!$K:$K,">=" & EOMONTH(N$2,-1) + 1,記帳區!$K:$K,"<=" & EOMONTH(N$2, 0),記帳區!$E:$E,$D45) -> 0 | ... S45: =SUMIFS(記帳區!$F:$F,記帳區!$K:$K,">=" & EOMONTH(S$2,-1) + 1,記帳區!$K:$K,"<=" & EOMONTH(S$2, 0),記帳區!$E:$E,$D45) -> 0
D46: 燃料稅 | G46: =SUMIFS(記帳區!$F:$F,記帳區!$K:$K,">=" & EOMONTH(G$2,-1) + 1,記帳區!$K:$K,"<=" & EOMONTH(G$2, 0),記帳區!$E:$E,$D46) -> 0 | H46: =SUMIFS(記帳區!$F:$F,記帳區!$K:$K,">=" & EOMONTH(H$2,-1) + 1,記帳區!$K:$K,"<=" & EOMONTH(H$2, 0),記帳區!$E:$E,$D46) -> 0 | I46: =SUMIFS(記帳區!$F:$F,記帳區!$K:$K,">=" & EOMONTH(I$2,-1) + 1,記帳區!$K:$K,"<=" & EOMONTH(I$2, 0),記帳區!$E:$E,$D46) -> 0 | J46: =SUMIFS(記帳區!$F:$F,記帳區!$K:$K,">=" & EOMONTH(J$2,-1) + 1,記帳區!$K:$K,"<=" & EOMONTH(J$2, 0),記帳區!$E:$E,$D46) -> 0 | K46: =SUMIFS(記帳區!$F:$F,記帳區!$K:$K,">=" & EOMONTH(K$2,-1) + 1,記帳區!$K:$K,"<=" & EOMONTH(K$2, 0),記帳區!$E:$E,$D46) -> 0 | L46: =SUMIFS(記帳區!$F:$F,記帳區!$K:$K,">=" & EOMONTH(L$2,-1) + 1,記帳區!$K:$K,"<=" & EOMONTH(L$2, 0),記帳區!$E:$E,$D46) -> 0 | M46: =SUMIFS(記帳區!$F:$F,記帳區!$K:$K,">=" & EOMONTH(M$2,-1) + 1,記帳區!$K:$K,"<=" & EOMONTH(M$2, 0),記帳區!$E:$E,$D46) -> 0 | N46: =SUMIFS(記帳區!$F:$F,記帳區!$K:$K,">=" & EOMONTH(N$2,-1) + 1,記帳區!$K:$K,"<=" & EOMONTH(N$2, 0),記帳區!$E:$E,$D46) -> 0 | ... S46: =SUMIFS(記帳區!$F:$F,記帳區!$K:$K,">=" & EOMONTH(S$2,-1) + 1,記帳區!$K:$K,"<=" & EOMONTH(S$2, 0),記帳區!$E:$E,$D46) -> 0
D47: 勞健保 | G47: =SUMIFS(記帳區!$F:$F,記帳區!$K:$K,">=" & EOMONTH(G$2,-1) + 1,記帳區!$K:$K,"<=" & EOMONTH(G$2, 0),記帳區!$E:$E,$D47) -> 0 | H47: =SUMIFS(記帳區!$F:$F,記帳區!$K:$K,">=" & EOMONTH(H$2,-1) + 1,記帳區!$K:$K,"<=" & EOMONTH(H$2, 0),記帳區!$E:$E,$D47) -> 0 | I47: =SUMIFS(記帳區!$F:$F,記帳區!$K:$K,">=" & EOMONTH(I$2,-1) + 1,記帳區!$K:$K,"<=" & EOMONTH(I$2, 0),記帳區!$E:$E,$D47) -> 0 | J47: =SUMIFS(記帳區!$F:$F,記帳區!$K:$K,">=" & EOMONTH(J$2,-1) + 1,記帳區!$K:$K,"<=" & EOMONTH(J$2, 0),記帳區!$E:$E,$D47) -> 0 | K47: =SUMIFS(記帳區!$F:$F,記帳區!$K:$K,">=" & EOMONTH(K$2,-1) + 1,記帳區!$K:$K,"<=" & EOMONTH(K$2, 0),記帳區!$E:$E,$D47) -> 0 | L47: =SUMIFS(記帳區!$F:$F,記帳區!$K:$K,">=" & EOMONTH(L$2,-1) + 1,記帳區!$K:$K,"<=" & EOMONTH(L$2, 0),記帳區!$E:$E,$D47) -> 0 | M47: =SUMIFS(記帳區!$F:$F,記帳區!$K:$K,">=" & EOMONTH(M$2,-1) + 1,記帳區!$K:$K,"<=" & EOMONTH(M$2, 0),記帳區!$E:$E,$D47) -> 0 | N47: =SUMIFS(記帳區!$F:$F,記帳區!$K:$K,">=" & EOMONTH(N$2,-1) + 1,記帳區!$K:$K,"<=" & EOMONTH(N$2, 0),記帳區!$E:$E,$D47) -> 0 | ... S47: =SUMIFS(記帳區!$F:$F,記帳區!$K:$K,">=" & EOMONTH(S$2,-1) + 1,記帳區!$K:$K,"<=" & EOMONTH(S$2, 0),記帳區!$E:$E,$D47) -> 0
D48: 貸款 | G48: =SUMIFS(記帳區!$F:$F,記帳區!$K:$K,">=" & EOMONTH(G$2,-1) + 1,記帳區!$K:$K,"<=" & EOMONTH(G$2, 0),記帳區!$D:$D,$D48) -> -86669 | H48: =SUMIFS(記帳區!$F:$F,記帳區!$K:$K,">=" & EOMONTH(H$2,-1) + 1,記帳區!$K:$K,"<=" & EOMONTH(H$2, 0),記帳區!$D:$D,$D48) -> -86669 | I48: =SUMIFS(記帳區!$F:$F,記帳區!$K:$K,">=" & EOMONTH(I$2,-1) + 1,記帳區!$K:$K,"<=" & EOMONTH(I$2, 0),記帳區!$D:$D,$D48) -> 0 | J48: =SUMIFS(記帳區!$F:$F,記帳區!$K:$K,">=" & EOMONTH(J$2,-1) + 1,記帳區!$K:$K,"<=" & EOMONTH(J$2, 0),記帳區!$D:$D,$D48) -> 0 | K48: =SUMIFS(記帳區!$F:$F,記帳區!$K:$K,">=" & EOMONTH(K$2,-1) + 1,記帳區!$K:$K,"<=" & EOMONTH(K$2, 0),記帳區!$D:$D,$D48) -> 0 | L48: =SUMIFS(記帳區!$F:$F,記帳區!$K:$K,">=" & EOMONTH(L$2,-1) + 1,記帳區!$K:$K,"<=" & EOMONTH(L$2, 0),記帳區!$D:$D,$D48) -> 0 | M48: =SUMIFS(記帳區!$F:$F,記帳區!$K:$K,">=" & EOMONTH(M$2,-1) + 1,記帳區!$K:$K,"<=" & EOMONTH(M$2, 0),記帳區!$D:$D,$D48) -> 0 | N48: =SUMIFS(記帳區!$F:$F,記帳區!$K:$K,">=" & EOMONTH(N$2,-1) + 1,記帳區!$K:$K,"<=" & EOMONTH(N$2, 0),記帳區!$D:$D,$D48) -> 0 | ... S48: =SUMIFS(記帳區!$F:$F,記帳區!$K:$K,">=" & EOMONTH(S$2,-1) + 1,記帳區!$K:$K,"<=" & EOMONTH(S$2, 0),記帳區!$D:$D,$D48) -> 0
D49: 壓榨性債務 | G49: =SUMIFS(記帳區!$F:$F,記帳區!$K:$K,">=" & EOMONTH(G$2,-1) + 1,記帳區!$K:$K,"<=" & EOMONTH(G$2, 0),記帳區!$E:$E,$D49) -> -77669 | H49: =SUMIFS(記帳區!$F:$F,記帳區!$K:$K,">=" & EOMONTH(H$2,-1) + 1,記帳區!$K:$K,"<=" & EOMONTH(H$2, 0),記帳區!$E:$E,$D49) -> -77669 | I49: =SUMIFS(記帳區!$F:$F,記帳區!$K:$K,">=" & EOMONTH(I$2,-1) + 1,記帳區!$K:$K,"<=" & EOMONTH(I$2, 0),記帳區!$E:$E,$D49) -> 0 | J49: =SUMIFS(記帳區!$F:$F,記帳區!$K:$K,">=" & EOMONTH(J$2,-1) + 1,記帳區!$K:$K,"<=" & EOMONTH(J$2, 0),記帳區!$E:$E,$D49) -> 0 | K49: =SUMIFS(記帳區!$F:$F,記帳區!$K:$K,">=" & EOMONTH(K$2,-1) + 1,記帳區!$K:$K,"<=" & EOMONTH(K$2, 0),記帳區!$E:$E,$D49) -> 0 | L49: =SUMIFS(記帳區!$F:$F,記帳區!$K:$K,">=" & EOMONTH(L$2,-1) + 1,記帳區!$K:$K,"<=" & EOMONTH(L$2, 0),記帳區!$E:$E,$D49) -> 0 | M49: =SUMIFS(記帳區!$F:$F,記帳區!$K:$K,">=" & EOMONTH(M$2,-1) + 1,記帳區!$K:$K,"<=" & EOMONTH(M$2, 0),記帳區!$E:$E,$D49) -> 0 | N49: =SUMIFS(記帳區!$F:$F,記帳區!$K:$K,">=" & EOMONTH(N$2,-1) + 1,記帳區!$K:$K,"<=" & EOMONTH(N$2, 0),記帳區!$E:$E,$D49) -> 0 | ... S49: =SUMIFS(記帳區!$F:$F,記帳區!$K:$K,">=" & EOMONTH(S$2,-1) + 1,記帳區!$K:$K,"<=" & EOMONTH(S$2, 0),記帳區!$E:$E,$D49) -> 0
D50: 功能性債務 | G50: =SUMIFS(記帳區!$F:$F,記帳區!$K:$K,">=" & EOMONTH(G$2,-1) + 1,記帳區!$K:$K,"<=" & EOMONTH(G$2, 0),記帳區!$E:$E,$D50) -> -9000 | H50: =SUMIFS(記帳區!$F:$F,記帳區!$K:$K,">=" & EOMONTH(H$2,-1) + 1,記帳區!$K:$K,"<=" & EOMONTH(H$2, 0),記帳區!$E:$E,$D50) -> -9000 | I50: =SUMIFS(記帳區!$F:$F,記帳區!$K:$K,">=" & EOMONTH(I$2,-1) + 1,記帳區!$K:$K,"<=" & EOMONTH(I$2, 0),記帳區!$E:$E,$D50) -> 0 | J50: =SUMIFS(記帳區!$F:$F,記帳區!$K:$K,">=" & EOMONTH(J$2,-1) + 1,記帳區!$K:$K,"<=" & EOMONTH(J$2, 0),記帳區!$E:$E,$D50) -> 0 | K50: =SUMIFS(記帳區!$F:$F,記帳區!$K:$K,">=" & EOMONTH(K$2,-1) + 1,記帳區!$K:$K,"<=" & EOMONTH(K$2, 0),記帳區!$E:$E,$D50) -> 0 | L50: =SUMIFS(記帳區!$F:$F,記帳區!$K:$K,">=" & EOMONTH(L$2,-1) + 1,記帳區!$K:$K,"<=" & EOMONTH(L$2, 0),記帳區!$E:$E,$D50) -> 0 | M50: =SUMIFS(記帳區!$F:$F,記帳區!$K:$K,">=" & EOMONTH(M$2,-1) + 1,記帳區!$K:$K,"<=" & EOMONTH(M$2, 0),記帳區!$E:$E,$D50) -> 0 | N50: =SUMIFS(記帳區!$F:$F,記帳區!$K:$K,">=" & EOMONTH(N$2,-1) + 1,記帳區!$K:$K,"<=" & EOMONTH(N$2, 0),記帳區!$E:$E,$D50) -> 0 | ... S50: =SUMIFS(記帳區!$F:$F,記帳區!$K:$K,">=" & EOMONTH(S$2,-1) + 1,記帳區!$K:$K,"<=" & EOMONTH(S$2, 0),記帳區!$E:$E,$D50) -> 0
D51: 致富性債務 | G51: =SUMIFS(記帳區!$F:$F,記帳區!$K:$K,">=" & EOMONTH(G$2,-1) + 1,記帳區!$K:$K,"<=" & EOMONTH(G$2, 0),記帳區!$E:$E,$D51) -> 0 | H51: =SUMIFS(記帳區!$F:$F,記帳區!$K:$K,">=" & EOMONTH(H$2,-1) + 1,記帳區!$K:$K,"<=" & EOMONTH(H$2, 0),記帳區!$E:$E,$D51) -> 0 | I51: =SUMIFS(記帳區!$F:$F,記帳區!$K:$K,">=" & EOMONTH(I$2,-1) + 1,記帳區!$K:$K,"<=" & EOMONTH(I$2, 0),記帳區!$E:$E,$D51) -> 0 | J51: =SUMIFS(記帳區!$F:$F,記帳區!$K:$K,">=" & EOMONTH(J$2,-1) + 1,記帳區!$K:$K,"<=" & EOMONTH(J$2, 0),記帳區!$E:$E,$D51) -> 0 | K51: =SUMIFS(記帳區!$F:$F,記帳區!$K:$K,">=" & EOMONTH(K$2,-1) + 1,記帳區!$K:$K,"<=" & EOMONTH(K$2, 0),記帳區!$E:$E,$D51) -> 0 | L51: =SUMIFS(記帳區!$F:$F,記帳區!$K:$K,">=" & EOMONTH(L$2,-1) + 1,記帳區!$K:$K,"<=" & EOMONTH(L$2, 0),記帳區!$E:$E,$D51) -> 0 | M51: =SUMIFS(記帳區!$F:$F,記帳區!$K:$K,">=" & EOMONTH(M$2,-1) + 1,記帳區!$K:$K,"<=" & EOMONTH(M$2, 0),記帳區!$E:$E,$D51) -> 0 | N51: =SUMIFS(記帳區!$F:$F,記帳區!$K:$K,">=" & EOMONTH(N$2,-1) + 1,記帳區!$K:$K,"<=" & EOMONTH(N$2, 0),記帳區!$E:$E,$D51) -> 0 | ... S51: =SUMIFS(記帳區!$F:$F,記帳區!$K:$K,">=" & EOMONTH(S$2,-1) + 1,記帳區!$K:$K,"<=" & EOMONTH(S$2, 0),記帳區!$E:$E,$D51) -> 0
C52: 需要 | D52: 育 | G52: =SUMIFS(記帳區!$F:$F,記帳區!$K:$K,">=" & EOMONTH(G$2,-1) + 1,記帳區!$K:$K,"<=" & EOMONTH(G$2, 0),記帳區!$D:$D,$D52) -> 0 | H52: =SUMIFS(記帳區!$F:$F,記帳區!$K:$K,">=" & EOMONTH(H$2,-1) + 1,記帳區!$K:$K,"<=" & EOMONTH(H$2, 0),記帳區!$D:$D,$D52) -> 0 | I52: =SUMIFS(記帳區!$F:$F,記帳區!$K:$K,">=" & EOMONTH(I$2,-1) + 1,記帳區!$K:$K,"<=" & EOMONTH(I$2, 0),記帳區!$D:$D,$D52) -> 0 | J52: =SUMIFS(記帳區!$F:$F,記帳區!$K:$K,">=" & EOMONTH(J$2,-1) + 1,記帳區!$K:$K,"<=" & EOMONTH(J$2, 0),記帳區!$D:$D,$D52) -> 0 | K52: =SUMIFS(記帳區!$F:$F,記帳區!$K:$K,">=" & EOMONTH(K$2,-1) + 1,記帳區!$K:$K,"<=" & EOMONTH(K$2, 0),記帳區!$D:$D,$D52) -> 0 | L52: =SUMIFS(記帳區!$F:$F,記帳區!$K:$K,">=" & EOMONTH(L$2,-1) + 1,記帳區!$K:$K,"<=" & EOMONTH(L$2, 0),記帳區!$D:$D,$D52) -> 0 | M52: =SUMIFS(記帳區!$F:$F,記帳區!$K:$K,">=" & EOMONTH(M$2,-1) + 1,記帳區!$K:$K,"<=" & EOMONTH(M$2, 0),記帳區!$D:$D,$D52) -> 0 | N52: =SUMIFS(記帳區!$F:$F,記帳區!$K:$K,">=" & EOMONTH(N$2,-1) + 1,記帳區!$K:$K,"<=" & EOMONTH(N$2, 0),記帳區!$D:$D,$D52) -> 0 | ... S52: =SUMIFS(記帳區!$F:$F,記帳區!$K:$K,">=" & EOMONTH(S$2,-1) + 1,記帳區!$K:$K,"<=" & EOMONTH(S$2, 0),記帳區!$D:$D,$D52) -> 0
D53: 進修 | G53: =SUMIFS(記帳區!$F:$F,記帳區!$K:$K,">=" & EOMONTH(G$2,-1) + 1,記帳區!$K:$K,"<=" & EOMONTH(G$2, 0),記帳區!$E:$E,$D53) -> 0 | H53: =SUMIFS(記帳區!$F:$F,記帳區!$K:$K,">=" & EOMONTH(H$2,-1) + 1,記帳區!$K:$K,"<=" & EOMONTH(H$2, 0),記帳區!$E:$E,$D53) -> 0 | I53: =SUMIFS(記帳區!$F:$F,記帳區!$K:$K,">=" & EOMONTH(I$2,-1) + 1,記帳區!$K:$K,"<=" & EOMONTH(I$2, 0),記帳區!$E:$E,$D53) -> 0 | J53: =SUMIFS(記帳區!$F:$F,記帳區!$K:$K,">=" & EOMONTH(J$2,-1) + 1,記帳區!$K:$K,"<=" & EOMONTH(J$2, 0),記帳區!$E:$E,$D53) -> 0 | K53: =SUMIFS(記帳區!$F:$F,記帳區!$K:$K,">=" & EOMONTH(K$2,-1) + 1,記帳區!$K:$K,"<=" & EOMONTH(K$2, 0),記帳區!$E:$E,$D53) -> 0 | L53: =SUMIFS(記帳區!$F:$F,記帳區!$K:$K,">=" & EOMONTH(L$2,-1) + 1,記帳區!$K:$K,"<=" & EOMONTH(L$2, 0),記帳區!$E:$E,$D53) -> 0 | M53: =SUMIFS(記帳區!$F:$F,記帳區!$K:$K,">=" & EOMONTH(M$2,-1) + 1,記帳區!$K:$K,"<=" & EOMONTH(M$2, 0),記帳區!$E:$E,$D53) -> 0 | N53: =SUMIFS(記帳區!$F:$F,記帳區!$K:$K,">=" & EOMONTH(N$2,-1) + 1,記帳區!$K:$K,"<=" & EOMONTH(N$2, 0),記帳區!$E:$E,$D53) -> 0 | ... S53: =SUMIFS(記帳區!$F:$F,記帳區!$K:$K,">=" & EOMONTH(S$2,-1) + 1,記帳區!$K:$K,"<=" & EOMONTH(S$2, 0),記帳區!$E:$E,$D53) -> 0
D54: 書籍 | G54: =SUMIFS(記帳區!$F:$F,記帳區!$K:$K,">=" & EOMONTH(G$2,-1) + 1,記帳區!$K:$K,"<=" & EOMONTH(G$2, 0),記帳區!$E:$E,$D54) -> 0 | H54: =SUMIFS(記帳區!$F:$F,記帳區!$K:$K,">=" & EOMONTH(H$2,-1) + 1,記帳區!$K:$K,"<=" & EOMONTH(H$2, 0),記帳區!$E:$E,$D54) -> 0 | I54: =SUMIFS(記帳區!$F:$F,記帳區!$K:$K,">=" & EOMONTH(I$2,-1) + 1,記帳區!$K:$K,"<=" & EOMONTH(I$2, 0),記帳區!$E:$E,$D54) -> 0 | J54: =SUMIFS(記帳區!$F:$F,記帳區!$K:$K,">=" & EOMONTH(J$2,-1) + 1,記帳區!$K:$K,"<=" & EOMONTH(J$2, 0),記帳區!$E:$E,$D54) -> 0 | K54: =SUMIFS(記帳區!$F:$F,記帳區!$K:$K,">=" & EOMONTH(K$2,-1) + 1,記帳區!$K:$K,"<=" & EOMONTH(K$2, 0),記帳區!$E:$E,$D54) -> 0 | L54: =SUMIFS(記帳區!$F:$F,記帳區!$K:$K,">=" & EOMONTH(L$2,-1) + 1,記帳區!$K:$K,"<=" & EOMONTH(L$2, 0),記帳區!$E:$E,$D54) -> 0 | M54: =SUMIFS(記帳區!$F:$F,記帳區!$K:$K,">=" & EOMONTH(M$2,-1) + 1,記帳區!$K:$K,"<=" & EOMONTH(M$2, 0),記帳區!$E:$E,$D54) -> 0 | N54: =SUMIFS(記帳區!$F:$F,記帳區!$K:$K,">=" & EOMONTH(N$2,-1) + 1,記帳區!$K:$K,"<=" & EOMONTH(N$2, 0),記帳區!$E:$E,$D54) -> 0 | ... S54: =SUMIFS(記帳區!$F:$F,記帳區!$K:$K,">=" & EOMONTH(S$2,-1) + 1,記帳區!$K:$K,"<=" & EOMONTH(S$2, 0),記帳區!$E:$E,$D54) -> 0
D55: 給予 | G55: =SUMIFS(記帳區!$F:$F,記帳區!$K:$K,">=" & EOMONTH(G$2,-1) + 1,記帳區!$K:$K,"<=" & EOMONTH(G$2, 0),記帳區!$D:$D,$D55) -> 0 | H55: =SUMIFS(記帳區!$F:$F,記帳區!$K:$K,">=" & EOMONTH(H$2,-1) + 1,記帳區!$K:$K,"<=" & EOMONTH(H$2, 0),記帳區!$D:$D,$D55) -> 0 | I55: =SUMIFS(記帳區!$F:$F,記帳區!$K:$K,">=" & EOMONTH(I$2,-1) + 1,記帳區!$K:$K,"<=" & EOMONTH(I$2, 0),記帳區!$D:$D,$D55) -> 0 | J55: =SUMIFS(記帳區!$F:$F,記帳區!$K:$K,">=" & EOMONTH(J$2,-1) + 1,記帳區!$K:$K,"<=" & EOMONTH(J$2, 0),記帳區!$D:$D,$D55) -> 0 | K55: =SUMIFS(記帳區!$F:$F,記帳區!$K:$K,">=" & EOMONTH(K$2,-1) + 1,記帳區!$K:$K,"<=" & EOMONTH(K$2, 0),記帳區!$D:$D,$D55) -> 0 | L55: =SUMIFS(記帳區!$F:$F,記帳區!$K:$K,">=" & EOMONTH(L$2,-1) + 1,記帳區!$K:$K,"<=" & EOMONTH(L$2, 0),記帳區!$D:$D,$D55) -> 0 | M55: =SUMIFS(記帳區!$F:$F,記帳區!$K:$K,">=" & EOMONTH(M$2,-1) + 1,記帳區!$K:$K,"<=" & EOMONTH(M$2, 0),記帳區!$D:$D,$D55) -> 0 | N55: =SUMIFS(記帳區!$F:$F,記帳區!$K:$K,">=" & EOMONTH(N$2,-1) + 1,記帳區!$K:$K,"<=" & EOMONTH(N$2, 0),記帳區!$D:$D,$D55) -> 0 | ... S55: =SUMIFS(記帳區!$F:$F,記帳區!$K:$K,">=" & EOMONTH(S$2,-1) + 1,記帳區!$K:$K,"<=" & EOMONTH(S$2, 0),記帳區!$D:$D,$D55) -> 0
D56: 紅白包 | G56: =SUMIFS(記帳區!$F:$F,記帳區!$K:$K,">=" & EOMONTH(G$2,-1) + 1,記帳區!$K:$K,"<=" & EOMONTH(G$2, 0),記帳區!$E:$E,$D56) -> 0 | H56: =SUMIFS(記帳區!$F:$F,記帳區!$K:$K,">=" & EOMONTH(H$2,-1) + 1,記帳區!$K:$K,"<=" & EOMONTH(H$2, 0),記帳區!$E:$E,$D56) -> 0 | I56: =SUMIFS(記帳區!$F:$F,記帳區!$K:$K,">=" & EOMONTH(I$2,-1) + 1,記帳區!$K:$K,"<=" & EOMONTH(I$2, 0),記帳區!$E:$E,$D56) -> 0 | J56: =SUMIFS(記帳區!$F:$F,記帳區!$K:$K,">=" & EOMONTH(J$2,-1) + 1,記帳區!$K:$K,"<=" & EOMONTH(J$2, 0),記帳區!$E:$E,$D56) -> 0 | K56: =SUMIFS(記帳區!$F:$F,記帳區!$K:$K,">=" & EOMONTH(K$2,-1) + 1,記帳區!$K:$K,"<=" & EOMONTH(K$2, 0),記帳區!$E:$E,$D56) -> 0 | L56: =SUMIFS(記帳區!$F:$F,記帳區!$K:$K,">=" & EOMONTH(L$2,-1) + 1,記帳區!$K:$K,"<=" & EOMONTH(L$2, 0),記帳區!$E:$E,$D56) -> 0 | M56: =SUMIFS(記帳區!$F:$F,記帳區!$K:$K,">=" & EOMONTH(M$2,-1) + 1,記帳區!$K:$K,"<=" & EOMONTH(M$2, 0),記帳區!$E:$E,$D56) -> 0 | N56: =SUMIFS(記帳區!$F:$F,記帳區!$K:$K,">=" & EOMONTH(N$2,-1) + 1,記帳區!$K:$K,"<=" & EOMONTH(N$2, 0),記帳區!$E:$E,$D56) -> 0 | ... S56: =SUMIFS(記帳區!$F:$F,記帳區!$K:$K,">=" & EOMONTH(S$2,-1) + 1,記帳區!$K:$K,"<=" & EOMONTH(S$2, 0),記帳區!$E:$E,$D56) -> 0
D57: 孝親 | G57: =SUMIFS(記帳區!$F:$F,記帳區!$K:$K,">=" & EOMONTH(G$2,-1) + 1,記帳區!$K:$K,"<=" & EOMONTH(G$2, 0),記帳區!$E:$E,$D57) -> 0 | H57: =SUMIFS(記帳區!$F:$F,記帳區!$K:$K,">=" & EOMONTH(H$2,-1) + 1,記帳區!$K:$K,"<=" & EOMONTH(H$2, 0),記帳區!$E:$E,$D57) -> 0 | I57: =SUMIFS(記帳區!$F:$F,記帳區!$K:$K,">=" & EOMONTH(I$2,-1) + 1,記帳區!$K:$K,"<=" & EOMONTH(I$2, 0),記帳區!$E:$E,$D57) -> 0 | J57: =SUMIFS(記帳區!$F:$F,記帳區!$K:$K,">=" & EOMONTH(J$2,-1) + 1,記帳區!$K:$K,"<=" & EOMONTH(J$2, 0),記帳區!$E:$E,$D57) -> 0 | K57: =SUMIFS(記帳區!$F:$F,記帳區!$K:$K,">=" & EOMONTH(K$2,-1) + 1,記帳區!$K:$K,"<=" & EOMONTH(K$2, 0),記帳區!$E:$E,$D57) -> 0 | L57: =SUMIFS(記帳區!$F:$F,記帳區!$K:$K,">=" & EOMONTH(L$2,-1) + 1,記帳區!$K:$K,"<=" & EOMONTH(L$2, 0),記帳區!$E:$E,$D57) -> 0 | M57: =SUMIFS(記帳區!$F:$F,記帳區!$K:$K,">=" & EOMONTH(M$2,-1) + 1,記帳區!$K:$K,"<=" & EOMONTH(M$2, 0),記帳區!$E:$E,$D57) -> 0 | N57: =SUMIFS(記帳區!$F:$F,記帳區!$K:$K,">=" & EOMONTH(N$2,-1) + 1,記帳區!$K:$K,"<=" & EOMONTH(N$2, 0),記帳區!$E:$E,$D57) -> 0 | ... S57: =SUMIFS(記帳區!$F:$F,記帳區!$K:$K,">=" & EOMONTH(S$2,-1) + 1,記帳區!$K:$K,"<=" & EOMONTH(S$2, 0),記帳區!$E:$E,$D57) -> 0
D58: 醫 | G58: =SUMIFS(記帳區!$F:$F,記帳區!$K:$K,">=" & EOMONTH(G$2,-1) + 1,記帳區!$K:$K,"<=" & EOMONTH(G$2, 0),記帳區!$D:$D,$D58) -> 0 | H58: =SUMIFS(記帳區!$F:$F,記帳區!$K:$K,">=" & EOMONTH(H$2,-1) + 1,記帳區!$K:$K,"<=" & EOMONTH(H$2, 0),記帳區!$D:$D,$D58) -> 0 | I58: =SUMIFS(記帳區!$F:$F,記帳區!$K:$K,">=" & EOMONTH(I$2,-1) + 1,記帳區!$K:$K,"<=" & EOMONTH(I$2, 0),記帳區!$D:$D,$D58) -> 0 | J58: =SUMIFS(記帳區!$F:$F,記帳區!$K:$K,">=" & EOMONTH(J$2,-1) + 1,記帳區!$K:$K,"<=" & EOMONTH(J$2, 0),記帳區!$D:$D,$D58) -> 0 | K58: =SUMIFS(記帳區!$F:$F,記帳區!$K:$K,">=" & EOMONTH(K$2,-1) + 1,記帳區!$K:$K,"<=" & EOMONTH(K$2, 0),記帳區!$D:$D,$D58) -> 0 | L58: =SUMIFS(記帳區!$F:$F,記帳區!$K:$K,">=" & EOMONTH(L$2,-1) + 1,記帳區!$K:$K,"<=" & EOMONTH(L$2, 0),記帳區!$D:$D,$D58) -> 0 | M58: =SUMIFS(記帳區!$F:$F,記帳區!$K:$K,">=" & EOMONTH(M$2,-1) + 1,記帳區!$K:$K,"<=" & EOMONTH(M$2, 0),記帳區!$D:$D,$D58) -> 0 | N58: =SUMIFS(記帳區!$F:$F,記帳區!$K:$K,">=" & EOMONTH(N$2,-1) + 1,記帳區!$K:$K,"<=" & EOMONTH(N$2, 0),記帳區!$D:$D,$D58) -> 0 | ... S58: =SUMIFS(記帳區!$F:$F,記帳區!$K:$K,">=" & EOMONTH(S$2,-1) + 1,記帳區!$K:$K,"<=" & EOMONTH(S$2, 0),記帳區!$D:$D,$D58) -> 0
D59: 藥品 | G59: =SUMIFS(記帳區!$F:$F,記帳區!$K:$K,">=" & EOMONTH(G$2,-1) + 1,記帳區!$K:$K,"<=" & EOMONTH(G$2, 0),記帳區!$E:$E,$D59) -> 0 | H59: =SUMIFS(記帳區!$F:$F,記帳區!$K:$K,">=" & EOMONTH(H$2,-1) + 1,記帳區!$K:$K,"<=" & EOMONTH(H$2, 0),記帳區!$E:$E,$D59) -> 0 | I59: =SUMIFS(記帳區!$F:$F,記帳區!$K:$K,">=" & EOMONTH(I$2,-1) + 1,記帳區!$K:$K,"<=" & EOMONTH(I$2, 0),記帳區!$E:$E,$D59) -> 0 | J59: =SUMIFS(記帳區!$F:$F,記帳區!$K:$K,">=" & EOMONTH(J$2,-1) + 1,記帳區!$K:$K,"<=" & EOMONTH(J$2, 0),記帳區!$E:$E,$D59) -> 0 | K59: =SUMIFS(記帳區!$F:$F,記帳區!$K:$K,">=" & EOMONTH(K$2,-1) + 1,記帳區!$K:$K,"<=" & EOMONTH(K$2, 0),記帳區!$E:$E,$D59) -> 0 | L59: =SUMIFS(記帳區!$F:$F,記帳區!$K:$K,">=" & EOMONTH(L$2,-1) + 1,記帳區!$K:$K,"<=" & EOMONTH(L$2, 0),記帳區!$E:$E,$D59) -> 0 | M59: =SUMIFS(記帳區!$F:$F,記帳區!$K:$K,">=" & EOMONTH(M$2,-1) + 1,記帳區!$K:$K,"<=" & EOMONTH(M$2, 0),記帳區!$E:$E,$D59) -> 0 | N59: =SUMIFS(記帳區!$F:$F,記帳區!$K:$K,">=" & EOMONTH(N$2,-1) + 1,記帳區!$K:$K,"<=" & EOMONTH(N$2, 0),記帳區!$E:$E,$D59) -> 0 | ... S59: =SUMIFS(記帳區!$F:$F,記帳區!$K:$K,">=" & EOMONTH(S$2,-1) + 1,記帳區!$K:$K,"<=" & EOMONTH(S$2, 0),記帳區!$E:$E,$D59) -> 0
D60: 門診 | G60: =SUMIFS(記帳區!$F:$F,記帳區!$K:$K,">=" & EOMONTH(G$2,-1) + 1,記帳區!$K:$K,"<=" & EOMONTH(G$2, 0),記帳區!$E:$E,$D60) -> 0 | H60: =SUMIFS(記帳區!$F:$F,記帳區!$K:$K,">=" & EOMONTH(H$2,-1) + 1,記帳區!$K:$K,"<=" & EOMONTH(H$2, 0),記帳區!$E:$E,$D60) -> 0 | I60: =SUMIFS(記帳區!$F:$F,記帳區!$K:$K,">=" & EOMONTH(I$2,-1) + 1,記帳區!$K:$K,"<=" & EOMONTH(I$2, 0),記帳區!$E:$E,$D60) -> 0 | J60: =SUMIFS(記帳區!$F:$F,記帳區!$K:$K,">=" & EOMONTH(J$2,-1) + 1,記帳區!$K:$K,"<=" & EOMONTH(J$2, 0),記帳區!$E:$E,$D60) -> 0 | K60: =SUMIFS(記帳區!$F:$F,記帳區!$K:$K,">=" & EOMONTH(K$2,-1) + 1,記帳區!$K:$K,"<=" & EOMONTH(K$2, 0),記帳區!$E:$E,$D60) -> 0 | L60: =SUMIFS(記帳區!$F:$F,記帳區!$K:$K,">=" & EOMONTH(L$2,-1) + 1,記帳區!$K:$K,"<=" & EOMONTH(L$2, 0),記帳區!$E:$E,$D60) -> 0 | M60: =SUMIFS(記帳區!$F:$F,記帳區!$K:$K,">=" & EOMONTH(M$2,-1) + 1,記帳區!$K:$K,"<=" & EOMONTH(M$2, 0),記帳區!$E:$E,$D60) -> 0 | N60: =SUMIFS(記帳區!$F:$F,記帳區!$K:$K,">=" & EOMONTH(N$2,-1) + 1,記帳區!$K:$K,"<=" & EOMONTH(N$2, 0),記帳區!$E:$E,$D60) -> 0 | ... S60: =SUMIFS(記帳區!$F:$F,記帳區!$K:$K,">=" & EOMONTH(S$2,-1) + 1,記帳區!$K:$K,"<=" & EOMONTH(S$2, 0),記帳區!$E:$E,$D60) -> 0
D61: 其他 | G61: =SUMIFS(記帳區!$F:$F,記帳區!$K:$K,">=" & EOMONTH(G$2,-1) + 1,記帳區!$K:$K,"<=" & EOMONTH(G$2, 0),記帳區!$D:$D,$D61) -> 0 | H61: =SUMIFS(記帳區!$F:$F,記帳區!$K:$K,">=" & EOMONTH(H$2,-1) + 1,記帳區!$K:$K,"<=" & EOMONTH(H$2, 0),記帳區!$D:$D,$D61) -> 0 | I61: =SUMIFS(記帳區!$F:$F,記帳區!$K:$K,">=" & EOMONTH(I$2,-1) + 1,記帳區!$K:$K,"<=" & EOMONTH(I$2, 0),記帳區!$D:$D,$D61) -> 0 | J61: =SUMIFS(記帳區!$F:$F,記帳區!$K:$K,">=" & EOMONTH(J$2,-1) + 1,記帳區!$K:$K,"<=" & EOMONTH(J$2, 0),記帳區!$D:$D,$D61) -> 0 | K61: =SUMIFS(記帳區!$F:$F,記帳區!$K:$K,">=" & EOMONTH(K$2,-1) + 1,記帳區!$K:$K,"<=" & EOMONTH(K$2, 0),記帳區!$D:$D,$D61) -> 0 | L61: =SUMIFS(記帳區!$F:$F,記帳區!$K:$K,">=" & EOMONTH(L$2,-1) + 1,記帳區!$K:$K,"<=" & EOMONTH(L$2, 0),記帳區!$D:$D,$D61) -> 0 | M61: =SUMIFS(記帳區!$F:$F,記帳區!$K:$K,">=" & EOMONTH(M$2,-1) + 1,記帳區!$K:$K,"<=" & EOMONTH(M$2, 0),記帳區!$D:$D,$D61) -> 0 | N61: =SUMIFS(記帳區!$F:$F,記帳區!$K:$K,">=" & EOMONTH(N$2,-1) + 1,記帳區!$K:$K,"<=" & EOMONTH(N$2, 0),記帳區!$D:$D,$D61) -> 0 | ... S61: =SUMIFS(記帳區!$F:$F,記帳區!$K:$K,">=" & EOMONTH(S$2,-1) + 1,記帳區!$K:$K,"<=" & EOMONTH(S$2, 0),記帳區!$D:$D,$D61) -> 0
D62: 工作支出 | G62: =SUMIFS(記帳區!$F:$F,記帳區!$K:$K,">=" & EOMONTH(G$2,-1) + 1,記帳區!$K:$K,"<=" & EOMONTH(G$2, 0),記帳區!$E:$E,$D62) -> 0 | H62: =SUMIFS(記帳區!$F:$F,記帳區!$K:$K,">=" & EOMONTH(H$2,-1) + 1,記帳區!$K:$K,"<=" & EOMONTH(H$2, 0),記帳區!$E:$E,$D62) -> 0 | I62: =SUMIFS(記帳區!$F:$F,記帳區!$K:$K,">=" & EOMONTH(I$2,-1) + 1,記帳區!$K:$K,"<=" & EOMONTH(I$2, 0),記帳區!$E:$E,$D62) -> 0 | J62: =SUMIFS(記帳區!$F:$F,記帳區!$K:$K,">=" & EOMONTH(J$2,-1) + 1,記帳區!$K:$K,"<=" & EOMONTH(J$2, 0),記帳區!$E:$E,$D62) -> 0 | K62: =SUMIFS(記帳區!$F:$F,記帳區!$K:$K,">=" & EOMONTH(K$2,-1) + 1,記帳區!$K:$K,"<=" & EOMONTH(K$2, 0),記帳區!$E:$E,$D62) -> 0 | L62: =SUMIFS(記帳區!$F:$F,記帳區!$K:$K,">=" & EOMONTH(L$2,-1) + 1,記帳區!$K:$K,"<=" & EOMONTH(L$2, 0),記帳區!$E:$E,$D62) -> 0 | M62: =SUMIFS(記帳區!$F:$F,記帳區!$K:$K,">=" & EOMONTH(M$2,-1) + 1,記帳區!$K:$K,"<=" & EOMONTH(M$2, 0),記帳區!$E:$E,$D62) -> 0 | N62: =SUMIFS(記帳區!$F:$F,記帳區!$K:$K,">=" & EOMONTH(N$2,-1) + 1,記帳區!$K:$K,"<=" & EOMONTH(N$2, 0),記帳區!$E:$E,$D62) -> 0 | ... S62: =SUMIFS(記帳區!$F:$F,記帳區!$K:$K,">=" & EOMONTH(S$2,-1) + 1,記帳區!$K:$K,"<=" & EOMONTH(S$2, 0),記帳區!$E:$E,$D62) -> 0
G63: =SUMIFS(記帳區!$F:$F,記帳區!$K:$K,">=" & EOMONTH(G$2,-1) + 1,記帳區!$K:$K,"<=" & EOMONTH(G$2, 0),記帳區!$E:$E,$D63) -> 0 | H63: =SUMIFS(記帳區!$F:$F,記帳區!$K:$K,">=" & EOMONTH(H$2,-1) + 1,記帳區!$K:$K,"<=" & EOMONTH(H$2, 0),記帳區!$E:$E,$D63) -> 0 | I63: =SUMIFS(記帳區!$F:$F,記帳區!$K:$K,">=" & EOMONTH(I$2,-1) + 1,記帳區!$K:$K,"<=" & EOMONTH(I$2, 0),記帳區!$E:$E,$D63) -> 0 | J63: =SUMIFS(記帳區!$F:$F,記帳區!$K:$K,">=" & EOMONTH(J$2,-1) + 1,記帳區!$K:$K,"<=" & EOMONTH(J$2, 0),記帳區!$E:$E,$D63) -> 0 | K63: =SUMIFS(記帳區!$F:$F,記帳區!$K:$K,">=" & EOMONTH(K$2,-1) + 1,記帳區!$K:$K,"<=" & EOMONTH(K$2, 0),記帳區!$E:$E,$D63) -> 0 | L63: =SUMIFS(記帳區!$F:$F,記帳區!$K:$K,">=" & EOMONTH(L$2,-1) + 1,記帳區!$K:$K,"<=" & EOMONTH(L$2, 0),記帳區!$E:$E,$D63) -> 0 | M63: =SUMIFS(記帳區!$F:$F,記帳區!$K:$K,">=" & EOMONTH(M$2,-1) + 1,記帳區!$K:$K,"<=" & EOMONTH(M$2, 0),記帳區!$E:$E,$D63) -> 0 | N63: =SUMIFS(記帳區!$F:$F,記帳區!$K:$K,">=" & EOMONTH(N$2,-1) + 1,記帳區!$K:$K,"<=" & EOMONTH(N$2, 0),記帳區!$E:$E,$D63) -> 0 | ... S63: =SUMIFS(記帳區!$F:$F,記帳區!$K:$K,">=" & EOMONTH(S$2,-1) + 1,記帳區!$K:$K,"<=" & EOMONTH(S$2, 0),記帳區!$E:$E,$D63) -> 0
C64: 想要 | D64: 樂 | G64: =SUMIFS(記帳區!$F:$F,記帳區!$K:$K,">=" & EOMONTH(G$2,-1) + 1,記帳區!$K:$K,"<=" & EOMONTH(G$2, 0),記帳區!$D:$D,$D64) -> 0 | H64: =SUMIFS(記帳區!$F:$F,記帳區!$K:$K,">=" & EOMONTH(H$2,-1) + 1,記帳區!$K:$K,"<=" & EOMONTH(H$2, 0),記帳區!$D:$D,$D64) -> 0 | I64: =SUMIFS(記帳區!$F:$F,記帳區!$K:$K,">=" & EOMONTH(I$2,-1) + 1,記帳區!$K:$K,"<=" & EOMONTH(I$2, 0),記帳區!$D:$D,$D64) -> 0 | J64: =SUMIFS(記帳區!$F:$F,記帳區!$K:$K,">=" & EOMONTH(J$2,-1) + 1,記帳區!$K:$K,"<=" & EOMONTH(J$2, 0),記帳區!$D:$D,$D64) -> 0 | K64: =SUMIFS(記帳區!$F:$F,記帳區!$K:$K,">=" & EOMONTH(K$2,-1) + 1,記帳區!$K:$K,"<=" & EOMONTH(K$2, 0),記帳區!$D:$D,$D64) -> 0 | L64: =SUMIFS(記帳區!$F:$F,記帳區!$K:$K,">=" & EOMONTH(L$2,-1) + 1,記帳區!$K:$K,"<=" & EOMONTH(L$2, 0),記帳區!$D:$D,$D64) -> 0 | M64: =SUMIFS(記帳區!$F:$F,記帳區!$K:$K,">=" & EOMONTH(M$2,-1) + 1,記帳區!$K:$K,"<=" & EOMONTH(M$2, 0),記帳區!$D:$D,$D64) -> 0 | N64: =SUMIFS(記帳區!$F:$F,記帳區!$K:$K,">=" & EOMONTH(N$2,-1) + 1,記帳區!$K:$K,"<=" & EOMONTH(N$2, 0),記帳區!$D:$D,$D64) -> 0 | ... S64: =SUMIFS(記帳區!$F:$F,記帳區!$K:$K,">=" & EOMONTH(S$2,-1) + 1,記帳區!$K:$K,"<=" & EOMONTH(S$2, 0),記帳區!$D:$D,$D64) -> 0
D65: 雜誌視聽 | G65: =SUMIFS(記帳區!$F:$F,記帳區!$K:$K,">=" & EOMONTH(G$2,-1) + 1,記帳區!$K:$K,"<=" & EOMONTH(G$2, 0),記帳區!$E:$E,$D65) -> 0 | H65: =SUMIFS(記帳區!$F:$F,記帳區!$K:$K,">=" & EOMONTH(H$2,-1) + 1,記帳區!$K:$K,"<=" & EOMONTH(H$2, 0),記帳區!$E:$E,$D65) -> 0 | I65: =SUMIFS(記帳區!$F:$F,記帳區!$K:$K,">=" & EOMONTH(I$2,-1) + 1,記帳區!$K:$K,"<=" & EOMONTH(I$2, 0),記帳區!$E:$E,$D65) -> 0 | J65: =SUMIFS(記帳區!$F:$F,記帳區!$K:$K,">=" & EOMONTH(J$2,-1) + 1,記帳區!$K:$K,"<=" & EOMONTH(J$2, 0),記帳區!$E:$E,$D65) -> 0 | K65: =SUMIFS(記帳區!$F:$F,記帳區!$K:$K,">=" & EOMONTH(K$2,-1) + 1,記帳區!$K:$K,"<=" & EOMONTH(K$2, 0),記帳區!$E:$E,$D65) -> 0 | L65: =SUMIFS(記帳區!$F:$F,記帳區!$K:$K,">=" & EOMONTH(L$2,-1) + 1,記帳區!$K:$K,"<=" & EOMONTH(L$2, 0),記帳區!$E:$E,$D65) -> 0 | M65: =SUMIFS(記帳區!$F:$F,記帳區!$K:$K,">=" & EOMONTH(M$2,-1) + 1,記帳區!$K:$K,"<=" & EOMONTH(M$2, 0),記帳區!$E:$E,$D65) -> 0 | N65: =SUMIFS(記帳區!$F:$F,記帳區!$K:$K,">=" & EOMONTH(N$2,-1) + 1,記帳區!$K:$K,"<=" & EOMONTH(N$2, 0),記帳區!$E:$E,$D65) -> 0 | ... S65: =SUMIFS(記帳區!$F:$F,記帳區!$K:$K,">=" & EOMONTH(S$2,-1) + 1,記帳區!$K:$K,"<=" & EOMONTH(S$2, 0),記帳區!$E:$E,$D65) -> 0
D66: 旅遊 | G66: =SUMIFS(記帳區!$F:$F,記帳區!$K:$K,">=" & EOMONTH(G$2,-1) + 1,記帳區!$K:$K,"<=" & EOMONTH(G$2, 0),記帳區!$E:$E,$D66) -> 0 | H66: =SUMIFS(記帳區!$F:$F,記帳區!$K:$K,">=" & EOMONTH(H$2,-1) + 1,記帳區!$K:$K,"<=" & EOMONTH(H$2, 0),記帳區!$E:$E,$D66) -> 0 | I66: =SUMIFS(記帳區!$F:$F,記帳區!$K:$K,">=" & EOMONTH(I$2,-1) + 1,記帳區!$K:$K,"<=" & EOMONTH(I$2, 0),記帳區!$E:$E,$D66) -> 0 | J66: =SUMIFS(記帳區!$F:$F,記帳區!$K:$K,">=" & EOMONTH(J$2,-1) + 1,記帳區!$K:$K,"<=" & EOMONTH(J$2, 0),記帳區!$E:$E,$D66) -> 0 | K66: =SUMIFS(記帳區!$F:$F,記帳區!$K:$K,">=" & EOMONTH(K$2,-1) + 1,記帳區!$K:$K,"<=" & EOMONTH(K$2, 0),記帳區!$E:$E,$D66) -> 0 | L66: =SUMIFS(記帳區!$F:$F,記帳區!$K:$K,">=" & EOMONTH(L$2,-1) + 1,記帳區!$K:$K,"<=" & EOMONTH(L$2, 0),記帳區!$E:$E,$D66) -> 0 | M66: =SUMIFS(記帳區!$F:$F,記帳區!$K:$K,">=" & EOMONTH(M$2,-1) + 1,記帳區!$K:$K,"<=" & EOMONTH(M$2, 0),記帳區!$E:$E,$D66) -> 0 | N66: =SUMIFS(記帳區!$F:$F,記帳區!$K:$K,">=" & EOMONTH(N$2,-1) + 1,記帳區!$K:$K,"<=" & EOMONTH(N$2, 0),記帳區!$E:$E,$D66) -> 0 | ... S66: =SUMIFS(記帳區!$F:$F,記帳區!$K:$K,">=" & EOMONTH(S$2,-1) + 1,記帳區!$K:$K,"<=" & EOMONTH(S$2, 0),記帳區!$E:$E,$D66) -> 0
D67: 夢想 | G67: =SUMIFS(記帳區!$F:$F,記帳區!$K:$K,">=" & EOMONTH(G$2,-1) + 1,記帳區!$K:$K,"<=" & EOMONTH(G$2, 0),記帳區!$D:$D,$D67) -> 0 | H67: =SUMIFS(記帳區!$F:$F,記帳區!$K:$K,">=" & EOMONTH(H$2,-1) + 1,記帳區!$K:$K,"<=" & EOMONTH(H$2, 0),記帳區!$D:$D,$D67) -> 0 | I67: =SUMIFS(記帳區!$F:$F,記帳區!$K:$K,">=" & EOMONTH(I$2,-1) + 1,記帳區!$K:$K,"<=" & EOMONTH(I$2, 0),記帳區!$D:$D,$D67) -> 0 | J67: =SUMIFS(記帳區!$F:$F,記帳區!$K:$K,">=" & EOMONTH(J$2,-1) + 1,記帳區!$K:$K,"<=" & EOMONTH(J$2, 0),記帳區!$D:$D,$D67) -> 0 | K67: =SUMIFS(記帳區!$F:$F,記帳區!$K:$K,">=" & EOMONTH(K$2,-1) + 1,記帳區!$K:$K,"<=" & EOMONTH(K$2, 0),記帳區!$D:$D,$D67) -> 0 | L67: =SUMIFS(記帳區!$F:$F,記帳區!$K:$K,">=" & EOMONTH(L$2,-1) + 1,記帳區!$K:$K,"<=" & EOMONTH(L$2, 0),記帳區!$D:$D,$D67) -> 0 | M67: =SUMIFS(記帳區!$F:$F,記帳區!$K:$K,">=" & EOMONTH(M$2,-1) + 1,記帳區!$K:$K,"<=" & EOMONTH(M$2, 0),記帳區!$D:$D,$D67) -> 0 | N67: =SUMIFS(記帳區!$F:$F,記帳區!$K:$K,">=" & EOMONTH(N$2,-1) + 1,記帳區!$K:$K,"<=" & EOMONTH(N$2, 0),記帳區!$D:$D,$D67) -> 0 | ... S67: =SUMIFS(記帳區!$F:$F,記帳區!$K:$K,">=" & EOMONTH(S$2,-1) + 1,記帳區!$K:$K,"<=" & EOMONTH(S$2, 0),記帳區!$D:$D,$D67) -> 0
G68: =SUMIFS(記帳區!$F:$F,記帳區!$K:$K,">=" & EOMONTH(G$2,-1) + 1,記帳區!$K:$K,"<=" & EOMONTH(G$2, 0),記帳區!$E:$E,$D68) -> 0 | H68: =SUMIFS(記帳區!$F:$F,記帳區!$K:$K,">=" & EOMONTH(H$2,-1) + 1,記帳區!$K:$K,"<=" & EOMONTH(H$2, 0),記帳區!$E:$E,$D68) -> 0 | I68: =SUMIFS(記帳區!$F:$F,記帳區!$K:$K,">=" & EOMONTH(I$2,-1) + 1,記帳區!$K:$K,"<=" & EOMONTH(I$2, 0),記帳區!$E:$E,$D68) -> 0 | J68: =SUMIFS(記帳區!$F:$F,記帳區!$K:$K,">=" & EOMONTH(J$2,-1) + 1,記帳區!$K:$K,"<=" & EOMONTH(J$2, 0),記帳區!$E:$E,$D68) -> 0 | K68: =SUMIFS(記帳區!$F:$F,記帳區!$K:$K,">=" & EOMONTH(K$2,-1) + 1,記帳區!$K:$K,"<=" & EOMONTH(K$2, 0),記帳區!$E:$E,$D68) -> 0 | L68: =SUMIFS(記帳區!$F:$F,記帳區!$K:$K,">=" & EOMONTH(L$2,-1) + 1,記帳區!$K:$K,"<=" & EOMONTH(L$2, 0),記帳區!$E:$E,$D68) -> 0 | M68: =SUMIFS(記帳區!$F:$F,記帳區!$K:$K,">=" & EOMONTH(M$2,-1) + 1,記帳區!$K:$K,"<=" & EOMONTH(M$2, 0),記帳區!$E:$E,$D68) -> 0 | N68: =SUMIFS(記帳區!$F:$F,記帳區!$K:$K,">=" & EOMONTH(N$2,-1) + 1,記帳區!$K:$K,"<=" & EOMONTH(N$2, 0),記帳區!$E:$E,$D68) -> 0 | ... S68: =SUMIFS(記帳區!$F:$F,記帳區!$K:$K,">=" & EOMONTH(S$2,-1) + 1,記帳區!$K:$K,"<=" & EOMONTH(S$2, 0),記帳區!$E:$E,$D68) -> 0
G69: =SUMIFS(記帳區!$F:$F,記帳區!$K:$K,">=" & EOMONTH(G$2,-1) + 1,記帳區!$K:$K,"<=" & EOMONTH(G$2, 0),記帳區!$E:$E,$D69) -> 0 | H69: =SUMIFS(記帳區!$F:$F,記帳區!$K:$K,">=" & EOMONTH(H$2,-1) + 1,記帳區!$K:$K,"<=" & EOMONTH(H$2, 0),記帳區!$E:$E,$D69) -> 0 | I69: =SUMIFS(記帳區!$F:$F,記帳區!$K:$K,">=" & EOMONTH(I$2,-1) + 1,記帳區!$K:$K,"<=" & EOMONTH(I$2, 0),記帳區!$E:$E,$D69) -> 0 | J69: =SUMIFS(記帳區!$F:$F,記帳區!$K:$K,">=" & EOMONTH(J$2,-1) + 1,記帳區!$K:$K,"<=" & EOMONTH(J$2, 0),記帳區!$E:$E,$D69) -> 0 | K69: =SUMIFS(記帳區!$F:$F,記帳區!$K:$K,">=" & EOMONTH(K$2,-1) + 1,記帳區!$K:$K,"<=" & EOMONTH(K$2, 0),記帳區!$E:$E,$D69) -> 0 | L69: =SUMIFS(記帳區!$F:$F,記帳區!$K:$K,">=" & EOMONTH(L$2,-1) + 1,記帳區!$K:$K,"<=" & EOMONTH(L$2, 0),記帳區!$E:$E,$D69) -> 0 | M69: =SUMIFS(記帳區!$F:$F,記帳區!$K:$K,">=" & EOMONTH(M$2,-1) + 1,記帳區!$K:$K,"<=" & EOMONTH(M$2, 0),記帳區!$E:$E,$D69) -> 0 | N69: =SUMIFS(記帳區!$F:$F,記帳區!$K:$K,">=" & EOMONTH(N$2,-1) + 1,記帳區!$K:$K,"<=" & EOMONTH(N$2, 0),記帳區!$E:$E,$D69) -> 0 | ... S69: =SUMIFS(記帳區!$F:$F,記帳區!$K:$K,">=" & EOMONTH(S$2,-1) + 1,記帳區!$K:$K,"<=" & EOMONTH(S$2, 0),記帳區!$E:$E,$D69) -> 0
B70: 理財支出 | D70: 總計 | E70: =SUM(E71+E74+E78) -> 34200 | G70: =SUM(G71+G74+G78) -> 0 | H70: =SUM(H71+H74+H78) -> -20000 | I70: =SUM(I71+I74+I78) -> 0 | J70: =SUM(J71+J74+J78) -> 0 | K70: =SUM(K71+K74+K78) -> 0 | L70: =SUM(L71+L74+L78) -> 0 | M70: =SUM(M71+M74+M78) -> 0 | N70: =SUM(N71+N74+N78) -> 0 | ... S70: =SUM(S71+S74+S78) -> 0
D71: 儲蓄 | E71: =E5*0.15 -> 11400 | G71: =SUMIFS(記帳區!$F:$F,記帳區!$K:$K,">=" & EOMONTH(G$2,-1) + 1,記帳區!$K:$K,"<=" & EOMONTH(G$2, 0),記帳區!$D:$D,$D71) -> 0 | H71: =SUMIFS(記帳區!$F:$F,記帳區!$K:$K,">=" & EOMONTH(H$2,-1) + 1,記帳區!$K:$K,"<=" & EOMONTH(H$2, 0),記帳區!$D:$D,$D71) -> 0 | I71: =SUMIFS(記帳區!$F:$F,記帳區!$K:$K,">=" & EOMONTH(I$2,-1) + 1,記帳區!$K:$K,"<=" & EOMONTH(I$2, 0),記帳區!$D:$D,$D71) -> 0 | J71: =SUMIFS(記帳區!$F:$F,記帳區!$K:$K,">=" & EOMONTH(J$2,-1) + 1,記帳區!$K:$K,"<=" & EOMONTH(J$2, 0),記帳區!$D:$D,$D71) -> 0 | K71: =SUMIFS(記帳區!$F:$F,記帳區!$K:$K,">=" & EOMONTH(K$2,-1) + 1,記帳區!$K:$K,"<=" & EOMONTH(K$2, 0),記帳區!$D:$D,$D71) -> 0 | L71: =SUMIFS(記帳區!$F:$F,記帳區!$K:$K,">=" & EOMONTH(L$2,-1) + 1,記帳區!$K:$K,"<=" & EOMONTH(L$2, 0),記帳區!$D:$D,$D71) -> 0 | M71: =SUMIFS(記帳區!$F:$F,記帳區!$K:$K,">=" & EOMONTH(M$2,-1) + 1,記帳區!$K:$K,"<=" & EOMONTH(M$2, 0),記帳區!$D:$D,$D71) -> 0 | N71: =SUMIFS(記帳區!$F:$F,記帳區!$K:$K,">=" & EOMONTH(N$2,-1) + 1,記帳區!$K:$K,"<=" & EOMONTH(N$2, 0),記帳區!$D:$D,$D71) -> 0 | ... S71: =SUMIFS(記帳區!$F:$F,記帳區!$K:$K,">=" & EOMONTH(S$2,-1) + 1,記帳區!$K:$K,"<=" & EOMONTH(S$2, 0),記帳區!$D:$D,$D71) -> 0
G72: =SUMIFS(記帳區!$F:$F,記帳區!$K:$K,">=" & EOMONTH(G$2,-1) + 1,記帳區!$K:$K,"<=" & EOMONTH(G$2, 0),記帳區!$E:$E,$D72) -> 0 | H72: =SUMIFS(記帳區!$F:$F,記帳區!$K:$K,">=" & EOMONTH(H$2,-1) + 1,記帳區!$K:$K,"<=" & EOMONTH(H$2, 0),記帳區!$E:$E,$D72) -> 0 | I72: =SUMIFS(記帳區!$F:$F,記帳區!$K:$K,">=" & EOMONTH(I$2,-1) + 1,記帳區!$K:$K,"<=" & EOMONTH(I$2, 0),記帳區!$E:$E,$D72) -> 0 | J72: =SUMIFS(記帳區!$F:$F,記帳區!$K:$K,">=" & EOMONTH(J$2,-1) + 1,記帳區!$K:$K,"<=" & EOMONTH(J$2, 0),記帳區!$E:$E,$D72) -> 0 | K72: =SUMIFS(記帳區!$F:$F,記帳區!$K:$K,">=" & EOMONTH(K$2,-1) + 1,記帳區!$K:$K,"<=" & EOMONTH(K$2, 0),記帳區!$E:$E,$D72) -> 0 | L72: =SUMIFS(記帳區!$F:$F,記帳區!$K:$K,">=" & EOMONTH(L$2,-1) + 1,記帳區!$K:$K,"<=" & EOMONTH(L$2, 0),記帳區!$E:$E,$D72) -> 0 | M72: =SUMIFS(記帳區!$F:$F,記帳區!$K:$K,">=" & EOMONTH(M$2,-1) + 1,記帳區!$K:$K,"<=" & EOMONTH(M$2, 0),記帳區!$E:$E,$D72) -> 0 | N72: =SUMIFS(記帳區!$F:$F,記帳區!$K:$K,">=" & EOMONTH(N$2,-1) + 1,記帳區!$K:$K,"<=" & EOMONTH(N$2, 0),記帳區!$E:$E,$D72) -> 0 | ... S72: =SUMIFS(記帳區!$F:$F,記帳區!$K:$K,">=" & EOMONTH(S$2,-1) + 1,記帳區!$K:$K,"<=" & EOMONTH(S$2, 0),記帳區!$E:$E,$D72) -> 0
G73: =SUMIFS(記帳區!$F:$F,記帳區!$K:$K,">=" & EOMONTH(G$2,-1) + 1,記帳區!$K:$K,"<=" & EOMONTH(G$2, 0),記帳區!$E:$E,$D73) -> 0 | H73: =SUMIFS(記帳區!$F:$F,記帳區!$K:$K,">=" & EOMONTH(H$2,-1) + 1,記帳區!$K:$K,"<=" & EOMONTH(H$2, 0),記帳區!$E:$E,$D73) -> 0 | I73: =SUMIFS(記帳區!$F:$F,記帳區!$K:$K,">=" & EOMONTH(I$2,-1) + 1,記帳區!$K:$K,"<=" & EOMONTH(I$2, 0),記帳區!$E:$E,$D73) -> 0 | J73: =SUMIFS(記帳區!$F:$F,記帳區!$K:$K,">=" & EOMONTH(J$2,-1) + 1,記帳區!$K:$K,"<=" & EOMONTH(J$2, 0),記帳區!$E:$E,$D73) -> 0 | K73: =SUMIFS(記帳區!$F:$F,記帳區!$K:$K,">=" & EOMONTH(K$2,-1) + 1,記帳區!$K:$K,"<=" & EOMONTH(K$2, 0),記帳區!$E:$E,$D73) -> 0 | L73: =SUMIFS(記帳區!$F:$F,記帳區!$K:$K,">=" & EOMONTH(L$2,-1) + 1,記帳區!$K:$K,"<=" & EOMONTH(L$2, 0),記帳區!$E:$E,$D73) -> 0 | M73: =SUMIFS(記帳區!$F:$F,記帳區!$K:$K,">=" & EOMONTH(M$2,-1) + 1,記帳區!$K:$K,"<=" & EOMONTH(M$2, 0),記帳區!$E:$E,$D73) -> 0 | N73: =SUMIFS(記帳區!$F:$F,記帳區!$K:$K,">=" & EOMONTH(N$2,-1) + 1,記帳區!$K:$K,"<=" & EOMONTH(N$2, 0),記帳區!$E:$E,$D73) -> 0 | ... S73: =SUMIFS(記帳區!$F:$F,記帳區!$K:$K,">=" & EOMONTH(S$2,-1) + 1,記帳區!$K:$K,"<=" & EOMONTH(S$2, 0),記帳區!$E:$E,$D73) -> 0
D74: 保險 | E74: =E6*0.15 -> 11400 | G74: =SUMIFS(記帳區!$F:$F,記帳區!$K:$K,">=" & EOMONTH(G$2,-1) + 1,記帳區!$K:$K,"<=" & EOMONTH(G$2, 0),記帳區!$D:$D,$D74) -> 0 | H74: =SUMIFS(記帳區!$F:$F,記帳區!$K:$K,">=" & EOMONTH(H$2,-1) + 1,記帳區!$K:$K,"<=" & EOMONTH(H$2, 0),記帳區!$D:$D,$D74) -> 0 | I74: =SUMIFS(記帳區!$F:$F,記帳區!$K:$K,">=" & EOMONTH(I$2,-1) + 1,記帳區!$K:$K,"<=" & EOMONTH(I$2, 0),記帳區!$D:$D,$D74) -> 0 | J74: =SUMIFS(記帳區!$F:$F,記帳區!$K:$K,">=" & EOMONTH(J$2,-1) + 1,記帳區!$K:$K,"<=" & EOMONTH(J$2, 0),記帳區!$D:$D,$D74) -> 0 | K74: =SUMIFS(記帳區!$F:$F,記帳區!$K:$K,">=" & EOMONTH(K$2,-1) + 1,記帳區!$K:$K,"<=" & EOMONTH(K$2, 0),記帳區!$D:$D,$D74) -> 0 | L74: =SUMIFS(記帳區!$F:$F,記帳區!$K:$K,">=" & EOMONTH(L$2,-1) + 1,記帳區!$K:$K,"<=" & EOMONTH(L$2, 0),記帳區!$D:$D,$D74) -> 0 | M74: =SUMIFS(記帳區!$F:$F,記帳區!$K:$K,">=" & EOMONTH(M$2,-1) + 1,記帳區!$K:$K,"<=" & EOMONTH(M$2, 0),記帳區!$D:$D,$D74) -> 0 | N74: =SUMIFS(記帳區!$F:$F,記帳區!$K:$K,">=" & EOMONTH(N$2,-1) + 1,記帳區!$K:$K,"<=" & EOMONTH(N$2, 0),記帳區!$D:$D,$D74) -> 0 | ... S74: =SUMIFS(記帳區!$F:$F,記帳區!$K:$K,">=" & EOMONTH(S$2,-1) + 1,記帳區!$K:$K,"<=" & EOMONTH(S$2, 0),記帳區!$D:$D,$D74) -> 0
G75: =SUMIFS(記帳區!$F:$F,記帳區!$K:$K,">=" & EOMONTH(G$2,-1) + 1,記帳區!$K:$K,"<=" & EOMONTH(G$2, 0),記帳區!$E:$E,$D75) -> 0 | H75: =SUMIFS(記帳區!$F:$F,記帳區!$K:$K,">=" & EOMONTH(H$2,-1) + 1,記帳區!$K:$K,"<=" & EOMONTH(H$2, 0),記帳區!$E:$E,$D75) -> 0 | I75: =SUMIFS(記帳區!$F:$F,記帳區!$K:$K,">=" & EOMONTH(I$2,-1) + 1,記帳區!$K:$K,"<=" & EOMONTH(I$2, 0),記帳區!$E:$E,$D75) -> 0 | J75: =SUMIFS(記帳區!$F:$F,記帳區!$K:$K,">=" & EOMONTH(J$2,-1) + 1,記帳區!$K:$K,"<=" & EOMONTH(J$2, 0),記帳區!$E:$E,$D75) -> 0 | K75: =SUMIFS(記帳區!$F:$F,記帳區!$K:$K,">=" & EOMONTH(K$2,-1) + 1,記帳區!$K:$K,"<=" & EOMONTH(K$2, 0),記帳區!$E:$E,$D75) -> 0 | L75: =SUMIFS(記帳區!$F:$F,記帳區!$K:$K,">=" & EOMONTH(L$2,-1) + 1,記帳區!$K:$K,"<=" & EOMONTH(L$2, 0),記帳區!$E:$E,$D75) -> 0 | M75: =SUMIFS(記帳區!$F:$F,記帳區!$K:$K,">=" & EOMONTH(M$2,-1) + 1,記帳區!$K:$K,"<=" & EOMONTH(M$2, 0),記帳區!$E:$E,$D75) -> 0 | N75: =SUMIFS(記帳區!$F:$F,記帳區!$K:$K,">=" & EOMONTH(N$2,-1) + 1,記帳區!$K:$K,"<=" & EOMONTH(N$2, 0),記帳區!$E:$E,$D75) -> 0 | ... S75: =SUMIFS(記帳區!$F:$F,記帳區!$K:$K,">=" & EOMONTH(S$2,-1) + 1,記帳區!$K:$K,"<=" & EOMONTH(S$2, 0),記帳區!$E:$E,$D75) -> 0
G76: =SUMIFS(記帳區!$F:$F,記帳區!$K:$K,">=" & EOMONTH(G$2,-1) + 1,記帳區!$K:$K,"<=" & EOMONTH(G$2, 0),記帳區!$E:$E,$D76) -> 0 | H76: =SUMIFS(記帳區!$F:$F,記帳區!$K:$K,">=" & EOMONTH(H$2,-1) + 1,記帳區!$K:$K,"<=" & EOMONTH(H$2, 0),記帳區!$E:$E,$D76) -> 0 | I76: =SUMIFS(記帳區!$F:$F,記帳區!$K:$K,">=" & EOMONTH(I$2,-1) + 1,記帳區!$K:$K,"<=" & EOMONTH(I$2, 0),記帳區!$E:$E,$D76) -> 0 | J76: =SUMIFS(記帳區!$F:$F,記帳區!$K:$K,">=" & EOMONTH(J$2,-1) + 1,記帳區!$K:$K,"<=" & EOMONTH(J$2, 0),記帳區!$E:$E,$D76) -> 0 | K76: =SUMIFS(記帳區!$F:$F,記帳區!$K:$K,">=" & EOMONTH(K$2,-1) + 1,記帳區!$K:$K,"<=" & EOMONTH(K$2, 0),記帳區!$E:$E,$D76) -> 0 | L76: =SUMIFS(記帳區!$F:$F,記帳區!$K:$K,">=" & EOMONTH(L$2,-1) + 1,記帳區!$K:$K,"<=" & EOMONTH(L$2, 0),記帳區!$E:$E,$D76) -> 0 | M76: =SUMIFS(記帳區!$F:$F,記帳區!$K:$K,">=" & EOMONTH(M$2,-1) + 1,記帳區!$K:$K,"<=" & EOMONTH(M$2, 0),記帳區!$E:$E,$D76) -> 0 | N76: =SUMIFS(記帳區!$F:$F,記帳區!$K:$K,">=" & EOMONTH(N$2,-1) + 1,記帳區!$K:$K,"<=" & EOMONTH(N$2, 0),記帳區!$E:$E,$D76) -> 0 | ... S76: =SUMIFS(記帳區!$F:$F,記帳區!$K:$K,">=" & EOMONTH(S$2,-1) + 1,記帳區!$K:$K,"<=" & EOMONTH(S$2, 0),記帳區!$E:$E,$D76) -> 0
G77: =SUMIFS(記帳區!$F:$F,記帳區!$K:$K,">=" & EOMONTH(G$2,-1) + 1,記帳區!$K:$K,"<=" & EOMONTH(G$2, 0),記帳區!$E:$E,$D77) -> 0 | H77: =SUMIFS(記帳區!$F:$F,記帳區!$K:$K,">=" & EOMONTH(H$2,-1) + 1,記帳區!$K:$K,"<=" & EOMONTH(H$2, 0),記帳區!$E:$E,$D77) -> 0 | I77: =SUMIFS(記帳區!$F:$F,記帳區!$K:$K,">=" & EOMONTH(I$2,-1) + 1,記帳區!$K:$K,"<=" & EOMONTH(I$2, 0),記帳區!$E:$E,$D77) -> 0 | J77: =SUMIFS(記帳區!$F:$F,記帳區!$K:$K,">=" & EOMONTH(J$2,-1) + 1,記帳區!$K:$K,"<=" & EOMONTH(J$2, 0),記帳區!$E:$E,$D77) -> 0 | K77: =SUMIFS(記帳區!$F:$F,記帳區!$K:$K,">=" & EOMONTH(K$2,-1) + 1,記帳區!$K:$K,"<=" & EOMONTH(K$2, 0),記帳區!$E:$E,$D77) -> 0 | L77: =SUMIFS(記帳區!$F:$F,記帳區!$K:$K,">=" & EOMONTH(L$2,-1) + 1,記帳區!$K:$K,"<=" & EOMONTH(L$2, 0),記帳區!$E:$E,$D77) -> 0 | M77: =SUMIFS(記帳區!$F:$F,記帳區!$K:$K,">=" & EOMONTH(M$2,-1) + 1,記帳區!$K:$K,"<=" & EOMONTH(M$2, 0),記帳區!$E:$E,$D77) -> 0 | N77: =SUMIFS(記帳區!$F:$F,記帳區!$K:$K,">=" & EOMONTH(N$2,-1) + 1,記帳區!$K:$K,"<=" & EOMONTH(N$2, 0),記帳區!$E:$E,$D77) -> 0 | ... S77: =SUMIFS(記帳區!$F:$F,記帳區!$K:$K,">=" & EOMONTH(S$2,-1) + 1,記帳區!$K:$K,"<=" & EOMONTH(S$2, 0),記帳區!$E:$E,$D77) -> 0
D78: 投資 | E78: =E6*0.15 -> 11400 | G78: =SUMIFS(記帳區!$F:$F,記帳區!$K:$K,">=" & EOMONTH(G$2,-1) + 1,記帳區!$K:$K,"<=" & EOMONTH(G$2, 0),記帳區!$D:$D,$D78) -> 0 | H78: =SUMIFS(記帳區!$F:$F,記帳區!$K:$K,">=" & EOMONTH(H$2,-1) + 1,記帳區!$K:$K,"<=" & EOMONTH(H$2, 0),記帳區!$D:$D,$D78) -> -20000 | I78: =SUMIFS(記帳區!$F:$F,記帳區!$K:$K,">=" & EOMONTH(I$2,-1) + 1,記帳區!$K:$K,"<=" & EOMONTH(I$2, 0),記帳區!$D:$D,$D78) -> 0 | J78: =SUMIFS(記帳區!$F:$F,記帳區!$K:$K,">=" & EOMONTH(J$2,-1) + 1,記帳區!$K:$K,"<=" & EOMONTH(J$2, 0),記帳區!$D:$D,$D78) -> 0 | K78: =SUMIFS(記帳區!$F:$F,記帳區!$K:$K,">=" & EOMONTH(K$2,-1) + 1,記帳區!$K:$K,"<=" & EOMONTH(K$2, 0),記帳區!$D:$D,$D78) -> 0 | L78: =SUMIFS(記帳區!$F:$F,記帳區!$K:$K,">=" & EOMONTH(L$2,-1) + 1,記帳區!$K:$K,"<=" & EOMONTH(L$2, 0),記帳區!$D:$D,$D78) -> 0 | M78: =SUMIFS(記帳區!$F:$F,記帳區!$K:$K,">=" & EOMONTH(M$2,-1) + 1,記帳區!$K:$K,"<=" & EOMONTH(M$2, 0),記帳區!$D:$D,$D78) -> 0 | N78: =SUMIFS(記帳區!$F:$F,記帳區!$K:$K,">=" & EOMONTH(N$2,-1) + 1,記帳區!$K:$K,"<=" & EOMONTH(N$2, 0),記帳區!$D:$D,$D78) -> 0 | ... S78: =SUMIFS(記帳區!$F:$F,記帳區!$K:$K,">=" & EOMONTH(S$2,-1) + 1,記帳區!$K:$K,"<=" & EOMONTH(S$2, 0),記帳區!$D:$D,$D78) -> 0
D79: 外匯 | G79: =SUMIFS(記帳區!$F:$F,記帳區!$K:$K,">=" & EOMONTH(G$2,-1) + 1,記帳區!$K:$K,"<=" & EOMONTH(G$2, 0),記帳區!$E:$E,$D79) -> 0 | H79: =SUMIFS(記帳區!$F:$F,記帳區!$K:$K,">=" & EOMONTH(H$2,-1) + 1,記帳區!$K:$K,"<=" & EOMONTH(H$2, 0),記帳區!$E:$E,$D79) -> -20000 | I79: =SUMIFS(記帳區!$F:$F,記帳區!$K:$K,">=" & EOMONTH(I$2,-1) + 1,記帳區!$K:$K,"<=" & EOMONTH(I$2, 0),記帳區!$E:$E,$D79) -> 0 | J79: =SUMIFS(記帳區!$F:$F,記帳區!$K:$K,">=" & EOMONTH(J$2,-1) + 1,記帳區!$K:$K,"<=" & EOMONTH(J$2, 0),記帳區!$E:$E,$D79) -> 0 | K79: =SUMIFS(記帳區!$F:$F,記帳區!$K:$K,">=" & EOMONTH(K$2,-1) + 1,記帳區!$K:$K,"<=" & EOMONTH(K$2, 0),記帳區!$E:$E,$D79) -> 0 | L79: =SUMIFS(記帳區!$F:$F,記帳區!$K:$K,">=" & EOMONTH(L$2,-1) + 1,記帳區!$K:$K,"<=" & EOMONTH(L$2, 0),記帳區!$E:$E,$D79) -> 0 | M79: =SUMIFS(記帳區!$F:$F,記帳區!$K:$K,">=" & EOMONTH(M$2,-1) + 1,記帳區!$K:$K,"<=" & EOMONTH(M$2, 0),記帳區!$E:$E,$D79) -> 0 | N79: =SUMIFS(記帳區!$F:$F,記帳區!$K:$K,">=" & EOMONTH(N$2,-1) + 1,記帳區!$K:$K,"<=" & EOMONTH(N$2, 0),記帳區!$E:$E,$D79) -> 0 | ... S79: =SUMIFS(記帳區!$F:$F,記帳區!$K:$K,">=" & EOMONTH(S$2,-1) + 1,記帳區!$K:$K,"<=" & EOMONTH(S$2, 0),記帳區!$E:$E,$D79) -> 0

Sheet 資產投資組合

Sheet 保險計畫表
B2: 年度保費 | C2: 名稱 | D2: 類型 | E2: 期限 | F2: 身故保障(萬元) | I2: 住院醫療(元) | K2: 傷殘給付(萬元) | N2: 手術給付(元) | P2: 癌症給付(萬元)
F3: 身故壽險 | G3: 意外身故 | H3: 癌症身故 | I3: 實支實付 | J3: 日院住額 | K3: 1-3級 | L3: 3-6級 | M3: 7-10級 | N3: 一般手術 | O3: 重大手術 | P3: 一次給付 | Q3: 治療給付
B4: 3600 | C4: XXX人壽全方位終生壽險 | F4: 100 | G4: 50 | H4: 50
B5: 3800 | C5: XXX人壽醫療實支實付 | I5: 2000
B30: =SUM(B4:B29) -> 7400 | C30: 總額 | F30: =SUM(F4:F29) -> 100 | G30: =SUM(G4:G29) -> 50 | H30: =SUM(H4:H29) -> 50 | I30: =SUM(I4:I29) -> 2000 | J30: =SUM(J4:J29) -> 0 | K30: =SUM(K4:K29) -> 0 | L30: =SUM(L4:L29) -> 0 | M30: =SUM(M4:M29) -> 0 | ... Q30: =SUM(Q4:Q29) -> 0
C31: 達標指數

Sheet 貸款試算
A1: 貸款名稱 | C1: 聯邦信用卡(16.07%) | G1: 星展信用卡(15.89%) | K1: 中信信貸(14.78%) | O1: 中信信貸(14.78%) | S1: 星展信貸(5.99%) | W1: 整合
A2: 貸款金額 | C2: 72230 | G2: 7887 | K2: 252574 | O2: 1459626 | S2: 31553 | W2: =D11+L11+P11+T11 -> 1642107.8
A3: 利率 | C3: 0.1607 | G3: 0.1589 | K3: 0.1478 | O3: 0.1478 | S3: 0.0599 | W3: 0.1478
A4: 期數 | C4: 12 | G4: 4 | K4: 74 | O4: 74 | S4: 22 | W4: 72
A5: 每期付款 | C5: =PMT(C3/12,C4,C2) -> -6555.8828 | G5: =PMT(G3/12,G4,G2) -> -2037.4524 | K5: =PMT(K3/12,K4,K2) -> -5221.2592 | O5: =PMT(O3/12,O4,O2) -> -30173.675 | S5: =PMT(S3/12,S4,S2) -> -1517.9924 | W5: =PMT(W3/12,W4,W2) -> -34526.501
B7: 總餘額 | C7: 期數 | D7: 餘額 | E7: 已償本金 | F7: 已償利息 | G7: 期數 | H7: 餘額 | I7: 已償本金 | J7: 已償利息 | K7: 期數 | L7: 餘額 | M7: 已償本金 | N7: 已償利息 | O7: 期數 | P7: 餘額 | Q7: 已償本金 | R7: 已償利息 | S7: 期數 | T7: 餘額 | U7: 已償本金 | V7: 已償利息 | W7: 期數 | X7: 餘額 | Y7: 已償本金 | Z7: 已償利息
A8: 45870 | B8: =D8+H8+L8+P8+T8 -> 1778363.7 | C8: 1 | D8: =C2+C5 -> 65674.117 | E8: =PPMT($C$3/12,C8,$C$4,$C$2) -> -5588.6027 | F8: =IPMT($C$3/12,C8,$C$4,$C$2) -> -967.28008 | G8: 1 | H8: =G2+G5 -> 5849.5476 | I8: =PPMT($G$3/12,G8,$G$4,$G$2) -> -1933.0154 | J8: =IPMT($G$3/12,G8,$G$4,$G$2) -> -104.43703 | K8: 1 | L8: =K2+K5 -> 247352.74 | M8: =PPMT($K$3/12,K8,$K$4,$K$2) -> -2110.3895 | N8: =IPMT($K$3/12,K8,$K$4,$K$2) -> -3110.8698 | O8: 1 | P8: =O2+O5 -> 1429452.3 | Q8: =PPMT($O$3/12,O8,$O$4,$O$2) -> -12195.948 | R8: =IPMT($O$3/12,O8,$O$4,$O$2) -> -17977.727 | S8: 1 | T8: =S2+S5 -> 30035.008 | U8: =PPMT($S$3/12,S8,$S$4,$S$2) -> -1360.4904 | V8: =IPMT($S$3/12,S8,$S$4,$S$2) -> -157.50206 | W8: 1 | X8: =W2+W5 -> 1607581.3 | Y8: =PPMT($O$3/12,W8,$O$4,$O$2) -> -12195.948 | Z8: =IPMT($O$3/12,W8,$O$4,$O$2) -> -17977.727 | AA8: 56 | AB8: =23128*AA8 -> 1295168
A9: =EDATE(A8,1) -> 45901 | B9: =D9+H9+L9+P9+T9 -> 1732857.5 | C9: 2 | D9: =D8+$C$5 -> 59118.234 | E9: =PPMT($C$3/12,C9,$C$4,$C$2) -> -5663.4434 | F9: =IPMT($C$3/12,C9,$C$4,$C$2) -> -892.43938 | G9: 2 | H9: =H8+$G$5 -> 3812.0951 | I9: =PPMT($G$3/12,G9,$G$4,$G$2) -> -1958.6118 | J9: =IPMT($G$3/12,G9,$G$4,$G$2) -> -78.840679 | K9: 2 | L9: =L8+$K$5 -> 242131.48 | M9: =IPMT($K$3/12,K9,$K$4,$K$2) -> -3084.8768 | N9: =IPMT($K$3/12,K9,$K$4,$K$2) -> -3084.8768 | O9: 2 | P9: =P8+$O$5 -> 1399278.7 | Q9: =PPMT($O$3/12,O9,$O$4,$O$2) -> -12346.161 | R9: =IPMT($O$3/12,O9,$O$4,$O$2) -> -17827.513 | S9: 2 | T9: =T8+$S$5 -> 28517.015 | U9: =PPMT($S$3/12,S9,$S$4,$S$2) -> -1367.2815 | V9: =IPMT($S$3/12,S9,$S$4,$S$2) -> -150.71094 | W9: 2 | X9: =X8+$O$5 -> 1577407.6 | Y9: =PPMT($O$3/12,W9,$O$4,$O$2) -> -12346.161 | Z9: =IPMT($O$3/12,W9,$O$4,$O$2) -> -17827.513 | AA9: =AA8-1 -> 55 | AB9: =23128*AA9 -> 1272040
A10: =EDATE(A9,1) -> 45931 | B10: =D10+H10+L10+P10+T10 -> 1687351.2 | C10: 3 | D10: =D9+$C$5 -> 52562.352 | E10: =PPMT($C$3/12,C10,$C$4,$C$2) -> -5739.2863 | F10: =IPMT($C$3/12,C10,$C$4,$C$2) -> -816.59643 | G10: 3 | H10: =H9+$G$5 -> 1774.6427 | I10: =PPMT($G$3/12,G10,$G$4,$G$2) -> -1984.5471 | J10: =IPMT($G$3/12,G10,$G$4,$G$2) -> -52.905395 | K10: 3 | L10: =L9+$K$5 -> 236910.22 | M10: =IPMT($K$3/12,K10,$K$4,$K$2) -> -3058.5637 | N10: =IPMT($K$3/12,K10,$K$4,$K$2) -> -3058.5637 | O10: 3 | P10: =P9+$O$5 -> 1369105 | Q10: =PPMT($O$3/12,O10,$O$4,$O$2) -> -12498.225 | R10: =IPMT($O$3/12,O10,$O$4,$O$2) -> -17675.45 | S10: 3 | T10: =T9+$S$5 -> 26999.023 | U10: =PPMT($S$3/12,S10,$S$4,$S$2) -> -1374.1065 | V10: =IPMT($S$3/12,S10,$S$4,$S$2) -> -143.88593 | W10: 3 | X10: =X9+$O$5 -> 1547233.9 | Y10: =PPMT($O$3/12,W10,$O$4,$O$2) -> -12498.225 | Z10: =IPMT($O$3/12,W10,$O$4,$O$2) -> -17675.45 | AA10: =AA9-1 -> 54 | AB10: =23128*AA10 -> 1248912
A11: =EDATE(A10,1) -> 45962 | B11: =D11+H11+L11+P11+T11 -> 1641845 | C11: 4 | D11: =D10+$C$5 -> 46006.469 | E11: =PPMT($C$3/12,C11,$C$4,$C$2) -> -5816.1449 | F11: =IPMT($C$3/12,C11,$C$4,$C$2) -> -739.73782 | G11: 4 | H11: =H10+$G$5 -> -262.80978 | I11: =PPMT($G$3/12,G11,$G$4,$G$2) -> -2010.8258 | J11: =IPMT($G$3/12,G11,$G$4,$G$2) -> -26.626684 | K11: 4 | L11: =L10+$K$5 -> 231688.96 | M11: =IPMT($K$3/12,K11,$K$4,$K$2) -> -3031.9265 | N11: =IPMT($K$3/12,K11,$K$4,$K$2) -> -3031.9265 | O11: 4 | P11: =P10+$O$5 -> 1338931.3 | Q11: =PPMT($O$3/12,O11,$O$4,$O$2) -> -12652.161 | R11: =IPMT($O$3/12,O11,$O$4,$O$2) -> -17521.513 | S11: 4 | T11: =T10+$S$5 -> 25481.03 | U11: =PPMT($S$3/12,S11,$S$4,$S$2) -> -1380.9656 | V11: =IPMT($S$3/12,S11,$S$4,$S$2) -> -137.02685 | W11: 4 | X11: =X10+$O$5 -> 1517060.2 | Y11: =PPMT($O$3/12,W11,$O$4,$O$2) -> -12652.161 | Z11: =IPMT($O$3/12,W11,$O$4,$O$2) -> -17521.513 | AA11: =AA10-1 -> 53 | AB11: =23128*AA11 -> 1225784
A12: =EDATE(A11,1) -> 45992 | B12: =D12+H12+L12+P12+T12 -> 1598639 | C12: 5 | D12: =D11+$C$5 -> 39450.586 | E12: =PPMT($C$3/12,C12,$C$4,$C$2) -> -5894.0328 | F12: =IPMT($C$3/12,C12,$C$4,$C$2) -> -661.84995 | K12: 5 | L12: =L11+$K$5 -> 226467.7 | M12: =IPMT($K$3/12,K12,$K$4,$K$2) -> -3004.9612 | N12: =IPMT($K$3/12,K12,$K$4,$K$2) -> -3004.9612 | O12: 5 | P12: =P11+$O$5 -> 1308757.6 | Q12: =PPMT($O$3/12,O12,$O$4,$O$2) -> -12807.994 | R12: =IPMT($O$3/12,O12,$O$4,$O$2) -> -17365.681 | S12: 5 | T12: =T11+$S$5 -> 23963.038 | U12: =PPMT($S$3/12,S12,$S$4,$S$2) -> -1387.8589 | V12: =IPMT($S$3/12,S12,$S$4,$S$2) -> -130.13353 | W12: 5 | X12: =X11+$O$5 -> 1486886.6 | Y12: =PPMT($O$3/12,W12,$O$4,$O$2) -> -12807.994 | Z12: =IPMT($O$3/12,W12,$O$4,$O$2) -> -17365.681 | AA12: =AA11-1 -> 52 | AB12: =23128*AA12 -> 1202656
A13: =EDATE(A12,1) -> 46023 | B13: =D13+H13+L13+P13+T13 -> 1555170.1 | C13: 6 | D13: =D12+$C$5 -> 32894.703 | E13: =PPMT($C$3/12,C13,$C$4,$C$2) -> -5972.9637 | F13: =IPMT($C$3/12,C13,$C$4,$C$2) -> -582.91903 | K13: 6 | L13: =L12+$K$5 -> 221246.44 | M13: =IPMT($K$3/12,K13,$K$4,$K$2) -> -2977.6638 | N13: =IPMT($K$3/12,K13,$K$4,$K$2) -> -2977.6638 | O13: 6 | P13: =P12+$O$5 -> 1278584 | Q13: =PPMT($O$3/12,O13,$O$4,$O$2) -> -12965.746 | R13: =IPMT($O$3/12,O13,$O$4,$O$2) -> -17207.929 | S13: 6 | T13: =T12+$S$5 -> 22445.046 | U13: =PPMT($S$3/12,S13,$S$4,$S$2) -> -1394.7866 | V13: =IPMT($S$3/12,S13,$S$4,$S$2) -> -123.2058 | W13: 6 | X13: =X12+$O$5 -> 1456712.9 | Y13: =PPMT($O$3/12,W13,$O$4,$O$2) -> -12965.746 | Z13: =IPMT($O$3/12,W13,$O$4,$O$2) -> -17207.929 | AA13: =AA12-1 -> 51 | AB13: =23128*AA13 -> 1179528
A14: =EDATE(A13,1) -> 46054 | B14: =D14+H14+L14+P14+T14 -> 1511701.3 | C14: 7 | D14: =D13+$C$5 -> 26338.821 | E14: =PPMT($C$3/12,C14,$C$4,$C$2) -> -6052.9517 | F14: =IPMT($C$3/12,C14,$C$4,$C$2) -> -502.93109 | K14: 7 | L14: =L13+$K$5 -> 216025.19 | M14: =IPMT($K$3/12,K14,$K$4,$K$2) -> -2950.0302 | N14: =IPMT($K$3/12,K14,$K$4,$K$2) -> -2950.0302 | O14: 7 | P14: =P13+$O$5 -> 1248410.3 | Q14: =PPMT($O$3/12,O14,$O$4,$O$2) -> -13125.44 | R14: =IPMT($O$3/12,O14,$O$4,$O$2) -> -17048.234 | S14: 7 | T14: =T13+$S$5 -> 20927.053 | U14: =PPMT($S$3/12,S14,$S$4,$S$2) -> -1401.7489 | V14: =IPMT($S$3/12,S14,$S$4,$S$2) -> -116.24349 | W14: 7 | X14: =X13+$O$5 -> 1426539.2 | Y14: =PPMT($O$3/12,W14,$O$4,$O$2) -> -13125.44 | Z14: =IPMT($O$3/12,W14,$O$4,$O$2) -> -17048.234 | AA14: =AA13-1 -> 50 | AB14: =23128*AA14 -> 1156400
A15: =EDATE(A14,1) -> 46082 | B15: =D15+H15+L15+P15+T15 -> 1468232.5 | C15: 8 | D15: =D14+$C$5 -> 19782.938 | E15: =PPMT($C$3/12,C15,$C$4,$C$2) -> -6134.0108 | F15: =IPMT($C$3/12,C15,$C$4,$C$2) -> -421.87198 | K15: 8 | L15: =L14+$K$5 -> 210803.93 | M15: =IPMT($K$3/12,K15,$K$4,$K$2) -> -2922.0562 | N15: =IPMT($K$3/12,K15,$K$4,$K$2) -> -2922.0562 | O15: 8 | P15: =P14+$O$5 -> 1218236.6 | Q15: =PPMT($O$3/12,O15,$O$4,$O$2) -> -13287.102 | R15: =IPMT($O$3/12,O15,$O$4,$O$2) -> -16886.573 | S15: 8 | T15: =T14+$S$5 -> 19409.061 | U15: =PPMT($S$3/12,S15,$S$4,$S$2) -> -1408.746 | V15: =IPMT($S$3/12,S15,$S$4,$S$2) -> -109.24643 | W15: 8 | X15: =X14+$O$5 -> 1396365.5 | Y15: =PPMT($O$3/12,W15,$O$4,$O$2) -> -13287.102 | Z15: =IPMT($O$3/12,W15,$O$4,$O$2) -> -16886.573 | AA15: =AA14-1 -> 49 | AB15: =23128*AA15 -> 1133272
A16: =EDATE(A15,1) -> 46113 | B16: =D16+H16+L16+P16+T16 -> 1424763.7 | C16: 9 | D16: =D15+$C$5 -> 13227.055 | E16: =PPMT($C$3/12,C16,$C$4,$C$2) -> -6216.1554 | F16: =IPMT($C$3/12,C16,$C$4,$C$2) -> -339.72735 | K16: 9 | L16: =L15+$K$5 -> 205582.67 | M16: =IPMT($K$3/12,K16,$K$4,$K$2) -> -2893.7377 | N16: =IPMT($K$3/12,K16,$K$4,$K$2) -> -2893.7377 | O16: 9 | P16: =P15+$O$5 -> 1188062.9 | Q16: =PPMT($O$3/12,O16,$O$4,$O$2) -> -13450.755 | R16: =IPMT($O$3/12,O16,$O$4,$O$2) -> -16722.92 | S16: 9 | T16: =T15+$S$5 -> 17891.068 | U16: =PPMT($S$3/12,S16,$S$4,$S$2) -> -1415.778 | V16: =IPMT($S$3/12,S16,$S$4,$S$2) -> -102.21444 | W16: 9 | X16: =X15+$O$5 -> 1366191.9 | Y16: =PPMT($O$3/12,W16,$O$4,$O$2) -> -13450.755 | Z16: =IPMT($O$3/12,W16,$O$4,$O$2) -> -16722.92 | AA16: =AA15-1 -> 48 | AB16: =23128*AA16 -> 1110144
A17: =EDATE(A16,1) -> 46143 | B17: =D17+H17+L17+P17+T17 -> 1381294.9 | C17: 10 | D17: =D16+$C$5 -> 6671.1725 | E17: =PPMT($C$3/12,C17,$C$4,$C$2) -> -6299.4001 | F17: =IPMT($C$3/12,C17,$C$4,$C$2) -> -256.48267 | K17: 10 | L17: =L16+$K$5 -> 200361.41 | M17: =IPMT($K$3/12,K17,$K$4,$K$2) -> -2865.0704 | N17: =IPMT($K$3/12,K17,$K$4,$K$2) -> -2865.0704 | O17: 10 | P17: =P16+$O$5 -> 1157889.3 | Q17: =PPMT($O$3/12,O17,$O$4,$O$2) -> -13616.423 | R17: =IPMT($O$3/12,O17,$O$4,$O$2) -> -16557.251 | S17: 10 | T17: =T16+$S$5 -> 16373.076 | U17: =PPMT($S$3/12,S17,$S$4,$S$2) -> -1422.8451 | V17: =IPMT($S$3/12,S17,$S$4,$S$2) -> -95.147345 | W17: 10 | X17: =X16+$O$5 -> 1336018.2 | Y17: =PPMT($O$3/12,W17,$O$4,$O$2) -> -13616.423 | Z17: =IPMT($O$3/12,W17,$O$4,$O$2) -> -16557.251 | AA17: =AA16-1 -> 47 | AB17: =23128*AA17 -> 1087016
A18: =EDATE(A17,1) -> 46174 | B18: =D18+H18+L18+P18+T18 -> 1337826.1 | C18: 11 | D18: =D17+$C$5 -> 115.28974 | E18: =PPMT($C$3/12,C18,$C$4,$C$2) -> -6383.7595 | F18: =IPMT($C$3/12,C18,$C$4,$C$2) -> -172.1232 | K18: 11 | L18: =L17+$K$5 -> 195140.15 | M18: =IPMT($K$3/12,K18,$K$4,$K$2) -> -2836.05 | N18: =IPMT($K$3/12,K18,$K$4,$K$2) -> -2836.05 | O18: 11 | P18: =P17+$O$5 -> 1127715.6 | Q18: =PPMT($O$3/12,O18,$O$4,$O$2) -> -13784.132 | R18: =IPMT($O$3/12,O18,$O$4,$O$2) -> -16389.543 | S18: 11 | T18: =T17+$S$5 -> 14855.083 | U18: =PPMT($S$3/12,S18,$S$4,$S$2) -> -1429.9474 | V18: =IPMT($S$3/12,S18,$S$4,$S$2) -> -88.044977 | W18: 11 | X18: =X17+$O$5 -> 1305844.5 | Y18: =PPMT($O$3/12,W18,$O$4,$O$2) -> -13784.132 | Z18: =IPMT($O$3/12,W18,$O$4,$O$2) -> -16389.543 | AA18: =AA17-1 -> 46 | AB18: =23128*AA18 -> 1063888
A19: =EDATE(A18,1) -> 46204 | B19: =D19+H19+L19+P19+T19 -> 1294357.3 | C19: 12 | D19: =D18+$C$5 -> -6440.593 | E19: =PPMT($C$3/12,C19,$C$4,$C$2) -> -6469.2487 | F19: =IPMT($C$3/12,C19,$C$4,$C$2) -> -86.634023 | K19: 12 | L19: =L18+$K$5 -> 189918.89 | M19: =IPMT($K$3/12,K19,$K$4,$K$2) -> -2806.6722 | N19: =IPMT($K$3/12,K19,$K$4,$K$2) -> -2806.6722 | O19: 12 | P19: =P18+$O$5 -> 1097541.9 | Q19: =PPMT($O$3/12,O19,$O$4,$O$2) -> -13953.907 | R19: =IPMT($O$3/12,O19,$O$4,$O$2) -> -16219.768 | S19: 12 | T19: =T18+$S$5 -> 13337.091 | U19: =PPMT($S$3/12,S19,$S$4,$S$2) -> -1437.0853 | V19: =IPMT($S$3/12,S19,$S$4,$S$2) -> -80.907156 | W19: 12 | X19: =X18+$O$5 -> 1275670.8 | Y19: =PPMT($O$3/12,W19,$O$4,$O$2) -> -13953.907 | Z19: =IPMT($O$3/12,W19,$O$4,$O$2) -> -16219.768 | AA19: =AA18-1 -> 45 | AB19: =23128*AA19 -> 1040760
A20: =EDATE(A19,1) -> 46235 | B20: =D20+H20+L20+P20+T20 -> 1263885 | K20: 13 | L20: =L19+$K$5 -> 184697.63 | M20: =IPMT($K$3/12,K20,$K$4,$K$2) -> -2776.9325 | N20: =IPMT($K$3/12,K20,$K$4,$K$2) -> -2776.9325 | O20: 13 | P20: =P19+$O$5 -> 1067368.2 | Q20: =PPMT($O$3/12,O20,$O$4,$O$2) -> -14125.772 | R20: =IPMT($O$3/12,O20,$O$4,$O$2) -> -16047.902 | S20: 13 | T20: =T19+$S$5 -> 11819.099 | U20: =PPMT($S$3/12,S20,$S$4,$S$2) -> -1444.2587 | V20: =IPMT($S$3/12,S20,$S$4,$S$2) -> -73.733705 | W20: 13 | X20: =X19+$O$5 -> 1245497.2 | Y20: =PPMT($O$3/12,W20,$O$4,$O$2) -> -14125.772 | Z20: =IPMT($O$3/12,W20,$O$4,$O$2) -> -16047.902 | AA20: =AA19-1 -> 44 | AB20: =23128*AA20 -> 1017632
A21: =EDATE(A20,1) -> 46266 | B21: =D21+H21+L21+P21+T21 -> 1226972 | K21: 14 | L21: =L20+$K$5 -> 179476.37 | M21: =IPMT($K$3/12,K21,$K$4,$K$2) -> -2746.8266 | N21: =IPMT($K$3/12,K21,$K$4,$K$2) -> -2746.8266 | O21: 14 | P21: =P20+$O$5 -> 1037194.6 | Q21: =PPMT($O$3/12,O21,$O$4,$O$2) -> -14299.755 | R21: =IPMT($O$3/12,O21,$O$4,$O$2) -> -15873.92 | S21: 14 | T21: =T20+$S$5 -> 10301.106 | U21: =PPMT($S$3/12,S21,$S$4,$S$2) -> -1451.468 | V21: =IPMT($S$3/12,S21,$S$4,$S$2) -> -66.524447 | W21: 14 | X21: =X20+$O$5 -> 1215323.5 | Y21: =PPMT($O$3/12,W21,$O$4,$O$2) -> -14299.755 | Z21: =IPMT($O$3/12,W21,$O$4,$O$2) -> -15873.92 | AA21: =AA20-1 -> 43 | AB21: =23128*AA21 -> 994504
A22: =EDATE(A21,1) -> 46296 | B22: =D22+H22+L22+P22+T22 -> 1190059.1 | K22: 15 | L22: =L21+$K$5 -> 174255.11 | M22: =IPMT($K$3/12,K22,$K$4,$K$2) -> -2716.3498 | N22: =IPMT($K$3/12,K22,$K$4,$K$2) -> -2716.3498 | O22: 15 | P22: =P21+$O$5 -> 1007020.9 | Q22: =PPMT($O$3/12,O22,$O$4,$O$2) -> -14475.88 | R22: =IPMT($O$3/12,O22,$O$4,$O$2) -> -15697.795 | S22: 15 | T22: =T21+$S$5 -> 8783.1138 | U22: =PPMT($S$3/12,S22,$S$4,$S$2) -> -1458.7132 | V22: =IPMT($S$3/12,S22,$S$4,$S$2) -> -59.279203 | W22: 15 | X22: =X21+$O$5 -> 1185149.8 | Y22: =PPMT($O$3/12,W22,$O$4,$O$2) -> -14475.88 | Z22: =IPMT($O$3/12,W22,$O$4,$O$2) -> -15697.795 | AA22: =AA21-1 -> 42 | AB22: =23128*AA22 -> 971376
A23: =EDATE(A22,1) -> 46327 | B23: =D23+H23+L23+P23+T23 -> 1153146.2 | K23: 16 | L23: =L22+$K$5 -> 169033.85 | M23: =IPMT($K$3/12,K23,$K$4,$K$2) -> -2685.4977 | N23: =IPMT($K$3/12,K23,$K$4,$K$2) -> -2685.4977 | O23: 16 | P23: =P22+$O$5 -> 976847.2 | Q23: =PPMT($O$3/12,O23,$O$4,$O$2) -> -14654.175 | R23: =IPMT($O$3/12,O23,$O$4,$O$2) -> -15519.5 | S23: 16 | T23: =T22+$S$5 -> 7265.1214 | U23: =PPMT($S$3/12,S23,$S$4,$S$2) -> -1465.9946 | V23: =IPMT($S$3/12,S23,$S$4,$S$2) -> -51.997793 | W23: 16 | X23: =X22+$O$5 -> 1154976.1 | Y23: =PPMT($O$3/12,W23,$O$4,$O$2) -> -14654.175 | Z23: =IPMT($O$3/12,W23,$O$4,$O$2) -> -15519.5 | AA23: =AA22-1 -> 41 | AB23: =23128*AA23 -> 948248
A24: =EDATE(A23,1) -> 46357 | B24: =D24+H24+L24+P24+T24 -> 1116233.2 | K24: 17 | L24: =L23+$K$5 -> 163812.59 | M24: =IPMT($K$3/12,K24,$K$4,$K$2) -> -2654.2655 | N24: =IPMT($K$3/12,K24,$K$4,$K$2) -> -2654.2655 | O24: 17 | P24: =P23+$O$5 -> 946673.53 | Q24: =PPMT($O$3/12,O24,$O$4,$O$2) -> -14834.665 | R24: =IPMT($O$3/12,O24,$O$4,$O$2) -> -15339.009 | S24: 17 | T24: =T23+$S$5 -> 5747.129 | U24: =PPMT($S$3/12,S24,$S$4,$S$2) -> -1473.3124 | V24: =IPMT($S$3/12,S24,$S$4,$S$2) -> -44.680036 | W24: 17 | X24: =X23+$O$5 -> 1124802.5 | Y24: =PPMT($O$3/12,W24,$O$4,$O$2) -> -14834.665 | Z24: =IPMT($O$3/12,W24,$O$4,$O$2) -> -15339.009 | AA24: =AA23-1 -> 40 | AB24: =23128*AA24 -> 925120
A25: =EDATE(A24,1) -> 46388 | B25: =D25+H25+L25+P25+T25 -> 1079320.3 | K25: 18 | L25: =L24+$K$5 -> 158591.33 | M25: =IPMT($K$3/12,K25,$K$4,$K$2) -> -2622.6487 | N25: =IPMT($K$3/12,K25,$K$4,$K$2) -> -2622.6487 | O25: 18 | P25: =P24+$O$5 -> 916499.85 | Q25: =PPMT($O$3/12,O25,$O$4,$O$2) -> -15017.379 | R25: =IPMT($O$3/12,O25,$O$4,$O$2) -> -15156.296 | S25: 18 | T25: =T24+$S$5 -> 4229.1366 | U25: =PPMT($S$3/12,S25,$S$4,$S$2) -> -1480.6667 | V25: =IPMT($S$3/12,S25,$S$4,$S$2) -> -37.325752 | W25: 18 | X25: =X24+$O$5 -> 1094628.8 | Y25: =PPMT($O$3/12,W25,$O$4,$O$2) -> -15017.379 | Z25: =IPMT($O$3/12,W25,$O$4,$O$2) -> -15156.296 | AA25: =AA24-1 -> 39 | AB25: =23128*AA25 -> 901992
A26: =EDATE(A25,1) -> 46419 | B26: =D26+H26+L26+P26+T26 -> 1042407.4 | K26: 19 | L26: =L25+$K$5 -> 153370.07 | M26: =IPMT($K$3/12,K26,$K$4,$K$2) -> -2590.6425 | N26: =IPMT($K$3/12,K26,$K$4,$K$2) -> -2590.6425 | O26: 19 | P26: =P25+$O$5 -> 886326.18 | Q26: =PPMT($O$3/12,O26,$O$4,$O$2) -> -15202.343 | R26: =IPMT($O$3/12,O26,$O$4,$O$2) -> -14971.332 | S26: 19 | T26: =T25+$S$5 -> 2711.1441 | U26: =PPMT($S$3/12,S26,$S$4,$S$2) -> -1488.0577 | V26: =IPMT($S$3/12,S26,$S$4,$S$2) -> -29.934758 | W26: 19 | X26: =X25+$O$5 -> 1064455.1 | Y26: =PPMT($O$3/12,W26,$O$4,$O$2) -> -15202.343 | Z26: =IPMT($O$3/12,W26,$O$4,$O$2) -> -14971.332 | AA26: =AA25-1 -> 38 | AB26: =23128*AA26 -> 878864
A27: =EDATE(A26,1) -> 46447 | B27: =D27+H27+L27+P27+T27 -> 1005494.5 | K27: 20 | L27: =L26+$K$5 -> 148148.82 | M27: =IPMT($K$3/12,K27,$K$4,$K$2) -> -2558.2421 | N27: =IPMT($K$3/12,K27,$K$4,$K$2) -> -2558.2421 | O27: 20 | P27: =P26+$O$5 -> 856152.5 | Q27: =PPMT($O$3/12,O27,$O$4,$O$2) -> -15389.585 | R27: =IPMT($O$3/12,O27,$O$4,$O$2) -> -14784.09 | S27: 20 | T27: =T26+$S$5 -> 1193.1517 | U27: =PPMT($S$3/12,S27,$S$4,$S$2) -> -1495.4855 | V27: =IPMT($S$3/12,S27,$S$4,$S$2) -> -22.50687 | W27: 20 | X27: =X26+$O$5 -> 1034281.4 | Y27: =PPMT($O$3/12,W27,$O$4,$O$2) -> -15389.585 | Z27: =IPMT($O$3/12,W27,$O$4,$O$2) -> -14784.09 | AA27: =AA26-1 -> 37 | AB27: =23128*AA27 -> 855736
A28: =EDATE(A27,1) -> 46478 | B28: =D28+H28+L28+P28+T28 -> 968581.54 | K28: 21 | L28: =L27+$K$5 -> 142927.56 | M28: =IPMT($K$3/12,K28,$K$4,$K$2) -> -2525.4426 | N28: =IPMT($K$3/12,K28,$K$4,$K$2) -> -2525.4426 | O28: 21 | P28: =P27+$O$5 -> 825978.83 | Q28: =PPMT($O$3/12,O28,$O$4,$O$2) -> -15579.134 | R28: =IPMT($O$3/12,O28,$O$4,$O$2) -> -14594.541 | S28: 21 | T28: =T27+$S$5 -> -324.84068 | U28: =PPMT($S$3/12,S28,$S$4,$S$2) -> -1502.9505 | V28: =IPMT($S$3/12,S28,$S$4,$S$2) -> -15.041905 | W28: 21 | X28: =X27+$O$5 -> 1004107.8 | Y28: =PPMT($O$3/12,W28,$O$4,$O$2) -> -15579.134 | Z28: =IPMT($O$3/12,W28,$O$4,$O$2) -> -14594.541 | AA28: =AA27-1 -> 36 | AB28: =23128*AA28 -> 832608
A29: =EDATE(A28,1) -> 46508 | B29: =D29+H29+L29+P29+T29 -> 931668.62 | K29: 22 | L29: =L28+$K$5 -> 137706.3 | M29: =IPMT($K$3/12,K29,$K$4,$K$2) -> -2492.2391 | N29: =IPMT($K$3/12,K29,$K$4,$K$2) -> -2492.2391 | O29: 22 | P29: =P28+$O$5 -> 795805.15 | Q29: =PPMT($O$3/12,O29,$O$4,$O$2) -> -15771.017 | R29: =IPMT($O$3/12,O29,$O$4,$O$2) -> -14402.658 | S29: 22 | T29: =T28+$S$5 -> -1842.8331 | U29: =PPMT($S$3/12,S29,$S$4,$S$2) -> -1510.4527 | V29: =IPMT($S$3/12,S29,$S$4,$S$2) -> -7.5396766 | W29: 22 | X29: =X28+$O$5 -> 973934.09 | Y29: =PPMT($O$3/12,W29,$O$4,$O$2) -> -15771.017 | Z29: =IPMT($O$3/12,W29,$O$4,$O$2) -> -14402.658 | AA29: =AA28-1 -> 35 | AB29: =23128*AA29 -> 809480
A30: =EDATE(A29,1) -> 46539 | B30: =D30+H30+L30+P30+T30 -> 898116.52 | K30: 23 | L30: =L29+$K$5 -> 132485.04 | M30: =IPMT($K$3/12,K30,$K$4,$K$2) -> -2458.6267 | N30: =IPMT($K$3/12,K30,$K$4,$K$2) -> -2458.6267 | O30: 23 | P30: =P29+$O$5 -> 765631.48 | Q30: =PPMT($O$3/12,O30,$O$4,$O$2) -> -15965.263 | R30: =IPMT($O$3/12,O30,$O$4,$O$2) -> -14208.412 | W30: 23 | X30: =X29+$O$5 -> 943760.42 | Y30: =PPMT($O$3/12,W30,$O$4,$O$2) -> -15965.263 | Z30: =IPMT($O$3/12,W30,$O$4,$O$2) -> -14208.412 | AA30: =AA29-1 -> 34 | AB30: =23128*AA30 -> 786352
A31: =EDATE(A30,1) -> 46569 | B31: =D31+H31+L31+P31+T31 -> 862721.58 | K31: 24 | L31: =L30+$K$5 -> 127263.78 | M31: =IPMT($K$3/12,K31,$K$4,$K$2) -> -2424.6002 | N31: =IPMT($K$3/12,K31,$K$4,$K$2) -> -2424.6002 | O31: 24 | P31: =P30+$O$5 -> 735457.8 | Q31: =PPMT($O$3/12,O31,$O$4,$O$2) -> -16161.902 | R31: =IPMT($O$3/12,O31,$O$4,$O$2) -> -14011.773 | W31: 24 | X31: =X30+$O$5 -> 913586.74 | Y31: =PPMT($O$3/12,W31,$O$4,$O$2) -> -16161.902 | Z31: =IPMT($O$3/12,W31,$O$4,$O$2) -> -14011.773 | AA31: =AA30-1 -> 33 | AB31: =23128*AA31 -> 763224
A32: =EDATE(A31,1) -> 46600 | B32: =D32+H32+L32+P32+T32 -> 827326.65 | K32: 25 | L32: =L31+$K$5 -> 122042.52 | M32: =IPMT($K$3/12,K32,$K$4,$K$2) -> -2390.1547 | N32: =IPMT($K$3/12,K32,$K$4,$K$2) -> -2390.1547 | O32: 25 | P32: =P31+$O$5 -> 705284.13 | Q32: =PPMT($O$3/12,O32,$O$4,$O$2) -> -16360.963 | R32: =IPMT($O$3/12,O32,$O$4,$O$2) -> -13812.712 | W32: 25 | X32: =X31+$O$5 -> 883413.07 | Y32: =PPMT($O$3/12,W32,$O$4,$O$2) -> -16360.963 | Z32: =IPMT($O$3/12,W32,$O$4,$O$2) -> -13812.712 | AA32: =AA31-1 -> 32 | AB32: =23128*AA32 -> 740096
A33: =EDATE(A32,1) -> 46631 | B33: =D33+H33+L33+P33+T33 -> 791931.71 | K33: 26 | L33: =L32+$K$5 -> 116821.26 | M33: =IPMT($K$3/12,K33,$K$4,$K$2) -> -2355.285 | N33: =IPMT($K$3/12,K33,$K$4,$K$2) -> -2355.285 | O33: 26 | P33: =P32+$O$5 -> 675110.45 | Q33: =PPMT($O$3/12,O33,$O$4,$O$2) -> -16562.475 | R33: =IPMT($O$3/12,O33,$O$4,$O$2) -> -13611.2 | W33: 26 | X33: =X32+$O$5 -> 853239.39 | Y33: =PPMT($O$3/12,W33,$O$4,$O$2) -> -16562.475 | Z33: =IPMT($O$3/12,W33,$O$4,$O$2) -> -13611.2 | AA33: =AA32-1 -> 31 | AB33: =23128*AA33 -> 716968
A34: =EDATE(A33,1) -> 46661 | B34: =D34+H34+L34+P34+T34 -> 756536.78 | K34: 27 | L34: =L33+$K$5 -> 111600 | M34: =IPMT($K$3/12,K34,$K$4,$K$2) -> -2319.9857 | N34: =IPMT($K$3/12,K34,$K$4,$K$2) -> -2319.9857 | O34: 27 | P34: =P33+$O$5 -> 644936.78 | Q34: =PPMT($O$3/12,O34,$O$4,$O$2) -> -16766.47 | R34: =IPMT($O$3/12,O34,$O$4,$O$2) -> -13407.205 | W34: 27 | X34: =X33+$O$5 -> 823065.72 | Y34: =PPMT($O$3/12,W34,$O$4,$O$2) -> -16766.47 | Z34: =IPMT($O$3/12,W34,$O$4,$O$2) -> -13407.205 | AA34: =AA33-1 -> 30 | AB34: =23128*AA34 -> 693840
A35: =EDATE(A34,1) -> 46692 | B35: =D35+H35+L35+P35+T35 -> 721141.85 | K35: 28 | L35: =L34+$K$5 -> 106378.74 | M35: =IPMT($K$3/12,K35,$K$4,$K$2) -> -2284.2517 | N35: =IPMT($K$3/12,K35,$K$4,$K$2) -> -2284.2517 | O35: 28 | P35: =P34+$O$5 -> 614763.1 | Q35: =PPMT($O$3/12,O35,$O$4,$O$2) -> -16972.977 | R35: =IPMT($O$3/12,O35,$O$4,$O$2) -> -13200.698 | W35: 28 | X35: =X34+$O$5 -> 792892.04 | Y35: =PPMT($O$3/12,W35,$O$4,$O$2) -> -16972.977 | Z35: =IPMT($O$3/12,W35,$O$4,$O$2) -> -13200.698 | AA35: =AA34-1 -> 29 | AB35: =23128*AA35 -> 670712
A36: =EDATE(A35,1) -> 46722 | B36: =D36+H36+L36+P36+T36 -> 685746.91 | K36: 29 | L36: =L35+$K$5 -> 101157.48 | M36: =IPMT($K$3/12,K36,$K$4,$K$2) -> -2248.0775 | N36: =IPMT($K$3/12,K36,$K$4,$K$2) -> -2248.0775 | O36: 29 | P36: =P35+$O$5 -> 584589.43 | Q36: =PPMT($O$3/12,O36,$O$4,$O$2) -> -17182.027 | R36: =IPMT($O$3/12,O36,$O$4,$O$2) -> -12991.648 | W36: 29 | X36: =X35+$O$5 -> 762718.37 | Y36: =PPMT($O$3/12,W36,$O$4,$O$2) -> -17182.027 | Z36: =IPMT($O$3/12,W36,$O$4,$O$2) -> -12991.648 | AA36: =AA35-1 -> 28 | AB36: =23128*AA36 -> 647584
A37: =EDATE(A36,1) -> 46753 | B37: =D37+H37+L37+P37+T37 -> 650351.98 | K37: 30 | L37: =L36+$K$5 -> 95936.223 | M37: =IPMT($K$3/12,K37,$K$4,$K$2) -> -2211.4579 | N37: =IPMT($K$3/12,K37,$K$4,$K$2) -> -2211.4579 | O37: 30 | P37: =P36+$O$5 -> 554415.75 | Q37: =PPMT($O$3/12,O37,$O$4,$O$2) -> -17393.652 | R37: =IPMT($O$3/12,O37,$O$4,$O$2) -> -12780.022 | W37: 30 | X37: =X36+$O$5 -> 732544.69 | Y37: =PPMT($O$3/12,W37,$O$4,$O$2) -> -17393.652 | Z37: =IPMT($O$3/12,W37,$O$4,$O$2) -> -12780.022 | AA37: =AA36-1 -> 27 | AB37: =23128*AA37 -> 624456
A38: =EDATE(A37,1) -> 46784 | B38: =D38+H38+L38+P38+T38 -> 614957.04 | K38: 31 | L38: =L37+$K$5 -> 90714.963 | M38: =IPMT($K$3/12,K38,$K$4,$K$2) -> -2174.3871 | N38: =IPMT($K$3/12,K38,$K$4,$K$2) -> -2174.3871 | O38: 31 | P38: =P37+$O$5 -> 524242.08 | Q38: =PPMT($O$3/12,O38,$O$4,$O$2) -> -17607.884 | R38: =IPMT($O$3/12,O38,$O$4,$O$2) -> -12565.791 | W38: 31 | X38: =X37+$O$5 -> 702371.02 | Y38: =PPMT($O$3/12,W38,$O$4,$O$2) -> -17607.884 | Z38: =IPMT($O$3/12,W38,$O$4,$O$2) -> -12565.791 | AA38: =AA37-1 -> 26 | AB38: =23128*AA38 -> 601328
A39: =EDATE(A38,1) -> 46813 | B39: =D39+H39+L39+P39+T39 -> 579562.11 | K39: 32 | L39: =L38+$K$5 -> 85493.704 | M39: =IPMT($K$3/12,K39,$K$4,$K$2) -> -2136.8598 | N39: =IPMT($K$3/12,K39,$K$4,$K$2) -> -2136.8598 | O39: 32 | P39: =P38+$O$5 -> 494068.41 | Q39: =PPMT($O$3/12,O39,$O$4,$O$2) -> -17824.755 | R39: =IPMT($O$3/12,O39,$O$4,$O$2) -> -12348.92 | W39: 32 | X39: =X38+$O$5 -> 672197.34 | Y39: =PPMT($O$3/12,W39,$O$4,$O$2) -> -17824.755 | Z39: =IPMT($O$3/12,W39,$O$4,$O$2) -> -12348.92 | AA39: =AA38-1 -> 25 | AB39: =23128*AA39 -> 578200
A40: =EDATE(A39,1) -> 46844 | B40: =D40+H40+L40+P40+T40 -> 544167.18 | K40: 33 | L40: =L39+$K$5 -> 80272.445 | M40: =IPMT($K$3/12,K40,$K$4,$K$2) -> -2098.8703 | N40: =IPMT($K$3/12,K40,$K$4,$K$2) -> -2098.8703 | O40: 33 | P40: =P39+$O$5 -> 463894.73 | Q40: =PPMT($O$3/12,O40,$O$4,$O$2) -> -18044.296 | R40: =IPMT($O$3/12,O40,$O$4,$O$2) -> -12129.379 | W40: 33 | X40: =X39+$O$5 -> 642023.67 | Y40: =PPMT($O$3/12,W40,$O$4,$O$2) -> -18044.296 | Z40: =IPMT($O$3/12,W40,$O$4,$O$2) -> -12129.379 | AA40: =AA39-1 -> 24 | AB40: =23128*AA40 -> 555072
A41: =EDATE(A40,1) -> 46874 | B41: =D41+H41+L41+P41+T41 -> 508772.24 | K41: 34 | L41: =L40+$K$5 -> 75051.186 | M41: =IPMT($K$3/12,K41,$K$4,$K$2) -> -2060.4129 | N41: =IPMT($K$3/12,K41,$K$4,$K$2) -> -2060.4129 | O41: 34 | P41: =P40+$O$5 -> 433721.06 | Q41: =PPMT($O$3/12,O41,$O$4,$O$2) -> -18266.542 | R41: =IPMT($O$3/12,O41,$O$4,$O$2) -> -11907.133 | W41: 34 | X41: =X40+$O$5 -> 611849.99 | Y41: =PPMT($O$3/12,W41,$O$4,$O$2) -> -18266.542 | Z41: =IPMT($O$3/12,W41,$O$4,$O$2) -> -11907.133 | AA41: =AA40-1 -> 23 | AB41: =23128*AA41 -> 531944
... A64: =EDATE(A63,1) -> 47574 | B64: =D64+H64+L64+P64+T64 -> -305311.24 | K64: 57 | L64: =L63+$K$5 -> -45037.777 | M64: =IPMT($K$3/12,K64,$K$4,$K$2) -> -1032.5493 | N64: =IPMT($K$3/12,K64,$K$4,$K$2) -> -1032.5493 | O64: 57 | P64: =P63+$O$5 -> -260273.47 | Q64: =PPMT($O$3/12,O64,$O$4,$O$2) -> -24206.569 | R64: =IPMT($O$3/12,O64,$O$4,$O$2) -> -5967.1058 | W64: 57 | X64: =X63+$O$5 -> -82144.529 | Y64: =PPMT($O$3/12,W64,$O$4,$O$2) -> -24206.569 | Z64: =IPMT($O$3/12,W64,$O$4,$O$2) -> -5967.1058 | AA64: =AA63-1 -> 0 | AB64: =23128*AA64 -> 0
A65: =EDATE(A64,1) -> 47604 | B65: =D65+H65+L65+P65+T65 -> -340706.18 | K65: 58 | L65: =L64+$K$5 -> -50259.036 | M65: =IPMT($K$3/12,K65,$K$4,$K$2) -> -980.95834 | N65: =IPMT($K$3/12,K65,$K$4,$K$2) -> -980.95834 | O65: 58 | P65: =P64+$O$5 -> -290447.14 | Q65: =PPMT($O$3/12,O65,$O$4,$O$2) -> -24504.713 | R65: =IPMT($O$3/12,O65,$O$4,$O$2) -> -5668.9615 | W65: 58 | X65: =X64+$O$5 -> -112318.2 | Y65: =PPMT($O$3/12,W65,$O$4,$O$2) -> -24504.713 | Z65: =IPMT($O$3/12,W65,$O$4,$O$2) -> -5668.9615
A66: =EDATE(A65,1) -> 47635 | B66: =D66+H66+L66+P66+T66 -> -376101.11 | K66: 59 | L66: =L65+$K$5 -> -55480.296 | M66: =IPMT($K$3/12,K66,$K$4,$K$2) -> -928.73196 | N66: =IPMT($K$3/12,K66,$K$4,$K$2) -> -928.73196 | O66: 59 | P66: =P65+$O$5 -> -320620.82 | Q66: =PPMT($O$3/12,O66,$O$4,$O$2) -> -24806.53 | R66: =IPMT($O$3/12,O66,$O$4,$O$2) -> -5367.1452 | W66: 59 | X66: =X65+$O$5 -> -142491.88 | Y66: =PPMT($O$3/12,W66,$O$4,$O$2) -> -24806.53 | Z66: =IPMT($O$3/12,W66,$O$4,$O$2) -> -5367.1452
